Workbook
Name UPDATE: 'Data Sheet'!$E$1

Sheet Executive Summary
B2: ="NESTLÉ INDIA — FP&A ANALYSIS | "&'Data Sheet'!B1&" | Executive Summary" -> NESTLÉ INDIA — FP&A ANALYSIS | NESTLE INDIA LTD | Executive Summary
B5: A. Company Overview | J5: B. Project Objective
B6: • Nestlé India Ltd is a subsidiary of Nestlé S.A. (Switzerland), listed on the BSE/NSE. • Core business: packaged food and beverages (nutrition, confectionery, beverages, dairy). • Major categories include instant noodles, coffee, milk products, chocolates & confectionery, and infant nutrition. • Manufactures and distributes across India through multiple factories and a pan-India distribution network. | J6: This project demonstrates an end-to-end FP&A workflow: • Historical financial analysis and ratio trends • Assumption building (revenue growth, cost ratios, monthly seasonality) • Derived monthly actuals from quarterly reported data • Monthly budgeting and a 12-month forward forecast • Budget vs Actual and Budget vs Forecast variance analysis • Management dashboards
B11: C. Data Used | J11: D. Methodology Flow
B12: • Historical annual and quarterly financials sourced from Nestlé India's publicly reported financial statements (Data Sheet tab). • Monthly company-reported P&L data is NOT publicly available. • Monthly figures are therefore DERIVED from reported quarterly data using an explicit allocation assumption (31% / 33% / 36% of each quarter). • Derived monthly figures are modelled estimates and are NOT company-reported monthly results. • FY2023-24 was a 15-month transition year (Nestlé India changed its financial year-end from December to March) and is not directly comparable with normal 12-month years in trend analyses (see Historical FS / Ratio Analysis). | J12: Historical Financials → Historical Analysis → Assumptions → Quarterly-to-Monthly Allocation → Derived Monthly Actuals → Monthly Budget → 12-Month Forecast → Budget vs Actual / Budget vs Forecast → Variance Analysis → Management Dashboard
B17: E. Key Assumptions
B18: Assumption | G18: Base / Historical | I18: Budget | K18: Forecast | M18: Unit | P18: Type
B19: Revenue Growth, YoY | G19: =Assumptions!C11 -> 0.14617881 | I19: =Assumptions!D11 -> 0.1 | K19: =Assumptions!E11 -> 0.12 | M19: % p.a. | P19: Historical trend / Analyst assumption
B20: COGS / Material Cost % of Revenue | G20: =Assumptions!C15 -> 0.39361336 | I20: =Assumptions!D15 -> 0.388 | K20: =Assumptions!E15 -> 0.395 | M20: % of revenue | P20: Historical average / Analyst assumption
B21: Employee Cost % of Revenue | G21: =Assumptions!C16 -> 0.098399886 | I21: =Assumptions!D16 -> 0.102 | K21: =Assumptions!E16 -> 0.1 | M21: % of revenue | P21: Historical average / Analyst assumption
B22: Other Operating Expenses % of Revenue | G22: =Assumptions!C17 -> 0.27878996 | I22: =Assumptions!D17 -> 0.281 | K22: =Assumptions!E17 -> 0.285 | M22: % of revenue | P22: Historical average / Analyst assumption
B23: Depreciation — YoY growth (simplified driver) | I23: =Assumptions!D22 -> 0.104 | K23: =Assumptions!E22 -> 0.105 | M23: % YoY | P23: Analyst assumption
B24: Interest — YoY growth (simplified driver) | I24: =Assumptions!D23 -> 0.075 | K24: =Assumptions!E23 -> 0.085 | M24: % YoY | P24: Analyst assumption
B25: Effective Tax Rate | G25: =Assumptions!C25 -> 0.23104791 | I25: =Assumptions!D25 -> 0.232 | K25: =Assumptions!E25 -> 0.235 | M25: % of EBT | P25: Historical average / Analyst assumption
B26: Monthly Allocation (Seasonality) | G26: =TEXT(Assumptions!E4,"0%")&" / "&TEXT(Assumptions!E5,"0%")&" / "&TEXT(Assumptions!E6,"0%")&" (Month 1/2/3 of quarter)" -> 31% / 33% / 36% (Month 1/2/3 of quarter) | P26: Analyst assumption
B28: F. Key Financial Analysis (₹ Crore unless %)
B29: Metric | H29: Historical (Last 12-mo Actual) | K29: Budget (12-mo) | N29: Forecast (12-mo) | Q29: Budget vs Forecast Var %
B30: Revenue | H30: ='Monthly Actuals'!C26 -> 24436.62 | K30: ='Monthly Budget'!C23 -> 26372.602 | N30: ='Rolling Forecast'!C25 -> 26852.104 | Q30: =IFERROR((N30-K30)/ABS(K30),0) -> 0.018181818
B31: EBITDA | H31: ='Monthly Actuals'!C27 -> 5747.32 | K31: ='Monthly Budget'!C24 -> 6039.3259 | N31: ='Rolling Forecast'!C26 -> 5907.4629 | Q31: =IFERROR((N31-K31)/ABS(K31),0) -> -0.021834061
B32: EBITDA Margin % | H32: ='Monthly Actuals'!C27/'Monthly Actuals'!C26 -> 0.23519292 | K32: ='Monthly Budget'!C24/'Monthly Budget'!C23 -> 0.229 | N32: ='Rolling Forecast'!C26/'Rolling Forecast'!C25 -> 0.22 | Q32: =IFERROR((N32-K32)/ABS(K32),0) -> -0.03930131
B33: PAT | H33: ='Monthly Actuals'!C28 -> 3860.49 | K33: ='Monthly Budget'!C25 -> 4024.0193 | N33: ='Rolling Forecast'!C27 -> 3926.3308 | Q33: =IFERROR((N33-K33)/ABS(K33),0) -> -0.02427635
B34: COGS % of Revenue | H34: =Assumptions!C15 -> 0.39361336 | K34: =Assumptions!D15 -> 0.388 | N34: =Assumptions!E15 -> 0.395 | Q34: =IFERROR((N34-K34)/ABS(K34),0) -> 0.018041237
B35: Employee Cost % of Revenue | H35: =Assumptions!C16 -> 0.098399886 | K35: =Assumptions!D16 -> 0.102 | N35: =Assumptions!E16 -> 0.1 | Q35: =IFERROR((N35-K35)/ABS(K35),0) -> -0.019607843
B36: Other Opex % of Revenue | H36: =Assumptions!C17 -> 0.27878996 | K36: =Assumptions!D17 -> 0.281 | N36: =Assumptions!E17 -> 0.285 | Q36: =IFERROR((N36-K36)/ABS(K36),0) -> 0.014234875
B38: Historical = trailing 12-month Derived Monthly Actual (not company-reported monthly data — see Section C and Assumptions notes).
B40: G. Key Management Insights | J40: H. Limitations
B41: • Full-year Budget vs Forecast: Forecast revenue runs above Budget, but Forecast cost ratios (COGS/Employee/Other Opex) are all set slightly higher than Budget's — a modelling choice (Assumptions Forecast column), not a bottom-up cost forecast. See Variance Analysis Part 2. • EBITDA margin: driven mechanically by the three cost-ratio assumptions in Assumptions Section C; the Budget vs Forecast margin gap reflects those assumption settings, not an operational finding. • Employee cost represents one of three cost lines split from Total Opex using the Section E cost-mix assumption (~13% of Opex) — an analyst approximation, since the quarterly source does not report this split. • Depreciation and Interest are modelled on a simplified YoY-growth basis (Assumptions Section D), not a full fixed-asset/debt schedule — see Model Checks limitations. • The largest Budget vs Forecast variance driver is the compounding effect of the cost-ratio assumptions across 12 months — see Variance Analysis 'Driver / Explanation' column for the full line-by-line breakdown. • All figures above are model outputs from stated assumptions, not independently verified operational explanations. | J41: 1. Monthly actuals are DERIVED from quarterly reported data using an allocation assumption — they are not company-reported monthly actuals. 2. The monthly allocation percentages (31/33/36) and the cost-mix split (Section E) are modelled estimates, not reported splits. 3. Budget and Forecast results depend entirely on analyst assumptions (Assumptions sheet, Budget/Forecast columns) — they are not company guidance. 4. Depreciation/Interest use a simplified YoY-growth methodology; no monthly/quarterly PP&E or debt schedule is available. 5. This model is intended for portfolio / analytical demonstration only, and is NOT Nestlé India's internal planning model. 6. FY2023-24 was a 15-month transition year (calendar-year to April–March fiscal-year change) and is not directly comparable with normal 12-month periods for growth/trend metrics.
B50: Derived monthly figures are modelled estimates and are not company-reported monthly results. See Assumptions sheet and Model Checks sheet for full methodology, source labelling and integrity checks.

Sheet Budget VS Actual Dashboard
B2: ="Management Dashboard for Q1 (Apr-26 to Jun-26) -"&'Data Sheet'!B1 -> Management Dashboard for Q1 (Apr-26 to Jun-26) -NESTLE INDIA LTD
B3: Revenue | F3: EBITDA Margin | J3: EBITDA | N3: Opex
B4: =SUM('Budget VS Actuals'!C8:E8) -> 6378.18 | F4: ='Variance Analysis'!D10/'Variance Analysis'!D6 -> 0.241155 | J4: =SUM('Budget VS Actuals'!C32:E32) -> 1538.13 | N4: =SUM('Monthly Actuals'!AD10:AF10) -> 4840.05
B5: vs Budget | C5: =(SUM('Budget VS Actuals'!C8:E8)-SUM('Budget VS Actuals'!C7:E7))/SUM('Budget VS Actuals'!C7:E7) -> 0.10593414 | D5: =IF(C5>0,"Increased","Decreased") -> Increased | F5: vs Budget | G5: =F4-('Variance Analysis'!C10/'Variance Analysis'!C6) -> 0.012155 | H5: =IF(G5>0,"Increased","Decreased") -> Increased | J5: vs Budget | K5: =(SUM('Budget VS Actuals'!C32:E32)-SUM('Budget VS Actuals'!C31:E31))/SUM('Budget VS Actuals'!C31:E31) -> 0.16463558 | L5: =IF(K5>0,"Increased","Decreased") -> Increased | N5: vs Budget | O5: =(SUM('Monthly Actuals'!AD10:AF10)-SUM('Monthly Budget'!C8:E8))/SUM('Monthly Budget'!C8:E8) -> 0.088498822 | P5: =IF(O5>0,"Increased","Decreased") -> Increased
B6: Note: 'Actual' figures are Derived Monthly Actuals - not company-reported - allocated from Nestle India's reported quarterly results using the seasonality assumption on the Assumptions sheet (see Assumptions!B34:B38).
B7: Revenue & Cost structure - Q1 FY26-27 Budget to Actual (Rs Crore)
B8: Revenue
B9: Month | C9: Actual (Derived) | D9: Budget | E9: Variance | F9: Variance % | J9: Cost Line | K9: Budget | L9: Actual (Derived) | M9: Variance %
B10: 46113 | C10: ='Budget VS Actuals'!C8 -> 1977.2358 | D10: ='Budget VS Actuals'!C7 -> 2179.5365 | E10: =C10-D10 -> -202.30068 | F10: =E10/D10 -> -0.092818212 | J10: COGS | K10: ='Variance Analysis'!C7 -> 2237.6865 | L10: ='Variance Analysis'!D7 -> 2395.8248 | M10: ='Variance Analysis'!F7 -> 0.070670446
B11: 46143 | C11: ='Budget VS Actuals'!D8 -> 2104.7994 | D11: ='Budget VS Actuals'!D7 -> 1737.7906 | E11: =C11-D11 -> 367.00884 | F11: =E11/D11 -> 0.21119279 | J11: Employee Cost | K11: ='Variance Analysis'!C8 -> 588.25778 | L11: ='Variance Analysis'!D8 -> 638.8866 | M11: ='Variance Analysis'!F8 -> 0.086065707
B12: 46174 | C12: ='Budget VS Actuals'!E8 -> 2296.1448 | D12: ='Budget VS Actuals'!E7 -> 1849.9061 | E12: =C12-D12 -> 446.23872 | F12: =E12/D12 -> 0.24122237 | J12: Other Operating Expenses | K12: ='Variance Analysis'!C9 -> 1620.5925 | L12: ='Variance Analysis'!D9 -> 1805.3387 | M12: ='Variance Analysis'!F9 -> 0.11399913
J29: ="What this shows: all three cost lines ran hotter than budget in Q1 (COGS +"&TEXT('Variance Analysis'!F7,"0.0%")&", Employee +"&TEXT('Variance Analysis'!F8,"0.0%")&", Other Opex +"&TEXT('Variance Analysis'!F9,"0.0%")&"), in line with the cost-ratio assumptions on the Assumptions sheet, not a one-off spend spike in any single line." -> What this shows: all three cost lines ran hotter than budget in Q1 (COGS +7.1%, Employee +8.6%, Other Opex +11.4%), in line with the cost-ratio assumptions on the Assumptions sheet, not a one-off spend spike in any single line.
B31: EBITDA Bridge - Q1 FY26-27 Budget to Actual (Rs Crore)
B33: Category | C33: Type | D33: Net Impact (Rs Cr) | E33: Running Total | F33: Base | G33: Increase | H33: Decrease | I33: Total
B34: Q1 Budget EBITDA | C34: Total | D34: ='Variance Analysis'!C10 -> 1320.6964 | E34: =D34 -> 1320.6964 | F34: =0 -> 0 | G34: =IF(C34="Increase",MAX(D34,0),0) -> 0 | H34: =IF(C34="Decrease",MAX(-D34,0),0) -> 0 | I34: =IF(C34="Total",D34,0) -> 1320.6964
B35: Revenue Variance | C35: Increase | D35: ='Variance Analysis'!D6-'Variance Analysis'!C6 -> 610.94688 | E35: =IF(C35="Total",D35,E34+D35) -> 1931.6433 | F35: =IF(C35="Total",0,MIN(E34,E35)) -> 1320.6964 | G35: =IF(C35="Increase",MAX(D35,0),0) -> 610.94688 | H35: =IF(C35="Decrease",MAX(-D35,0),0) -> 0 | I35: =IF(C35="Total",D35,0) -> 0
B36: COGS Impact | C36: Decrease | D36: =-('Variance Analysis'!D7-'Variance Analysis'!C7) -> -158.1383 | E36: =IF(C36="Total",D36,E35+D36) -> 1773.505 | F36: =IF(C36="Total",0,MIN(E35,E36)) -> 1773.505 | G36: =IF(C36="Increase",MAX(D36,0),0) -> 0 | H36: =IF(C36="Decrease",MAX(-D36,0),0) -> 158.1383 | I36: =IF(C36="Total",D36,0) -> 0
B37: Employee Cost Impact | C37: Decrease | D37: =-('Variance Analysis'!D8-'Variance Analysis'!C8) -> -50.628822 | E37: =IF(C37="Total",D37,E36+D37) -> 1722.8761 | F37: =IF(C37="Total",0,MIN(E36,E37)) -> 1722.8761 | G37: =IF(C37="Increase",MAX(D37,0),0) -> 0 | H37: =IF(C37="Decrease",MAX(-D37,0),0) -> 50.628822 | I37: =IF(C37="Total",D37,0) -> 0
B38: Other Opex Impact | C38: Decrease | D38: =-('Variance Analysis'!D9-'Variance Analysis'!C9) -> -184.74614 | E38: =IF(C38="Total",D38,E37+D38) -> 1538.13 | F38: =IF(C38="Total",0,MIN(E37,E38)) -> 1538.13 | G38: =IF(C38="Increase",MAX(D38,0),0) -> 0 | H38: =IF(C38="Decrease",MAX(-D38,0),0) -> 184.74614 | I38: =IF(C38="Total",D38,0) -> 0
B39: Q1 Actual EBITDA | C39: Total | D39: ='Variance Analysis'!D10 -> 1538.13 | E39: =IF(C39="Total",D39,E38+D39) -> 1538.13 | F39: =IF(C39="Total",0,MIN(E38,E39)) -> 0 | G39: =IF(C39="Increase",MAX(D39,0),0) -> 0 | H39: =IF(C39="Decrease",MAX(-D39,0),0) -> 0 | I39: =IF(C39="Total",D39,0) -> 1538.13
B52: ="What this shows: EBITDA moved from Rs "&TEXT('Variance Analysis'!C10,"#,##0")&" Cr (budget) to Rs "&TEXT('Variance Analysis'!D10,"#,##0")&" Cr (actual), a "&TEXT('Variance Analysis'!F10,"+0.0%;-0.0%")&" beat. "&"Higher revenue added Rs "&TEXT('Variance Analysis'!D6-'Variance Analysis'!C6,"#,##0")&" Cr, which more than offset cost overruns "&"in COGS, employee cost and other opex (each ran ahead of budget by roughly "&TEXT('Variance Analysis'!F7,"0.0%")&"). "&"April alone missed budget on revenue; May and June both beat it - worth checking what changed after April." -> What this shows: EBITDA moved from Rs 1,321 Cr (budget) to Rs 1,538 Cr (actual), a +16.5% beat. Higher revenue added Rs 611 Cr, which more than offset cost overruns in COGS, employee cost and other opex (each ran ahead of budget by roughly 7.1%). April alone missed budget on revenue; May and June both beat it - worth checking what changed after April.
B56: EBITDA Margin Trend & PAT - Actual vs Budget (Q1 FY26-27)
B58: Month | C58: Budget Margin % | D58: Actual Margin % | J58: Month | K58: Budget | L58: Actual (Derived) | M58: Variance %
B59: =B10 -> 46113 | C59: ='Monthly Budget'!C13 -> 0.229 | D59: ='Monthly Actuals'!AD15 -> 0.241155 | J59: =B10 -> 46113 | K59: ='Budget VS Actuals'!C55 -> 340.94869 | L59: ='Budget VS Actuals'!C56 -> 302.2872 | M59: ='Budget VS Actuals'!C58 -> -0.11339386
B60: =B11 -> 46143 | C60: ='Monthly Budget'!D13 -> 0.229 | D60: ='Monthly Actuals'!AE15 -> 0.241155 | J60: =B11 -> 46143 | K60: ='Budget VS Actuals'!D55 -> 257.6172 | L60: ='Budget VS Actuals'!D56 -> 321.7896 | M60: ='Budget VS Actuals'!D58 -> 0.2490998
B61: =B12 -> 46174 | C61: ='Monthly Budget'!E13 -> 0.229 | D61: ='Monthly Actuals'!AF15 -> 0.241155 | J61: =B12 -> 46174 | K61: ='Budget VS Actuals'!E55 -> 272.74154 | L61: ='Budget VS Actuals'!E56 -> 351.0432 | M61: ='Budget VS Actuals'!E58 -> 0.28709105
B79: ="What this shows: actual EBITDA margin held near "&TEXT('Variance Analysis'!D10/'Variance Analysis'!D6,"0.0%")&" through Q1. April revenue was below budget, while stronger performance in May and June more than offset "&"the initial shortfall; EBITDA margin remained broadly stable because the derived monthly cost structure follows "&"the assumed quarterly allocation pattern, not because of an operational cost or revenue finding." -> What this shows: actual EBITDA margin held near 24.1% through Q1. April revenue was below budget, while stronger performance in May and June more than offset the initial shortfall; EBITDA margin remained broadly stable because the derived monthly cost structure follows the assumed quarterly allocation pattern, not because of an operational cost or revenue finding.
B80: ="What this shows: PAT beat budget by Rs "&TEXT('Variance Analysis'!E14,"#,##0")&" Cr for the quarter ("&TEXT('Variance Analysis'!F14,"+0.0%;-0.0%")&"), proportionally less than the "&TEXT('Variance Analysis'!F10,"0.0%")&" EBITDA beat, because the higher pre-tax profit also pushed the tax charge up "&TEXT('Variance Analysis'!F13,"0.0%")&" - normal flow-through, not a new issue." -> What this shows: PAT beat budget by Rs 104 Cr for the quarter (+11.9%), proportionally less than the 16.5% EBITDA beat, because the higher pre-tax profit also pushed the tax charge up 32.7% - normal flow-through, not a new issue.

Sheet Budget VS Forecast Dashboard
B2: ="Forecast Dashboard for FY27 (Jul-26 to Jun-27) - "&'Data Sheet'!B1 -> Forecast Dashboard for FY27 (Jul-26 to Jun-27) - NESTLE INDIA LTD
B3: Revenue | F3: EBITDA Margin | J3: EBITDA | N3: PAT
B4: ='Variance Analysis'!D18 -> 26852.104 | F4: ='Variance Analysis'!D22/'Variance Analysis'!D18 -> 0.22 | J4: ='Variance Analysis'!D22 -> 5907.4629 | N4: ='Variance Analysis'!D26 -> 3926.3308
B5: vs Budget | C5: ='Variance Analysis'!F18 -> 0.018181818 | D5: =IF(C5>0,"Increased","Decreased") -> Increased | F5: vs Budget | G5: =F4-('Variance Analysis'!C22/'Variance Analysis'!C18) -> -0.009 | H5: =IF(G5>0,"Increased","Decreased") -> Decreased | J5: vs Budget | K5: ='Variance Analysis'!F22 -> -0.021834061 | L5: =IF(K5>0,"Increased","Decreased") -> Decreased | N5: vs Budget | O5: ='Variance Analysis'!F26 -> -0.02427635 | P5: =IF(O5>0,"Increased","Decreased") -> Decreased
B6: Note: 'Forecast' is a model-generated projection built on its own growth/cost assumptions (Assumptions!E11, E15:E17) - a separate scenario from Budget, not a company estimate or guidance (see Assumptions!B36:B37).
B7: Revenue - FY Jul26-Jun27 Budget to Forecast (Rs Crore)
B8: Revenue
B9: Month | C9: Forecast | D9: Budget | E9: Variance | F9: Variance %
B10: ='Budget VS Forecast'!C4 -> 46204 | C10: ='Budget VS Forecast'!C8 -> 2054.7717 | D10: ='Budget VS Forecast'!C7 -> 2018.0794 | E10: =C10-D10 -> 36.692352 | F10: =IFERROR(E10/ABS(D10),0) -> 0.018181818
B11: ='Budget VS Forecast'!D4 -> 46235 | C11: ='Budget VS Forecast'!D8 -> 1959.4614 | D11: ='Budget VS Forecast'!D7 -> 1924.471 | E11: =C11-D11 -> 34.990382 | F11: =IFERROR(E11/ABS(D11),0) -> 0.018181818
B12: ='Budget VS Forecast'!E4 -> 46266 | C12: ='Budget VS Forecast'!E8 -> 2085.8783 | D12: ='Budget VS Forecast'!E7 -> 2048.6304 | E12: =C12-D12 -> 37.247826 | F12: =IFERROR(E12/ABS(D12),0) -> 0.018181818
B13: ='Budget VS Forecast'!F4 -> 46296 | C13: ='Budget VS Forecast'!F8 -> 2275.5036 | D13: ='Budget VS Forecast'!F7 -> 2234.8696 | E13: =C13-D13 -> 40.633992 | F13: =IFERROR(E13/ABS(D13),0) -> 0.018181818
B14: ='Budget VS Forecast'!G4 -> 46327 | C14: ='Budget VS Forecast'!G8 -> 1967.5963 | D14: ='Budget VS Forecast'!G7 -> 1932.4606 | E14: =C14-D14 -> 35.135648 | F14: =IFERROR(E14/ABS(D14),0) -> 0.018181818
B15: ='Budget VS Forecast'!H4 -> 46357 | C15: ='Budget VS Forecast'!H8 -> 2094.538 | D15: ='Budget VS Forecast'!H7 -> 2057.1355 | E15: =C15-D15 -> 37.402464 | F15: =IFERROR(E15/ABS(D15),0) -> 0.018181818
B16: ='Budget VS Forecast'!I4 -> 46388 | C16: ='Budget VS Forecast'!I8 -> 2284.9505 | D16: ='Budget VS Forecast'!I7 -> 2244.1478 | E16: =C16-D16 -> 40.802688 | F16: =IFERROR(E16/ABS(D16),0) -> 0.018181818
B17: ='Budget VS Forecast'!J4 -> 46419 | C17: ='Budget VS Forecast'!J8 -> 2342.8327 | D17: ='Budget VS Forecast'!J7 -> 2300.9964 | E17: =C17-D17 -> 41.836298 | F17: =IFERROR(E17/ABS(D17),0) -> 0.018181818
B18: ='Budget VS Forecast'!K4 -> 46447 | C18: ='Budget VS Forecast'!K8 -> 2493.9832 | D18: ='Budget VS Forecast'!K7 -> 2449.4478 | E18: =C18-D18 -> 44.535414 | F18: =IFERROR(E18/ABS(D18),0) -> 0.018181818
B19: ='Budget VS Forecast'!L4 -> 46478 | C19: ='Budget VS Forecast'!L8 -> 2720.7089 | D19: ='Budget VS Forecast'!L7 -> 2672.1248 | E19: =C19-D19 -> 48.584088 | F19: =IFERROR(E19/ABS(D19),0) -> 0.018181818
B20: ='Budget VS Forecast'!M4 -> 46508 | C20: ='Budget VS Forecast'!M8 -> 2214.5041 | D20: ='Budget VS Forecast'!M7 -> 2174.9594 | E20: =C20-D20 -> 39.544716 | F20: =IFERROR(E20/ABS(D20),0) -> 0.018181818
B21: ='Budget VS Forecast'!N4 -> 46539 | C21: ='Budget VS Forecast'!N8 -> 2357.3753 | D21: ='Budget VS Forecast'!N7 -> 2315.2793 | E21: =C21-D21 -> 42.095988 | F21: =IFERROR(E21/ABS(D21),0) -> 0.018181818
B23: Revenue exceeded budget — driven by the higher revenue growth assumption used in the Forecast (12% p.a.) versus the Budget (10% p.a.), a modelling choice on the Assumptions sheet rather than a confirmed operational trend. Variance between the Budget and the Forecast is approximately +1.82%.
B25: EBITDA Bridge - FY Jul26-Jun27 Budget to Forecast (Rs Crore)
B27: Category | C27: Type | D27: Net Impact (Rs Cr) | E27: Running Total | F27: Base | G27: Increase | H27: Decrease | I27: Total
B28: FY Budget EBITDA | C28: Total | D28: ='Variance Analysis'!C22 -> 6039.3259 | E28: =D28 -> 6039.3259 | F28: =0 -> 0 | G28: =IF(C28="Increase",MAX(D28,0),0) -> 0 | H28: =IF(C28="Decrease",MAX(-D28,0),0) -> 0 | I28: =IF(C28="Total",D28,0) -> 6039.3259
B29: Revenue Variance | C29: Increase | D29: ='Variance Analysis'!D18-'Variance Analysis'!C18 -> 479.50186 | E29: =IF(C29="Total",D29,E28+D29) -> 6518.8277 | F29: =IF(C29="Total",0,MIN(E28,E29)) -> 6039.3259 | G29: =IF(C29="Increase",MAX(D29,0),0) -> 479.50186 | H29: =IF(C29="Decrease",MAX(-D29,0),0) -> 0 | I29: =IF(C29="Total",D29,0) -> 0
B30: COGS Impact | C30: Decrease | D30: =-('Variance Analysis'!D19-'Variance Analysis'!C19) -> -374.01145 | E30: =IF(C30="Total",D30,E29+D30) -> 6144.8163 | F30: =IF(C30="Total",0,MIN(E29,E30)) -> 6144.8163 | G30: =IF(C30="Increase",MAX(D30,0),0) -> 0 | H30: =IF(C30="Decrease",MAX(-D30,0),0) -> 374.01145 | I30: =IF(C30="Total",D30,0) -> 0
B31: Employee Cost Impact | C31: Decrease | D31: =-('Variance Analysis'!D20-'Variance Analysis'!C20) -> 4.7950186 | E31: =IF(C31="Total",D31,E30+D31) -> 6149.6113 | F31: =IF(C31="Total",0,MIN(E30,E31)) -> 6144.8163 | G31: =IF(C31="Increase",MAX(D31,0),0) -> 0 | H31: =IF(C31="Decrease",MAX(-D31,0),0) -> 0 | I31: =IF(C31="Total",D31,0) -> 0
B32: Other Opex Impact | C32: Decrease | D32: =-('Variance Analysis'!D21-'Variance Analysis'!C21) -> -242.14844 | E32: =IF(C32="Total",D32,E31+D32) -> 5907.4629 | F32: =IF(C32="Total",0,MIN(E31,E32)) -> 5907.4629 | G32: =IF(C32="Increase",MAX(D32,0),0) -> 0 | H32: =IF(C32="Decrease",MAX(-D32,0),0) -> 242.14844 | I32: =IF(C32="Total",D32,0) -> 0
B33: FY Forecast EBITDA | C33: Total | D33: ='Variance Analysis'!D22 -> 5907.4629 | E33: =IF(C33="Total",D33,E32+D33) -> 5907.4629 | F33: =IF(C33="Total",0,MIN(E32,E33)) -> 0 | G33: =IF(C33="Increase",MAX(D33,0),0) -> 0 | H33: =IF(C33="Decrease",MAX(-D33,0),0) -> 0 | I33: =IF(C33="Total",D33,0) -> 5907.4629
B44: ="What this shows: full-year forecast EBITDA comes in at Rs "&TEXT('Variance Analysis'!D22,"#,##0")&" Cr versus a Rs "&TEXT('Variance Analysis'!C22,"#,##0")&" Cr budget, a "&TEXT('Variance Analysis'!F22,"+0.0%;-0.0%")&" shortfall. Forecast revenue is actually Rs "&TEXT('Variance Analysis'!D18-'Variance Analysis'!C18,"#,##0")&" Cr above budget, but COGS, employee cost and other opex are all forecast to run further ahead of budget still - "&"cost growth is outpacing revenue growth in this scenario, the opposite pattern from the Q1 actuals." -> What this shows: full-year forecast EBITDA comes in at Rs 5,907 Cr versus a Rs 6,039 Cr budget, a -2.2% shortfall. Forecast revenue is actually Rs 480 Cr above budget, but COGS, employee cost and other opex are all forecast to run further ahead of budget still - cost growth is outpacing revenue growth in this scenario, the opposite pattern from the Q1 actuals.
B46: Cost Structure - FY Budget vs Forecast (Rs Crore)
B48: Cost Line | C48: Budget | D48: Forecast | E48: Variance %
B49: COGS | C49: ='Variance Analysis'!C19 -> 10232.57 | D49: ='Variance Analysis'!D19 -> 10606.581 | E49: ='Variance Analysis'!F19 -> 0.036551078
B50: Employee Cost | C50: ='Variance Analysis'!C20 -> 2690.0054 | D50: ='Variance Analysis'!D20 -> 2685.2104 | E50: ='Variance Analysis'!F20 -> -0.0017825312
B51: Other Operating Expenses | C51: ='Variance Analysis'!C21 -> 7410.7012 | D51: ='Variance Analysis'!D21 -> 7652.8496 | E51: ='Variance Analysis'!F21 -> 0.03267551
B64: ="What this shows: every cost line is forecast to exceed budget by roughly "&TEXT('Variance Analysis'!F19,"0.0%")&" - all three cost-ratio assumptions (Assumptions!E15:E17) were set slightly higher than Budget's, so this gap "&"is a modelling choice, not a bottom-up cost forecast." -> What this shows: every cost line is forecast to exceed budget by roughly 3.7% - all three cost-ratio assumptions (Assumptions!E15:E17) were set slightly higher than Budget's, so this gap is a modelling choice, not a bottom-up cost forecast.
B66: EBITDA Margin Trend - Budget vs Forecast (FY Jul26-Jun27)
B68: Month | C68: Budget Margin % | D68: Forecast Margin %
B69: ='Budget VS Forecast'!C4 -> 46204 | C69: ='Monthly Budget'!F13 -> 0.229 | D69: ='Rolling Forecast'!D14 -> 0.22
B70: ='Budget VS Forecast'!D4 -> 46235 | C70: ='Monthly Budget'!G13 -> 0.229 | D70: ='Rolling Forecast'!E14 -> 0.22
B71: ='Budget VS Forecast'!E4 -> 46266 | C71: ='Monthly Budget'!H13 -> 0.229 | D71: ='Rolling Forecast'!F14 -> 0.22
B72: ='Budget VS Forecast'!F4 -> 46296 | C72: ='Monthly Budget'!I13 -> 0.229 | D72: ='Rolling Forecast'!G14 -> 0.22
B73: ='Budget VS Forecast'!G4 -> 46327 | C73: ='Monthly Budget'!J13 -> 0.229 | D73: ='Rolling Forecast'!H14 -> 0.22
B74: ='Budget VS Forecast'!H4 -> 46357 | C74: ='Monthly Budget'!K13 -> 0.229 | D74: ='Rolling Forecast'!I14 -> 0.22
B75: ='Budget VS Forecast'!I4 -> 46388 | C75: ='Monthly Budget'!L13 -> 0.229 | D75: ='Rolling Forecast'!J14 -> 0.22
B76: ='Budget VS Forecast'!J4 -> 46419 | C76: ='Monthly Budget'!M13 -> 0.229 | D76: ='Rolling Forecast'!K14 -> 0.22
B77: ='Budget VS Forecast'!K4 -> 46447 | C77: ='Monthly Budget'!N13 -> 0.229 | D77: ='Rolling Forecast'!L14 -> 0.22
B78: ='Budget VS Forecast'!L4 -> 46478 | C78: ='Monthly Budget'!O13 -> 0.229 | D78: ='Rolling Forecast'!M14 -> 0.22
B79: ='Budget VS Forecast'!M4 -> 46508 | C79: ='Monthly Budget'!P13 -> 0.229 | D79: ='Rolling Forecast'!N14 -> 0.22
B80: ='Budget VS Forecast'!N4 -> 46539 | C80: ='Monthly Budget'!Q13 -> 0.229 | D80: ='Rolling Forecast'!O14 -> 0.22
B83: What this shows: forecast margin sits below the flat 22.9% budget line in every single month, since the forecast cost-ratio assumptions are uniformly higher than budget's - confirm this margin gap is an intentional, conservative scenario before sharing it as 'the forecast.'
B85: PAT - Budget vs Forecast (FY Jul26-Jun27, Rs Crore)
B87: Month | C87: Budget | D87: Forecast | E87: Variance %
B88: ='Budget VS Forecast'!C4 -> 46204 | C88: ='Budget VS Forecast'!C55 -> 310.18495 | D88: ='Budget VS Forecast'!C56 -> 295.05072 | E88: ='Budget VS Forecast'!C58 -> -0.048790993
B89: ='Budget VS Forecast'!D4 -> 46235 | C89: ='Budget VS Forecast'!D55 -> 289.71825 | D89: ='Budget VS Forecast'!D56 -> 285.52263 | E89: ='Budget VS Forecast'!D58 -> -0.014481738
B90: ='Budget VS Forecast'!E4 -> 46266 | C90: ='Budget VS Forecast'!E55 -> 306.86974 | D90: ='Budget VS Forecast'!E56 -> 303.94344 | E90: ='Budget VS Forecast'!E58 -> -0.0095359641
B91: ='Budget VS Forecast'!F4 -> 46296 | C91: ='Budget VS Forecast'!F55 -> 351.13528 | D91: ='Budget VS Forecast'!F56 -> 331.57466 | E91: ='Budget VS Forecast'!F58 -> -0.055706776
B92: ='Budget VS Forecast'!G4 -> 46327 | C92: ='Budget VS Forecast'!G55 -> 293.01638 | D92: ='Budget VS Forecast'!G56 -> 288.70972 | E92: ='Budget VS Forecast'!G58 -> -0.014697676
B93: ='Budget VS Forecast'!H4 -> 46357 | C93: ='Budget VS Forecast'!H55 -> 310.42956 | D93: ='Budget VS Forecast'!H56 -> 307.33615 | E93: ='Budget VS Forecast'!H58 -> -0.0099649245
B94: ='Budget VS Forecast'!I4 -> 46388 | C94: ='Budget VS Forecast'!I55 -> 342.71862 | D94: ='Budget VS Forecast'!I56 -> 335.2758 | E94: ='Budget VS Forecast'!I58 -> -0.021716985
B95: ='Budget VS Forecast'!J4 -> 46419 | C95: ='Budget VS Forecast'!J55 -> 348.92519 | D95: ='Budget VS Forecast'!J56 -> 343.78874 | E95: ='Budget VS Forecast'!J58 -> -0.014720775
B96: ='Budget VS Forecast'!K4 -> 46447 | C96: ='Budget VS Forecast'!K55 -> 369.66177 | D96: ='Budget VS Forecast'!K56 -> 365.96866 | E96: ='Budget VS Forecast'!K58 -> -0.009990515
B97: ='Budget VS Forecast'!L4 -> 46478 | C97: ='Budget VS Forecast'!L55 -> 423.13439 | D97: ='Budget VS Forecast'!L56 -> 399.23853 | E97: ='Budget VS Forecast'!L58 -> -0.056473453
B98: ='Budget VS Forecast'!M4 -> 46508 | C98: ='Budget VS Forecast'!M55 -> 329.33398 | D98: ='Budget VS Forecast'!M56 -> 324.49334 | E98: ='Budget VS Forecast'!M58 -> -0.014698272
B99: ='Budget VS Forecast'!N4 -> 46539 | C99: ='Budget VS Forecast'!N55 -> 348.89118 | D99: ='Budget VS Forecast'!N56 -> 345.42839 | E99: ='Budget VS Forecast'!N58 -> -0.0099251303
B101: ="What this shows: forecast PAT for the year is Rs "&TEXT('Variance Analysis'!D26,"#,##0")&" Cr versus a Rs "&TEXT('Variance Analysis'!C26,"#,##0")&" Cr budget ("&TEXT('Variance Analysis'!F26,"+0.0%;-0.0%")&"), tracking the EBITDA shortfall almost unchanged - depreciation, interest and tax are all forecast "&"close to their budgeted ratios, so none of them offset the operating gap." -> What this shows: forecast PAT for the year is Rs 3,926 Cr versus a Rs 4,024 Cr budget (-2.4%), tracking the EBITDA shortfall almost unchanged - depreciation, interest and tax are all forecast close to their budgeted ratios, so none of them offset the operating gap.

Sheet  Model>

Sheet Monthly Actuals
B2: ="Derived Monthly Actuals -"&'Data Sheet'!B1 -> Derived Monthly Actuals -NESTLE INDIA LTD
B3: Derived Monthly Actual - NOT company-reported. Allocated from Nestlé India's reported quarterly results (Data Sheet) using the monthly seasonality assumption on the Assumptions sheet.
B5: Month | C5: 45292 | D5: 45323 | E5: 45352 | F5: 45383 | G5: 45413 | H5: 45444 | I5: 45474 | J5: 45505 | K5: 45536 | L5: 45566 | M5: 45597 | N5: 45627 | O5: 45658 | P5: 45689 | Q5: 45717 | R5: 45748 | S5: 45778 | T5: 45809 | U5: 45839 | V5: 45870 | W5: 45901 | X5: 45931 | Y5: 45962 | Z5: 45992 | AA5: 46023 | AB5: 46054 | AC5: 46082 | AD5: 46113 | AE5: 46143 | AF5: 46174
B6: Reported Quarter (source) | C6: Q4 FY23-24 | D6: Q4 FY23-24 | E6: Q4 FY23-24 | F6: Q1 FY24-25 | G6: Q1 FY24-25 | H6: Q1 FY24-25 | I6: Q2 FY24-25 | J6: Q2 FY24-25 | K6: Q2 FY24-25 | L6: Q3 FY24-25 | M6: Q3 FY24-25 | N6: Q3 FY24-25 | O6: Q4 FY24-25 | P6: Q4 FY24-25 | Q6: Q4 FY24-25 | R6: Q1 FY25-26 | S6: Q1 FY25-26 | T6: Q1 FY25-26 | U6: Q2 FY25-26 | V6: Q2 FY25-26 | W6: Q2 FY25-26 | X6: Q3 FY25-26 | Y6: Q3 FY25-26 | Z6: Q3 FY25-26 | AA6: Q4 FY25-26 | AB6: Q4 FY25-26 | AC6: Q4 FY25-26 | AD6: Q1 FY26-27 | AE6: Q1 FY26-27 | AF6: Q1 FY26-27
B8: Income Statement (Derived Monthly Actual )
B9: Revenue | C9: ='Data Sheet'!B42*Assumptions!$E$4 -> 1632.9529 | D9: ='Data Sheet'!B42*Assumptions!$E$5 -> 1738.3047 | E9: ='Data Sheet'!B42*Assumptions!$E$6 -> 1896.3324 | F9: ='Data Sheet'!C42*Assumptions!$E$4 -> 1492.3245 | G9: ='Data Sheet'!C42*Assumptions!$E$5 -> 1588.6035 | H9: ='Data Sheet'!C42*Assumptions!$E$6 -> 1733.022 | I9: ='Data Sheet'!D42*Assumptions!$E$4 -> 1582.24 | J9: ='Data Sheet'!D42*Assumptions!$E$5 -> 1684.32 | K9: ='Data Sheet'!D42*Assumptions!$E$6 -> 1837.44 | L9: ='Data Sheet'!E42*Assumptions!$E$4 -> 1481.7163 | M9: ='Data Sheet'!E42*Assumptions!$E$5 -> 1577.3109 | N9: ='Data Sheet'!E42*Assumptions!$E$6 -> 1720.7028 | O9: ='Data Sheet'!F42*Assumptions!$E$4 -> 1706.2028 | P9: ='Data Sheet'!F42*Assumptions!$E$5 -> 1816.2804 | Q9: ='Data Sheet'!F42*Assumptions!$E$6 -> 1981.3968 | R9: ='Data Sheet'!G42*Assumptions!$E$4 -> 1579.8096 | S9: ='Data Sheet'!G42*Assumptions!$E$5 -> 1681.7328 | T9: ='Data Sheet'!G42*Assumptions!$E$6 -> 1834.6176 | U9: ='Data Sheet'!H42*Assumptions!$E$4 -> 1749.5191 | V9: ='Data Sheet'!H42*Assumptions!$E$5 -> 1862.3913 | W9: ='Data Sheet'!H42*Assumptions!$E$6 -> 2031.6996 | X9: ='Data Sheet'!I42*Assumptions!$E$4 -> 1756.7824 | Y9: ='Data Sheet'!I42*Assumptions!$E$5 -> 1870.1232 | Z9: ='Data Sheet'!I42*Assumptions!$E$6 -> 2040.1344 | AA9: ='Data Sheet'!J42*Assumptions!$E$4 -> 2091.8149 | AB9: ='Data Sheet'!J42*Assumptions!$E$5 -> 2226.7707 | AC9: ='Data Sheet'!J42*Assumptions!$E$6 -> 2429.2044 | AD9: ='Data Sheet'!K42*Assumptions!$E$4 -> 1977.2358 | AE9: ='Data Sheet'!K42*Assumptions!$E$5 -> 2104.7994 | AF9: ='Data Sheet'!K42*Assumptions!$E$6 -> 2296.1448
B10: Total Operating Expenses | C10: ='Data Sheet'!B43*Assumptions!$E$4 -> 1214.4374 | D10: ='Data Sheet'!B43*Assumptions!$E$5 -> 1292.7882 | E10: ='Data Sheet'!B43*Assumptions!$E$6 -> 1410.3144 | F10: ='Data Sheet'!C43*Assumptions!$E$4 -> 1146.8822 | G10: ='Data Sheet'!C43*Assumptions!$E$5 -> 1220.8746 | H10: ='Data Sheet'!C43*Assumptions!$E$6 -> 1331.8632 | I10: ='Data Sheet'!D43*Assumptions!$E$4 -> 1220.2437 | J10: ='Data Sheet'!D43*Assumptions!$E$5 -> 1298.9691 | K10: ='Data Sheet'!D43*Assumptions!$E$6 -> 1417.0572 | L10: ='Data Sheet'!E43*Assumptions!$E$4 -> 1139.8824 | M10: ='Data Sheet'!E43*Assumptions!$E$5 -> 1213.4232 | N10: ='Data Sheet'!E43*Assumptions!$E$6 -> 1323.7344 | O10: ='Data Sheet'!F43*Assumptions!$E$4 -> 1275.8298 | P10: ='Data Sheet'!F43*Assumptions!$E$5 -> 1358.1414 | Q10: ='Data Sheet'!F43*Assumptions!$E$6 -> 1481.6088 | R10: ='Data Sheet'!G43*Assumptions!$E$4 -> 1238.7693 | S10: ='Data Sheet'!G43*Assumptions!$E$5 -> 1318.6899 | T10: ='Data Sheet'!G43*Assumptions!$E$6 -> 1438.5708 | U10: ='Data Sheet'!H43*Assumptions!$E$4 -> 1366.1607 | V10: ='Data Sheet'!H43*Assumptions!$E$5 -> 1454.3001 | W10: ='Data Sheet'!H43*Assumptions!$E$6 -> 1586.5092 | X10: ='Data Sheet'!I43*Assumptions!$E$4 -> 1384.4879 | Y10: ='Data Sheet'!I43*Assumptions!$E$5 -> 1473.8097 | Z10: ='Data Sheet'!I43*Assumptions!$E$6 -> 1607.7924 | AA10: ='Data Sheet'!J43*Assumptions!$E$4 -> 1542.6189 | AB10: ='Data Sheet'!J43*Assumptions!$E$5 -> 1642.1427 | AC10: ='Data Sheet'!J43*Assumptions!$E$6 -> 1791.4284 | AD10: ='Data Sheet'!K43*Assumptions!$E$4 -> 1500.4155 | AE10: ='Data Sheet'!K43*Assumptions!$E$5 -> 1597.2165 | AF10: ='Data Sheet'!K43*Assumptions!$E$6 -> 1742.418
B11: COGS / Material Cost | C11: =C10*Assumptions!$E$29 -> 601.14651 | D11: =D10*Assumptions!$E$29 -> 639.93016 | E11: =E10*Assumptions!$E$29 -> 698.10563 | F11: =F10*Assumptions!$E$29 -> 567.70669 | G11: =G10*Assumptions!$E$29 -> 604.33293 | H11: =H10*Assumptions!$E$29 -> 659.27228 | I11: =I10*Assumptions!$E$29 -> 604.02063 | J11: =J10*Assumptions!$E$29 -> 642.9897 | ... AF11: =AF10*Assumptions!$E$29 -> 862.49691
B12: Employee Cost | C12: =Assumptions!$E$30*C10 -> 160.30574 | D12: =Assumptions!$E$30*D10 -> 170.64804 | E12: =Assumptions!$E$30*E10 -> 186.1615 | F12: =Assumptions!$E$30*F10 -> 151.38845 | G12: =Assumptions!$E$30*G10 -> 161.15545 | H12: =Assumptions!$E$30*H10 -> 175.80594 | I12: =Assumptions!$E$30*I10 -> 161.07217 | J12: =Assumptions!$E$30*J10 -> 171.46392 | ... AF12: =Assumptions!$E$30*AF10 -> 229.99918
B13: Other Operating Expenses | C13: =C10*Assumptions!$E$31 -> 452.98515 | D13: =D10*Assumptions!$E$31 -> 482.21 | E13: =E10*Assumptions!$E$31 -> 526.04727 | F13: =F10*Assumptions!$E$31 -> 427.78706 | G13: =G10*Assumptions!$E$31 -> 455.38623 | H13: =H10*Assumptions!$E$31 -> 496.78497 | I13: =I10*Assumptions!$E$31 -> 455.1509 | J13: =J10*Assumptions!$E$31 -> 484.51547 | ... AF13: =AF10*Assumptions!$E$31 -> 649.92191
B14: EBITDA | C14: =C9-C10 -> 418.5155 | D14: =D9-D10 -> 445.5165 | E14: =E9-E10 -> 486.018 | F14: =F9-F10 -> 345.4423 | G14: =G9-G10 -> 367.7289 | H14: =H9-H10 -> 401.1588 | I14: =I9-I10 -> 361.9963 | J14: =J9-J10 -> 385.3509 | ... AF14: =AF9-AF10 -> 553.7268
B15: EBITDA Margin % | C15: =C14/C9 -> 0.25629368 | D15: =D14/D9 -> 0.25629368 | E15: =E14/E9 -> 0.25629368 | F15: =F14/F9 -> 0.23147935 | G15: =G14/G9 -> 0.23147935 | H15: =H14/H9 -> 0.23147935 | I15: =I14/I9 -> 0.22878723 | J15: =J14/J9 -> 0.22878723 | ... AF15: =AF14/AF9 -> 0.241155
B16: Other Income | C16: ='Data Sheet'!B44*Assumptions!$E$4 -> 11.4173 | D16: ='Data Sheet'!B44*Assumptions!$E$5 -> 12.1539 | E16: ='Data Sheet'!B44*Assumptions!$E$6 -> 13.2588 | F16: ='Data Sheet'!C44*Assumptions!$E$4 -> 12.1272 | G16: ='Data Sheet'!C44*Assumptions!$E$5 -> 12.9096 | H16: ='Data Sheet'!C44*Assumptions!$E$6 -> 14.0832 | I16: ='Data Sheet'!D44*Assumptions!$E$4 -> 92.2808 | J16: ='Data Sheet'!D44*Assumptions!$E$5 -> 98.2344 | K16: ='Data Sheet'!D44*Assumptions!$E$6 -> 107.1648 | L16: ='Data Sheet'!E44*Assumptions!$E$4 -> 1.3764 | M16: ='Data Sheet'!E44*Assumptions!$E$5 -> 1.4652 | N16: ='Data Sheet'!E44*Assumptions!$E$6 -> 1.5984 | O16: ='Data Sheet'!F44*Assumptions!$E$4 -> 2.821 | P16: ='Data Sheet'!F44*Assumptions!$E$5 -> 3.003 | Q16: ='Data Sheet'!F44*Assumptions!$E$6 -> 3.276 | R16: ='Data Sheet'!G44*Assumptions!$E$4 -> 1.2927 | S16: ='Data Sheet'!G44*Assumptions!$E$5 -> 1.3761 | T16: ='Data Sheet'!G44*Assumptions!$E$6 -> 1.5012 | U16: ='Data Sheet'!H44*Assumptions!$E$4 -> 0.5084 | V16: ='Data Sheet'!H44*Assumptions!$E$5 -> 0.5412 | W16: ='Data Sheet'!H44*Assumptions!$E$6 -> 0.5904 | X16: ='Data Sheet'!I44*Assumptions!$E$4 -> 52.6318 | Y16: ='Data Sheet'!I44*Assumptions!$E$5 -> 56.0274 | Z16: ='Data Sheet'!I44*Assumptions!$E$6 -> 61.1208 | AA16: ='Data Sheet'!J44*Assumptions!$E$4 -> -5.4932 | AB16: ='Data Sheet'!J44*Assumptions!$E$5 -> -5.8476 | AC16: ='Data Sheet'!J44*Assumptions!$E$6 -> -6.3792 | AD16: ='Data Sheet'!K44*Assumptions!$E$4 -> 5.0344 | AE16: ='Data Sheet'!K44*Assumptions!$E$5 -> 5.3592 | AF16: ='Data Sheet'!K44*Assumptions!$E$6 -> 5.8464
B17: Depreciation | C17: ='Data Sheet'!B45*Assumptions!$E$4 -> 34.131 | D17: ='Data Sheet'!B45*Assumptions!$E$5 -> 36.333 | E17: ='Data Sheet'!B45*Assumptions!$E$6 -> 39.636 | F17: ='Data Sheet'!C45*Assumptions!$E$4 -> 34.9401 | G17: ='Data Sheet'!C45*Assumptions!$E$5 -> 37.1943 | H17: ='Data Sheet'!C45*Assumptions!$E$6 -> 40.5756 | I17: ='Data Sheet'!D45*Assumptions!$E$4 -> 37.696 | J17: ='Data Sheet'!D45*Assumptions!$E$5 -> 40.128 | K17: ='Data Sheet'!D45*Assumptions!$E$6 -> 43.776 | L17: ='Data Sheet'!E45*Assumptions!$E$4 -> 46.5837 | M17: ='Data Sheet'!E45*Assumptions!$E$5 -> 49.5891 | N17: ='Data Sheet'!E45*Assumptions!$E$6 -> 54.0972 | O17: ='Data Sheet'!F45*Assumptions!$E$4 -> 48.1554 | P17: ='Data Sheet'!F45*Assumptions!$E$5 -> 51.2622 | Q17: ='Data Sheet'!F45*Assumptions!$E$6 -> 55.9224 | R17: ='Data Sheet'!G45*Assumptions!$E$4 -> 48.6514 | S17: ='Data Sheet'!G45*Assumptions!$E$5 -> 51.7902 | T17: ='Data Sheet'!G45*Assumptions!$E$6 -> 56.4984 | U17: ='Data Sheet'!H45*Assumptions!$E$4 -> 50.6385 | V17: ='Data Sheet'!H45*Assumptions!$E$5 -> 53.9055 | W17: ='Data Sheet'!H45*Assumptions!$E$6 -> 58.806 | X17: ='Data Sheet'!I45*Assumptions!$E$4 -> 54.0671 | Y17: ='Data Sheet'!I45*Assumptions!$E$5 -> 57.5553 | Z17: ='Data Sheet'!I45*Assumptions!$E$6 -> 62.7876 | AA17: ='Data Sheet'!J45*Assumptions!$E$4 -> 63.4043 | AB17: ='Data Sheet'!J45*Assumptions!$E$5 -> 67.4949 | AC17: ='Data Sheet'!J45*Assumptions!$E$6 -> 73.6308 | AD17: ='Data Sheet'!K45*Assumptions!$E$4 -> 58.218 | AE17: ='Data Sheet'!K45*Assumptions!$E$5 -> 61.974 | AF17: ='Data Sheet'!K45*Assumptions!$E$6 -> 67.608
B18: EBIT | C18: =C14-(C17)+C16 -> 395.8018 | D18: =D14-(D17)+D16 -> 421.3374 | E18: =E14-(E17)+E16 -> 459.6408 | F18: =F14-(F17)+F16 -> 322.6294 | G18: =G14-(G17)+G16 -> 343.4442 | H18: =H14-(H17)+H16 -> 374.6664 | I18: =I14-(I17)+I16 -> 416.5811 | J18: =J14-(J17)+J16 -> 443.4573 | ... AF18: =AF14-(AF17)+AF16 -> 491.9652
B19: Interest | C19: ='Data Sheet'!B46*Assumptions!$E$4 -> 8.122 | D19: ='Data Sheet'!B46*Assumptions!$E$5 -> 8.646 | E19: ='Data Sheet'!B46*Assumptions!$E$6 -> 9.432 | F19: ='Data Sheet'!C46*Assumptions!$E$4 -> 9.8208 | G19: ='Data Sheet'!C46*Assumptions!$E$5 -> 10.4544 | H19: ='Data Sheet'!C46*Assumptions!$E$6 -> 11.4048 | I19: ='Data Sheet'!D46*Assumptions!$E$4 -> 9.9882 | J19: ='Data Sheet'!D46*Assumptions!$E$5 -> 10.6326 | K19: ='Data Sheet'!D46*Assumptions!$E$6 -> 11.5992 | L19: ='Data Sheet'!E46*Assumptions!$E$4 -> 10.726 | M19: ='Data Sheet'!E46*Assumptions!$E$5 -> 11.418 | N19: ='Data Sheet'!E46*Assumptions!$E$6 -> 12.456 | O19: ='Data Sheet'!F46*Assumptions!$E$4 -> 11.625 | P19: ='Data Sheet'!F46*Assumptions!$E$5 -> 12.375 | Q19: ='Data Sheet'!F46*Assumptions!$E$6 -> 13.5 | R19: ='Data Sheet'!G46*Assumptions!$E$4 -> 14.5359 | S19: ='Data Sheet'!G46*Assumptions!$E$5 -> 15.4737 | T19: ='Data Sheet'!G46*Assumptions!$E$6 -> 16.8804 | U19: ='Data Sheet'!H46*Assumptions!$E$4 -> 14.3871 | V19: ='Data Sheet'!H46*Assumptions!$E$5 -> 15.3153 | W19: ='Data Sheet'!H46*Assumptions!$E$6 -> 16.7076 | X19: ='Data Sheet'!I46*Assumptions!$E$4 -> 8.7575 | Y19: ='Data Sheet'!I46*Assumptions!$E$5 -> 9.3225 | Z19: ='Data Sheet'!I46*Assumptions!$E$6 -> 10.17 | AA19: ='Data Sheet'!J46*Assumptions!$E$4 -> 11.3956 | AB19: ='Data Sheet'!J46*Assumptions!$E$5 -> 12.1308 | AC19: ='Data Sheet'!J46*Assumptions!$E$6 -> 13.2336 | AD19: ='Data Sheet'!K46*Assumptions!$E$4 -> 13.0758 | AE19: ='Data Sheet'!K46*Assumptions!$E$5 -> 13.9194 | AF19: ='Data Sheet'!K46*Assumptions!$E$6 -> 15.1848
B20: EBT | C20: =C18-C19 -> 387.6798 | D20: =D18-D19 -> 412.6914 | E20: =E18-E19 -> 450.2088 | F20: =F18-F19 -> 312.8086 | G20: =G18-G19 -> 332.9898 | H20: =H18-H19 -> 363.2616 | I20: =I18-I19 -> 406.5929 | J20: =J18-J19 -> 432.8247 | ... AF20: =AF18-AF19 -> 476.7804
B21: Tax | C21: ='Data Sheet'!B48*Assumptions!$E$4 -> 98.0871 | D21: ='Data Sheet'!B48*Assumptions!$E$5 -> 104.4153 | E21: ='Data Sheet'!B48*Assumptions!$E$6 -> 113.9076 | F21: ='Data Sheet'!C48*Assumptions!$E$4 -> 81.3626 | G21: ='Data Sheet'!C48*Assumptions!$E$5 -> 86.6118 | H21: ='Data Sheet'!C48*Assumptions!$E$6 -> 94.4856 | I21: ='Data Sheet'!D48*Assumptions!$E$4 -> 100.8213 | J21: ='Data Sheet'!D48*Assumptions!$E$5 -> 107.3259 | K21: ='Data Sheet'!D48*Assumptions!$E$6 -> 117.0828 | L21: ='Data Sheet'!E48*Assumptions!$E$4 -> 70.1003 | M21: ='Data Sheet'!E48*Assumptions!$E$5 -> 74.6229 | N21: ='Data Sheet'!E48*Assumptions!$E$6 -> 81.4068 | O21: ='Data Sheet'!F48*Assumptions!$E$4 -> 98.9365 | P21: ='Data Sheet'!F48*Assumptions!$E$5 -> 105.3195 | Q21: ='Data Sheet'!F48*Assumptions!$E$6 -> 114.894 | R21: ='Data Sheet'!G48*Assumptions!$E$4 -> 74.7844 | S21: ='Data Sheet'!G48*Assumptions!$E$5 -> 79.6092 | T21: ='Data Sheet'!G48*Assumptions!$E$6 -> 86.8464 | U21: ='Data Sheet'!H48*Assumptions!$E$4 -> 85.3492 | V21: ='Data Sheet'!H48*Assumptions!$E$5 -> 90.8556 | W21: ='Data Sheet'!H48*Assumptions!$E$6 -> 99.1152 | X21: ='Data Sheet'!I48*Assumptions!$E$4 -> 46.5031 | Y21: ='Data Sheet'!I48*Assumptions!$E$5 -> 49.5033 | Z21: ='Data Sheet'!I48*Assumptions!$E$6 -> 54.0036 | AA21: ='Data Sheet'!J48*Assumptions!$E$4 -> 123.5288 | AB21: ='Data Sheet'!J48*Assumptions!$E$5 -> 131.4984 | AC21: ='Data Sheet'!J48*Assumptions!$E$6 -> 143.4528 | AD21: ='Data Sheet'!K48*Assumptions!$E$4 -> 108.2737 | AE21: ='Data Sheet'!K48*Assumptions!$E$5 -> 115.2591 | AF21: ='Data Sheet'!K48*Assumptions!$E$6 -> 125.7372
B22: PAT | C22: =C20-C21 -> 289.5927 | D22: =D20-D21 -> 308.2761 | E22: =E20-E21 -> 336.3012 | F22: =F20-F21 -> 231.446 | G22: =G20-G21 -> 246.378 | H22: =H20-H21 -> 268.776 | I22: =I20-I21 -> 305.7716 | J22: =J20-J21 -> 325.4988 | ... AF22: =AF20-AF21 -> 351.0432
B23: PAT Margin % | C23: =C22/C9 -> 0.17734296 | D23: =D22/D9 -> 0.17734296 | E23: =E22/E9 -> 0.17734296 | F23: =F22/F9 -> 0.15509093 | G23: =G22/G9 -> 0.15509093 | H23: =H22/H9 -> 0.15509093 | I23: =I22/I9 -> 0.19325235 | J23: =J22/J9 -> 0.19325235 | ... AF23: =AF22/AF9 -> 0.15288374
B25: Last 12-Month Actuals
B26: Revenue (12-mo sum) | C26: =SUM(U9:AF9) -> 24436.62
B27: EBITDA (12-mo sum) | C27: =SUM(U14:AF14) -> 5747.32
B28: PAT (12-mo sum) | C28: =SUM(U22:AF22) -> 3860.49
B30: Model Checks — Quarterly Reconciliation (Derived Monthly Actuals must sum exactly to reported quarterly figures)
B31: Confirms SUM(Month 1 + Month 2 + Month 3) = Reported Quarter, for both Revenue and Total Operating Expenses. Any non-zero difference is flagged.
B33: Quarter | C33: Reported Revenue (Data Sheet) | D33: Sum of 3 Derived Months (Revenue) | E33: Difference | F33: Reported Total Opex (Data Sheet) | G33: Sum of 3 Derived Months (Opex) | H33: Difference | I33: Status
B34: Q4 FY23-24 | C34: ='Data Sheet'!B42 -> 5267.59 | D34: =SUM(C9:E9) -> 5267.59 | E34: =C34-D34 -> 0 | F34: ='Data Sheet'!B43 -> 3917.54 | G34: =SUM(C10:E10) -> 3917.54 | H34: =F34-G34 -> 0 | I34: =IF(AND(ABS(E34)<0.01,ABS(H34)<0.01),"OK","FLAG — CHECK") -> OK
B35: Q1 FY24-25 | C35: ='Data Sheet'!C42 -> 4813.95 | D35: =SUM(F9:H9) -> 4813.95 | E35: =C35-D35 -> 0 | F35: ='Data Sheet'!C43 -> 3699.62 | G35: =SUM(F10:H10) -> 3699.62 | H35: =F35-G35 -> 0 | I35: =IF(AND(ABS(E35)<0.01,ABS(H35)<0.01),"OK","FLAG — CHECK") -> OK
B36: Q2 FY24-25 | C36: ='Data Sheet'!D42 -> 5104 | D36: =SUM(I9:K9) -> 5104 | E36: =C36-D36 -> 0 | F36: ='Data Sheet'!D43 -> 3936.27 | G36: =SUM(I10:K10) -> 3936.27 | H36: =F36-G36 -> 0 | I36: =IF(AND(ABS(E36)<0.01,ABS(H36)<0.01),"OK","FLAG — CHECK") -> OK
B37: Q3 FY24-25 | C37: ='Data Sheet'!E42 -> 4779.73 | D37: =SUM(L9:N9) -> 4779.73 | E37: =C37-D37 -> 0 | F37: ='Data Sheet'!E43 -> 3677.04 | G37: =SUM(L10:N10) -> 3677.04 | H37: =F37-G37 -> 0 | I37: =IF(AND(ABS(E37)<0.01,ABS(H37)<0.01),"OK","FLAG — CHECK") -> OK
B38: Q4 FY24-25 | C38: ='Data Sheet'!F42 -> 5503.88 | D38: =SUM(O9:Q9) -> 5503.88 | E38: =C38-D38 -> 0 | F38: ='Data Sheet'!F43 -> 4115.58 | G38: =SUM(O10:Q10) -> 4115.58 | H38: =F38-G38 -> 0 | I38: =IF(AND(ABS(E38)<0.01,ABS(H38)<0.01),"OK","FLAG — CHECK") -> OK
B39: Q1 FY25-26 | C39: ='Data Sheet'!G42 -> 5096.16 | D39: =SUM(R9:T9) -> 5096.16 | E39: =C39-D39 -> 0 | F39: ='Data Sheet'!G43 -> 3996.03 | G39: =SUM(R10:T10) -> 3996.03 | H39: =F39-G39 -> 0 | I39: =IF(AND(ABS(E39)<0.01,ABS(H39)<0.01),"OK","FLAG — CHECK") -> OK
B40: Q2 FY25-26 | C40: ='Data Sheet'!H42 -> 5643.61 | D40: =SUM(U9:W9) -> 5643.61 | E40: =C40-D40 -> 0 | F40: ='Data Sheet'!H43 -> 4406.97 | G40: =SUM(U10:W10) -> 4406.97 | H40: =F40-G40 -> 0 | I40: =IF(AND(ABS(E40)<0.01,ABS(H40)<0.01),"OK","FLAG — CHECK") -> OK
B41: Q3 FY25-26 | C41: ='Data Sheet'!I42 -> 5667.04 | D41: =SUM(X9:Z9) -> 5667.04 | E41: =C41-D41 -> 0 | F41: ='Data Sheet'!I43 -> 4466.09 | G41: =SUM(X10:Z10) -> 4466.09 | H41: =F41-G41 -> 0 | I41: =IF(AND(ABS(E41)<0.01,ABS(H41)<0.01),"OK","FLAG — CHECK") -> OK
B42: Q4 FY25-26 | C42: ='Data Sheet'!J42 -> 6747.79 | D42: =SUM(AA9:AC9) -> 6747.79 | E42: =C42-D42 -> 0 | F42: ='Data Sheet'!J43 -> 4976.19 | G42: =SUM(AA10:AC10) -> 4976.19 | H42: =F42-G42 -> 0 | I42: =IF(AND(ABS(E42)<0.01,ABS(H42)<0.01),"OK","FLAG — CHECK") -> OK
B43: Q1 FY26-27 | C43: ='Data Sheet'!K42 -> 6378.18 | D43: =SUM(AD9:AF9) -> 6378.18 | E43: =C43-D43 -> 0 | F43: ='Data Sheet'!K43 -> 4840.05 | G43: =SUM(AD10:AF10) -> 4840.05 | H43: =F43-G43 -> 0 | I43: =IF(AND(ABS(E43)<0.01,ABS(H43)<0.01),"OK","FLAG — CHECK") -> OK
B45: Overall Reconciliation Status | C45: =IF(COUNTIF(I34:I43,"OK")=COUNTA(I34:I43),"ALL QUARTERS RECONCILE","REVIEW FLAGGED QUARTERS") -> ALL QUARTERS RECONCILE

Sheet Monthly Budget
B2: ="Monthly Budget -"&'Data Sheet'!B1 -> Monthly Budget -NESTLE INDIA LTD
B4: Month | C4: 46113 | D4: 46143 | E4: 46174 | F4: 46204 | G4: 46235 | H4: 46266 | I4: 46296 | J4: 46327 | K4: 46357 | L4: 46388 | M4: 46419 | N4: 46447 | O4: 46478 | P4: 46508 | Q4: 46539
B6: Monthly Budget (₹ Crore)
B7: Revenue Budget | C7: ='Monthly Actuals'!Q$9*(1+Assumptions!$D$11) -> 2179.5365 | D7: ='Monthly Actuals'!R$9*(1+Assumptions!$D$11) -> 1737.7906 | E7: ='Monthly Actuals'!S$9*(1+Assumptions!$D$11) -> 1849.9061 | F7: ='Monthly Actuals'!T$9*(1+Assumptions!$D$11) -> 2018.0794 | G7: ='Monthly Actuals'!U$9*(1+Assumptions!$D$11) -> 1924.471 | H7: ='Monthly Actuals'!V$9*(1+Assumptions!$D$11) -> 2048.6304 | I7: ='Monthly Actuals'!W$9*(1+Assumptions!$D$11) -> 2234.8696 | J7: ='Monthly Actuals'!X$9*(1+Assumptions!$D$11) -> 1932.4606 | ... Q7: ='Monthly Actuals'!AE$9*(1+Assumptions!$D$11) -> 2315.2793
B8: Total Operating Expenses Budget | C8: =C9+C10+C11 -> 1680.4226 | D8: =D9+D10+D11 -> 1339.8365 | E8: =E9+E10+E11 -> 1426.2776 | F8: =F9+F10+F11 -> 1555.9392 | G8: =G9+G10+G11 -> 1483.7671 | H8: =H9+H10+H11 -> 1579.4941 | I8: =I9+I10+I11 -> 1723.0844 | J8: =J9+J10+J11 -> 1489.9272 | ... Q8: =Q9+Q10+Q11 -> 1785.0804
B9: COGS Budget | C9: =C7*Assumptions!$D$15 -> 845.66015 | D9: =D7*Assumptions!$D$15 -> 674.26274 | E9: =E7*Assumptions!$D$15 -> 717.76356 | F9: =F7*Assumptions!$D$15 -> 783.01479 | G9: =G7*Assumptions!$D$15 -> 746.69475 | H9: =H7*Assumptions!$D$15 -> 794.86861 | I9: =I7*Assumptions!$D$15 -> 867.12939 | J9: =J7*Assumptions!$D$15 -> 749.79473 | ... Q9: =Q7*Assumptions!$D$15 -> 898.32838
B10: Employee Cost Budget | C10: =C7*Assumptions!$D$16 -> 222.31272 | D10: =D7*Assumptions!$D$16 -> 177.25464 | E10: =E7*Assumptions!$D$16 -> 188.69042 | F10: =F7*Assumptions!$D$16 -> 205.84409 | G10: =G7*Assumptions!$D$16 -> 196.29604 | H10: =H7*Assumptions!$D$16 -> 208.9603 | I10: =I7*Assumptions!$D$16 -> 227.9567 | J10: =J7*Assumptions!$D$16 -> 197.11099 | ... Q10: =Q7*Assumptions!$D$16 -> 236.15849
B11: Other Opex Budget | C11: =C7*Assumptions!$D$17 -> 612.44975 | D11: =D7*Assumptions!$D$17 -> 488.31915 | E11: =E7*Assumptions!$D$17 -> 519.82361 | F11: =F7*Assumptions!$D$17 -> 567.0803 | G11: =G7*Assumptions!$D$17 -> 540.77635 | H11: =H7*Assumptions!$D$17 -> 575.66515 | I11: =I7*Assumptions!$D$17 -> 627.99835 | J11: =J7*Assumptions!$D$17 -> 543.02144 | ... Q11: =Q7*Assumptions!$D$17 -> 650.59349
B12: EBITDA Budget | C12: =C7-C8 -> 499.11385 | D12: =D7-D8 -> 397.95404 | E12: =E7-E8 -> 423.62849 | F12: =F7-F8 -> 462.14017 | G12: =G7-G8 -> 440.70386 | H12: =H7-H8 -> 469.13637 | I12: =I7-I8 -> 511.78513 | J12: =J7-J8 -> 442.53349 | ... Q12: =Q7-Q8 -> 530.19897
B13: EBITDA Margin % | C13: =C12/C7 -> 0.229 | D13: =D12/D7 -> 0.229 | E13: =E12/E7 -> 0.229 | F13: =F12/F7 -> 0.229 | G13: =G12/G7 -> 0.229 | H13: =H12/H7 -> 0.229 | I13: =I12/I7 -> 0.229 | J13: =J12/J7 -> 0.229 | ... Q13: =Q12/Q7 -> 0.229
B14: Other Income Budget | C14: =C7*Assumptions!$D$24 -> 14.166987 | D14: =D7*Assumptions!$D$24 -> 11.295639 | E14: =E7*Assumptions!$D$24 -> 12.02439 | F14: =F7*Assumptions!$D$24 -> 13.117516 | G14: =G7*Assumptions!$D$24 -> 12.509062 | H14: =H7*Assumptions!$D$24 -> 13.316098 | I14: =I7*Assumptions!$D$24 -> 14.526652 | J14: =J7*Assumptions!$D$24 -> 12.560994 | ... Q14: =Q7*Assumptions!$D$24 -> 15.049316
B15: Depreciation Budget | C15: ='Monthly Actuals'!R$17*(1+Assumptions!$D$22) -> 53.711146 | D15: ='Monthly Actuals'!S$17*(1+Assumptions!$D$22) -> 57.176381 | E15: ='Monthly Actuals'!T$17*(1+Assumptions!$D$22) -> 62.374234 | F15: ='Monthly Actuals'!U$17*(1+Assumptions!$D$22) -> 55.904904 | G15: ='Monthly Actuals'!V$17*(1+Assumptions!$D$22) -> 59.511672 | H15: ='Monthly Actuals'!W$17*(1+Assumptions!$D$22) -> 64.921824 | I15: ='Monthly Actuals'!X$17*(1+Assumptions!$D$22) -> 59.690078 | J15: ='Monthly Actuals'!Y$17*(1+Assumptions!$D$22) -> 63.541051 | ... Q15: ='Monthly Actuals'!AF$17*(1+Assumptions!$D$22) -> 74.639232
B16: EBIT Budget | C16: =C12-C15+C14 -> 459.5697 | D16: =D12-D15+D14 -> 352.0733 | E16: =E12-E15+E14 -> 373.27865 | F16: =F12-F15+F14 -> 419.35279 | G16: =G12-G15+G14 -> 393.70125 | H16: =H12-H15+H14 -> 417.53064 | I16: =I12-I15+I14 -> 466.6217 | J16: =J12-J15+J14 -> 391.55343 | ... Q16: =Q12-Q15+Q14 -> 470.60905
B17: Interest Budget | C17: ='Monthly Actuals'!R$19*(1+Assumptions!$D$23) -> 15.626092 | D17: ='Monthly Actuals'!S$19*(1+Assumptions!$D$23) -> 16.634228 | E17: ='Monthly Actuals'!T$19*(1+Assumptions!$D$23) -> 18.14643 | F17: ='Monthly Actuals'!U$19*(1+Assumptions!$D$23) -> 15.466132 | G17: ='Monthly Actuals'!V$19*(1+Assumptions!$D$23) -> 16.463947 | H17: ='Monthly Actuals'!W$19*(1+Assumptions!$D$23) -> 17.96067 | I17: ='Monthly Actuals'!X$19*(1+Assumptions!$D$23) -> 9.4143125 | J17: ='Monthly Actuals'!Y$19*(1+Assumptions!$D$23) -> 10.021687 | ... Q17: ='Monthly Actuals'!AF$19*(1+Assumptions!$D$23) -> 16.32366
B18: PBT Budget | C18: =C16-C17 -> 443.9436 | D18: =D16-D17 -> 335.43907 | E18: =E16-E17 -> 355.13222 | F18: =F16-F17 -> 403.88665 | G18: =G16-G17 -> 377.2373 | H18: =H16-H17 -> 399.56997 | I18: =I16-I17 -> 457.20739 | J18: =J16-J17 -> 381.53174 | ... Q18: =Q16-Q17 -> 454.28539
B19: Tax Budget | C19: =C18*Assumptions!$D$25 -> 102.99492 | D19: =D18*Assumptions!$D$25 -> 77.821864 | E19: =E18*Assumptions!$D$25 -> 82.390675 | F19: =F18*Assumptions!$D$25 -> 93.701703 | G19: =G18*Assumptions!$D$25 -> 87.519054 | H19: =H18*Assumptions!$D$25 -> 92.700234 | I19: =I18*Assumptions!$D$25 -> 106.07211 | J19: =J18*Assumptions!$D$25 -> 88.515364 | ... Q19: =Q18*Assumptions!$D$25 -> 105.39421
B20: PAT Budget | C20: =C18-C19 -> 340.94869 | D20: =D18-D19 -> 257.6172 | E20: =E18-E19 -> 272.74154 | F20: =F18-F19 -> 310.18495 | G20: =G18-G19 -> 289.71825 | H20: =H18-H19 -> 306.86974 | I20: =I18-I19 -> 351.13528 | J20: =J18-J19 -> 293.01638 | ... Q20: =Q18-Q19 -> 348.89118
B21: PAT Margin % | C21: =C20/C7 -> 0.15643174 | D21: =D20/D7 -> 0.1482441 | E21: =E20/E7 -> 0.14743535 | F21: =F20/F7 -> 0.15370305 | G21: =G20/G7 -> 0.15054436 | H21: =H20/H7 -> 0.14979263 | I21: =I20/I7 -> 0.15711668 | J21: =J20/J7 -> 0.15162864 | ... Q21: =Q20/Q7 -> 0.15069075
B22: 12-Month Budget (Jul-26 to Jun-27)
B23: Revenue (12-mo sum) | C23: =SUM(F7:Q7) -> 26372.602
B24: EBITDA (12-mo sum) | C24: =SUM(F12:Q12) -> 6039.3259
B25: PAT (12-mo sum) | C25: =SUM(F20:Q20) -> 4024.0193

Sheet Rolling Forecast
B2: ="Rolling Forecast -"&'Data Sheet'!B1 -> Rolling Forecast -NESTLE INDIA LTD
B3: Framework: 12-Month Forward Forecast (rolls forward from the latest Derived Monthly Actual using the Forecast growth/cost assumptions on the Assumptions sheet, Section B-D, Forecast column). This is a single forward-projection window refreshed by advancing the base month — not a fully automated, continuously-rolling multi-scenario engine.
B4: Month | C4: 46174 | D4: 46204 | E4: 46235 | F4: 46266 | G4: 46296 | H4: 46327 | I4: 46357 | J4: 46388 | K4: 46419 | L4: 46447 | M4: 46478 | N4: 46508 | O4: 46539
C5: Actual (Derived) | D5: Forecast | E5: Forecast | F5: Forecast | G5: Forecast | H5: Forecast | I5: Forecast | J5: Forecast | K5: Forecast | L5: Forecast | M5: Forecast | N5: Forecast | O5: Forecast
B7: 12-Month Rolling Forecast (₹ Crore)
B8: Revenue | C8: ='Monthly Actuals'!AF9 -> 2296.1448 | D8: ='Monthly Actuals'!T$9*(1+Assumptions!$E$11) -> 2054.7717 | E8: ='Monthly Actuals'!U$9*(1+Assumptions!$E$11) -> 1959.4614 | F8: ='Monthly Actuals'!V$9*(1+Assumptions!$E$11) -> 2085.8783 | G8: ='Monthly Actuals'!W$9*(1+Assumptions!$E$11) -> 2275.5036 | H8: ='Monthly Actuals'!X$9*(1+Assumptions!$E$11) -> 1967.5963 | I8: ='Monthly Actuals'!Y$9*(1+Assumptions!$E$11) -> 2094.538 | J8: ='Monthly Actuals'!Z$9*(1+Assumptions!$E$11) -> 2284.9505 | K8: ='Monthly Actuals'!AA$9*(1+Assumptions!$E$11) -> 2342.8327 | ... O8: ='Monthly Actuals'!AE$9*(1+Assumptions!$E$11) -> 2357.3753
B9: Total Operating Expenses | C9: ='Monthly Actuals'!AF10 -> 1742.418 | D9: =D10+D11+D12 -> 1602.7219 | E9: =E10+E11+E12 -> 1528.3799 | F9: =F10+F11+F12 -> 1626.985 | G9: =G10+G11+G12 -> 1774.8928 | H9: =H10+H11+H12 -> 1534.7251 | I9: =I10+I11+I12 -> 1633.7396 | J9: =J10+J11+J12 -> 1782.2614 | K9: =K10+K11+K12 -> 1827.4095 | ... O9: =O10+O11+O12 -> 1838.7528
B10: COGS | C10: ='Monthly Actuals'!AF11 -> 862.49691 | D10: =D8*Assumptions!$E$15 -> 811.63483 | E10: =E8*Assumptions!$E$15 -> 773.98725 | F10: =F8*Assumptions!$E$15 -> 823.92191 | G10: =G8*Assumptions!$E$15 -> 898.8239 | H10: =H8*Assumptions!$E$15 -> 777.20053 | I10: =I8*Assumptions!$E$15 -> 827.3425 | J10: =J8*Assumptions!$E$15 -> 902.55546 | K10: =K8*Assumptions!$E$15 -> 925.41891 | ... O10: =O8*Assumptions!$E$15 -> 931.16325
B11: Employee Cost | C11: ='Monthly Actuals'!AF12 -> 229.99918 | D11: =D8*Assumptions!$E$16 -> 205.47717 | E11: =E8*Assumptions!$E$16 -> 195.94614 | F11: =F8*Assumptions!$E$16 -> 208.58783 | G11: =G8*Assumptions!$E$16 -> 227.55036 | H11: =H8*Assumptions!$E$16 -> 196.75963 | I11: =I8*Assumptions!$E$16 -> 209.4538 | J11: =J8*Assumptions!$E$16 -> 228.49505 | K11: =K8*Assumptions!$E$16 -> 234.28327 | ... O11: =O8*Assumptions!$E$16 -> 235.73753
B12: Other Opex | C12: ='Monthly Actuals'!AF13 -> 649.92191 | D12: =D8*Assumptions!$E$17 -> 585.60994 | E12: =E8*Assumptions!$E$17 -> 558.4465 | F12: =F8*Assumptions!$E$17 -> 594.4753 | G12: =G8*Assumptions!$E$17 -> 648.51851 | H12: =H8*Assumptions!$E$17 -> 560.76494 | I12: =I8*Assumptions!$E$17 -> 596.94333 | J12: =J8*Assumptions!$E$17 -> 651.2109 | K12: =K8*Assumptions!$E$17 -> 667.70732 | ... O12: =O8*Assumptions!$E$17 -> 671.85197
B13: EBITDA | C13: ='Monthly Actuals'!AF14 -> 553.7268 | D13: =D8-D9 -> 452.04978 | E13: =E8-E9 -> 431.08151 | F13: =F8-F9 -> 458.89322 | G13: =G8-G9 -> 500.61078 | H13: =H8-H9 -> 432.87118 | I13: =I8-I9 -> 460.79836 | J13: =J8-J9 -> 502.68912 | K13: =K8-K9 -> 515.42319 | ... O13: =O8-O9 -> 518.62257
B14: EBITDA Margin % | C14: =C13/C8 -> 0.241155 | D14: =D13/D8 -> 0.22 | E14: =E13/E8 -> 0.22 | F14: =F13/F8 -> 0.22 | G14: =G13/G8 -> 0.22 | H14: =H13/H8 -> 0.22 | I14: =I13/I8 -> 0.22 | J14: =J13/J8 -> 0.22 | ... O14: =O13/O8 -> 0.22
B15: Other Income | C15: ='Monthly Actuals'!AF16 -> 5.8464 | D15: =D8*Assumptions!$E$24 -> 14.383402 | E15: =E8*Assumptions!$E$24 -> 13.71623 | F15: =F8*Assumptions!$E$24 -> 14.601148 | G15: =G8*Assumptions!$E$24 -> 15.928525 | H15: =H8*Assumptions!$E$24 -> 13.773174 | I15: =I8*Assumptions!$E$24 -> 14.661766 | J15: =J8*Assumptions!$E$24 -> 15.994654 | K15: =K8*Assumptions!$E$24 -> 16.399829 | ... O15: =O8*Assumptions!$E$24 -> 16.501627
B16: Depreciation | C16: ='Monthly Actuals'!AF17 -> 67.608 | D16: ='Monthly Actuals'!T$17*(1+Assumptions!$E$22) -> 62.430732 | E16: ='Monthly Actuals'!U$17*(1+Assumptions!$E$22) -> 55.955542 | F16: ='Monthly Actuals'!V$17*(1+Assumptions!$E$22) -> 59.565578 | G16: ='Monthly Actuals'!W$17*(1+Assumptions!$E$22) -> 64.98063 | H16: ='Monthly Actuals'!X$17*(1+Assumptions!$E$22) -> 59.744145 | I16: ='Monthly Actuals'!Y$17*(1+Assumptions!$E$22) -> 63.598607 | J16: ='Monthly Actuals'!Z$17*(1+Assumptions!$E$22) -> 69.380298 | K16: ='Monthly Actuals'!AA$17*(1+Assumptions!$E$22) -> 70.061751 | ... O16: ='Monthly Actuals'!AE$17*(1+Assumptions!$E$22) -> 68.48127
B17: EBIT | C17: ='Monthly Actuals'!AF18 -> 491.9652 | D17: =D13+D15-D16 -> 404.00245 | E17: =E13+E15-E16 -> 388.84219 | F17: =F13+F15-F16 -> 413.92879 | G17: =G13+G15-G16 -> 451.55868 | H17: =H13+H15-H16 -> 386.90021 | I17: =I13+I15-I16 -> 411.86152 | J17: =J13+J15-J16 -> 449.30347 | K17: =K13+K15-K16 -> 461.76127 | ... O17: =O13+O15-O16 -> 466.64293
B18: Interest | C18: ='Monthly Actuals'!AF19 -> 15.1848 | D18: ='Monthly Actuals'!T$19*(1+Assumptions!$E$23) -> 18.315234 | E18: ='Monthly Actuals'!U$19*(1+Assumptions!$E$23) -> 15.610003 | F18: ='Monthly Actuals'!V$19*(1+Assumptions!$E$23) -> 16.6171 | G18: ='Monthly Actuals'!W$19*(1+Assumptions!$E$23) -> 18.127746 | H18: ='Monthly Actuals'!X$19*(1+Assumptions!$E$23) -> 9.5018875 | I18: ='Monthly Actuals'!Y$19*(1+Assumptions!$E$23) -> 10.114912 | J18: ='Monthly Actuals'!Z$19*(1+Assumptions!$E$23) -> 11.03445 | K18: ='Monthly Actuals'!AA$19*(1+Assumptions!$E$23) -> 12.364226 | ... O18: ='Monthly Actuals'!AE$19*(1+Assumptions!$E$23) -> 15.102549
B19: EBT | C19: ='Monthly Actuals'!AF20 -> 476.7804 | D19: =D17-D18 -> 385.68721 | E19: =E17-E18 -> 373.23219 | F19: =F17-F18 -> 397.31169 | G19: =G17-G18 -> 433.43093 | H19: =H17-H18 -> 377.39832 | I19: =I17-I18 -> 401.7466 | J19: =J17-J18 -> 438.26902 | K19: =K17-K18 -> 449.39704 | ... O19: =O17-O18 -> 451.54038
B20: Tax | C20: ='Monthly Actuals'!AF21 -> 125.7372 | D20: =D19*Assumptions!$E$25 -> 90.636495 | E20: =E19*Assumptions!$E$25 -> 87.709565 | F20: =F19*Assumptions!$E$25 -> 93.368246 | G20: =G19*Assumptions!$E$25 -> 101.85627 | H20: =H19*Assumptions!$E$25 -> 88.688606 | I20: =I19*Assumptions!$E$25 -> 94.410452 | J20: =J19*Assumptions!$E$25 -> 102.99322 | K20: =K19*Assumptions!$E$25 -> 105.60831 | ... O20: =O19*Assumptions!$E$25 -> 106.11199
B21: PAT | C21: ='Monthly Actuals'!AF22 -> 351.0432 | D21: =D19-D20 -> 295.05072 | E21: =E19-E20 -> 285.52263 | F21: =F19-F20 -> 303.94344 | G21: =G19-G20 -> 331.57466 | H21: =H19-H20 -> 288.70972 | I21: =I19-I20 -> 307.33615 | J21: =J19-J20 -> 335.2758 | K21: =K19-K20 -> 343.78874 | ... O21: =O19-O20 -> 345.42839
B22: PAT Margin % | C22: =C21/C8 -> 0.15288374 | D22: =D21/D8 -> 0.14359294 | E22: =E21/E8 -> 0.14571485 | F22: =F21/F8 -> 0.14571485 | G22: =G21/G8 -> 0.14571485 | H22: =H21/H8 -> 0.14673219 | I22: =I21/I8 -> 0.14673219 | J22: =J21/J8 -> 0.14673219 | ... O22: =O21/O8 -> 0.14653093
B24: 12-Month Rolling Forecast Total
B25: Revenue (12-mo sum) | C25: =SUM(D8:O8) -> 26852.104
B26: EBITDA (12-mo sum) | C26: =SUM(D13:O13) -> 5907.4629
B27: PAT (12-mo sum) | C27: =SUM(D21:O21) -> 3926.3308

Sheet Budget VS Actuals
B2: ="Budget vs Actual (Apr-26 to Jun-26) -"&'Data Sheet'!B1 -> Budget vs Actual (Apr-26 to Jun-26) -NESTLE INDIA LTD
B4: Month | C4: 46113 | D4: 46143 | E4: 46174
B6: Revenue
B7: Budget | C7: ='Monthly Budget'!C7 -> 2179.5365 | D7: ='Monthly Budget'!D7 -> 1737.7906 | E7: ='Monthly Budget'!E7 -> 1849.9061
B8: Actual (Derived) | C8: ='Monthly Actuals'!AD9 -> 1977.2358 | D8: ='Monthly Actuals'!AE9 -> 2104.7994 | E8: ='Monthly Actuals'!AF9 -> 2296.1448
B9: Variance | C9: =C8-C7 -> -202.30068 | D9: =D8-D7 -> 367.00884 | E9: =E8-E7 -> 446.23872
B10: Variance % | C10: =IFERROR((C8-C7)/ABS(C7),0) -> -0.092818212 | D10: =IFERROR((D8-D7)/ABS(D7),0) -> 0.21119279 | E10: =IFERROR((E8-E7)/ABS(E7),0) -> 0.24122237
B12: COGS
B13: Budget | C13: ='Monthly Budget'!C9 -> 845.66015 | D13: ='Monthly Budget'!D9 -> 674.26274 | E13: ='Monthly Budget'!E9 -> 717.76356
B14: Actual (Derived) | C14: ='Monthly Actuals'!AD11 -> 742.70567 | D14: ='Monthly Actuals'!AE11 -> 790.62217 | E14: ='Monthly Actuals'!AF11 -> 862.49691
B15: Variance | C15: =C14-C13 -> -102.95448 | D15: =D14-D13 -> 116.35943 | E15: =E14-E13 -> 144.73335
B16: Variance % | C16: =IFERROR((C14-C13)/ABS(C13),0) -> -0.12174451 | D16: =IFERROR((D14-D13)/ABS(D13),0) -> 0.17257283 | E16: =IFERROR((E14-E13)/ABS(E13),0) -> 0.20164489
B18: Employee Cost
B19: Budget | C19: ='Monthly Budget'!C10 -> 222.31272 | D19: ='Monthly Budget'!D10 -> 177.25464 | E19: ='Monthly Budget'!E10 -> 188.69042
B20: Actual (Derived) | C20: ='Monthly Actuals'!AD12 -> 198.05485 | D20: ='Monthly Actuals'!AE12 -> 210.83258 | E20: ='Monthly Actuals'!AF12 -> 229.99918
B21: Variance | C21: =C20-C19 -> -24.257875 | D21: =D20-D19 -> 33.577941 | E21: =E20-E19 -> 41.308756
B22: Variance % | C22: =IFERROR((C20-C19)/ABS(C19),0) -> -0.109116 | D22: =IFERROR((D20-D19)/ABS(D19),0) -> 0.18943336 | E22: =IFERROR((E20-E19)/ABS(E19),0) -> 0.21892344
B24: Other Operating Expenses
B25: Budget | C25: ='Monthly Budget'!C11 -> 612.44975 | D25: ='Monthly Budget'!D11 -> 488.31915 | E25: ='Monthly Budget'!E11 -> 519.82361
B26: Actual (Derived) | C26: ='Monthly Actuals'!AD13 -> 559.65498 | D26: ='Monthly Actuals'!AE13 -> 595.76175 | E26: ='Monthly Actuals'!AF13 -> 649.92191
B27: Variance | C27: =C26-C25 -> -52.794769 | D27: =D26-D25 -> 107.44261 | E27: =E26-E25 -> 130.09831
B28: Variance % | C28: =IFERROR((C26-C25)/ABS(C25),0) -> -0.086202614 | D28: =IFERROR((D26-D25)/ABS(D25),0) -> 0.22002538 | E28: =IFERROR((E26-E25)/ABS(E25),0) -> 0.25027395
B30: EBITDA
B31: Budget | C31: ='Monthly Budget'!C12 -> 499.11385 | D31: ='Monthly Budget'!D12 -> 397.95404 | E31: ='Monthly Budget'!E12 -> 423.62849
B32: Actual (Derived) | C32: ='Monthly Actuals'!AD14 -> 476.8203 | D32: ='Monthly Actuals'!AE14 -> 507.5829 | E32: ='Monthly Actuals'!AF14 -> 553.7268
B33: Variance | C33: =C32-C31 -> -22.293554 | D33: =D32-D31 -> 109.62886 | E33: =E32-E31 -> 130.09831
B34: Variance % | C34: =IFERROR((C32-C31)/ABS(C31),0) -> -0.04466627 | D34: =IFERROR((D32-D31)/ABS(D31),0) -> 0.27548121 | E34: =IFERROR((E32-E31)/ABS(E31),0) -> 0.30710472
B36: Depreciation
B37: Budget | C37: ='Monthly Budget'!C15 -> 53.711146 | D37: ='Monthly Budget'!D15 -> 57.176381 | E37: ='Monthly Budget'!E15 -> 62.374234
B38: Actual (Derived) | C38: ='Monthly Actuals'!AD17 -> 58.218 | D38: ='Monthly Actuals'!AE17 -> 61.974 | E38: ='Monthly Actuals'!AF17 -> 67.608
B39: Variance | C39: =C38-C37 -> 4.5068544 | D39: =D38-D37 -> 4.7976192 | E39: =E38-E37 -> 5.2337664
B40: Variance % | C40: =IFERROR((C38-C37)/ABS(C37),0) -> 0.08390911 | D40: =IFERROR((D38-D37)/ABS(D37),0) -> 0.08390911 | E40: =IFERROR((E38-E37)/ABS(E37),0) -> 0.08390911
B42: Interest
B43: Budget | C43: ='Monthly Budget'!C17 -> 15.626092 | D43: ='Monthly Budget'!D17 -> 16.634228 | E43: ='Monthly Budget'!E17 -> 18.14643
B44: Actual (Derived) | C44: ='Monthly Actuals'!AD19 -> 13.0758 | D44: ='Monthly Actuals'!AE19 -> 13.9194 | E44: ='Monthly Actuals'!AF19 -> 15.1848
B45: Variance | C45: =C44-C43 -> -2.5502925 | D45: =D44-D43 -> -2.7148275 | E45: =E44-E43 -> -2.96163
B46: Variance % | C46: =IFERROR((C44-C43)/ABS(C43),0) -> -0.16320731 | D46: =IFERROR((D44-D43)/ABS(D43),0) -> -0.16320731 | E46: =IFERROR((E44-E43)/ABS(E43),0) -> -0.16320731
B48: Tax
B49: Budget | C49: ='Monthly Budget'!C19 -> 102.99492 | D49: ='Monthly Budget'!D19 -> 77.821864 | E49: ='Monthly Budget'!E19 -> 82.390675
B50: Actual (Derived) | C50: ='Monthly Actuals'!AD21 -> 108.2737 | D50: ='Monthly Actuals'!AE21 -> 115.2591 | E50: ='Monthly Actuals'!AF21 -> 125.7372
B51: Variance | C51: =C50-C49 -> 5.2787841 | D51: =D50-D49 -> 37.437236 | E51: =E50-E49 -> 43.346525
B52: Variance % | C52: =IFERROR((C50-C49)/ABS(C49),0) -> 0.051252861 | D52: =IFERROR((D50-D49)/ABS(D49),0) -> 0.48106322 | E52: =IFERROR((E50-E49)/ABS(E49),0) -> 0.52610961
B54: PAT
B55: Budget | C55: ='Monthly Budget'!C20 -> 340.94869 | D55: ='Monthly Budget'!D20 -> 257.6172 | E55: ='Monthly Budget'!E20 -> 272.74154
B56: Actual (Derived) | C56: ='Monthly Actuals'!AD22 -> 302.2872 | D56: ='Monthly Actuals'!AE22 -> 321.7896 | E56: ='Monthly Actuals'!AF22 -> 351.0432
B57: Variance | C57: =C56-C55 -> -38.661487 | D57: =D56-D55 -> 64.172395 | E57: =E56-E55 -> 78.301656
B58: Variance % | C58: =IFERROR((C56-C55)/ABS(C55),0) -> -0.11339386 | D58: =IFERROR((D56-D55)/ABS(D55),0) -> 0.2490998 | E58: =IFERROR((E56-E55)/ABS(E55),0) -> 0.28709105

Sheet Budget VS Forecast
B2: ="Budget vs Forecast (Jul-26 to Jun-27) -"&'Data Sheet'!B1 -> Budget vs Forecast (Jul-26 to Jun-27) -NESTLE INDIA LTD
B4: Month | C4: 46204 | D4: 46235 | E4: 46266 | F4: 46296 | G4: 46327 | H4: 46357 | I4: 46388 | J4: 46419 | K4: 46447 | L4: 46478 | M4: 46508 | N4: 46539
B6: Revenue
B7: Budget | C7: ='Monthly Budget'!F7 -> 2018.0794 | D7: ='Monthly Budget'!G7 -> 1924.471 | E7: ='Monthly Budget'!H7 -> 2048.6304 | F7: ='Monthly Budget'!I7 -> 2234.8696 | G7: ='Monthly Budget'!J7 -> 1932.4606 | H7: ='Monthly Budget'!K7 -> 2057.1355 | I7: ='Monthly Budget'!L7 -> 2244.1478 | J7: ='Monthly Budget'!M7 -> 2300.9964 | ... N7: ='Monthly Budget'!Q7 -> 2315.2793
B8: Forecast | C8: ='Rolling Forecast'!D8 -> 2054.7717 | D8: ='Rolling Forecast'!E8 -> 1959.4614 | E8: ='Rolling Forecast'!F8 -> 2085.8783 | F8: ='Rolling Forecast'!G8 -> 2275.5036 | G8: ='Rolling Forecast'!H8 -> 1967.5963 | H8: ='Rolling Forecast'!I8 -> 2094.538 | I8: ='Rolling Forecast'!J8 -> 2284.9505 | J8: ='Rolling Forecast'!K8 -> 2342.8327 | ... N8: ='Rolling Forecast'!O8 -> 2357.3753
B9: Variance | C9: =C8-C7 -> 36.692352 | D9: =D8-D7 -> 34.990382 | E9: =E8-E7 -> 37.247826 | F9: =F8-F7 -> 40.633992 | G9: =G8-G7 -> 35.135648 | H9: =H8-H7 -> 37.402464 | I9: =I8-I7 -> 40.802688 | J9: =J8-J7 -> 41.836298 | ... N9: =N8-N7 -> 42.095988
B10: Variance % | C10: =IFERROR((C8-C7)/ABS(C7),0) -> 0.018181818 | D10: =IFERROR((D8-D7)/ABS(D7),0) -> 0.018181818 | E10: =IFERROR((E8-E7)/ABS(E7),0) -> 0.018181818 | F10: =IFERROR((F8-F7)/ABS(F7),0) -> 0.018181818 | G10: =IFERROR((G8-G7)/ABS(G7),0) -> 0.018181818 | H10: =IFERROR((H8-H7)/ABS(H7),0) -> 0.018181818 | I10: =IFERROR((I8-I7)/ABS(I7),0) -> 0.018181818 | J10: =IFERROR((J8-J7)/ABS(J7),0) -> 0.018181818 | ... N10: =IFERROR((N8-N7)/ABS(N7),0) -> 0.018181818
B12: COGS
B13: Budget | C13: ='Monthly Budget'!F9 -> 783.01479 | D13: ='Monthly Budget'!G9 -> 746.69475 | E13: ='Monthly Budget'!H9 -> 794.86861 | F13: ='Monthly Budget'!I9 -> 867.12939 | G13: ='Monthly Budget'!J9 -> 749.79473 | H13: ='Monthly Budget'!K9 -> 798.16858 | I13: ='Monthly Budget'!L9 -> 870.72936 | J13: ='Monthly Budget'!M9 -> 892.7866 | ... N13: ='Monthly Budget'!Q9 -> 898.32838
B14: Forecast | C14: ='Rolling Forecast'!D10 -> 811.63483 | D14: ='Rolling Forecast'!E10 -> 773.98725 | E14: ='Rolling Forecast'!F10 -> 823.92191 | F14: ='Rolling Forecast'!G10 -> 898.8239 | G14: ='Rolling Forecast'!H10 -> 777.20053 | H14: ='Rolling Forecast'!I10 -> 827.3425 | I14: ='Rolling Forecast'!J10 -> 902.55546 | J14: ='Rolling Forecast'!K10 -> 925.41891 | ... N14: ='Rolling Forecast'!O10 -> 931.16325
B15: Variance | C15: =C14-C13 -> 28.620035 | D15: =D14-D13 -> 27.292498 | E15: =E14-E13 -> 29.053304 | F15: =F14-F13 -> 31.694514 | G15: =G14-G13 -> 27.405805 | H15: =H14-H13 -> 29.173922 | I15: =I14-I13 -> 31.826097 | J15: =J14-J13 -> 32.632312 | ... N15: =N14-N13 -> 32.834871
B16: Variance % | C16: =IFERROR((C14-C13)/ABS(C13),0) -> 0.036551078 | D16: =IFERROR((D14-D13)/ABS(D13),0) -> 0.036551078 | E16: =IFERROR((E14-E13)/ABS(E13),0) -> 0.036551078 | F16: =IFERROR((F14-F13)/ABS(F13),0) -> 0.036551078 | G16: =IFERROR((G14-G13)/ABS(G13),0) -> 0.036551078 | H16: =IFERROR((H14-H13)/ABS(H13),0) -> 0.036551078 | I16: =IFERROR((I14-I13)/ABS(I13),0) -> 0.036551078 | J16: =IFERROR((J14-J13)/ABS(J13),0) -> 0.036551078 | ... N16: =IFERROR((N14-N13)/ABS(N13),0) -> 0.036551078
B18: Employee Cost
B19: Budget | C19: ='Monthly Budget'!F10 -> 205.84409 | D19: ='Monthly Budget'!G10 -> 196.29604 | E19: ='Monthly Budget'!H10 -> 208.9603 | F19: ='Monthly Budget'!I10 -> 227.9567 | G19: ='Monthly Budget'!J10 -> 197.11099 | H19: ='Monthly Budget'!K10 -> 209.82782 | I19: ='Monthly Budget'!L10 -> 228.90308 | J19: ='Monthly Budget'!M10 -> 234.70163 | ... N19: ='Monthly Budget'!Q10 -> 236.15849
B20: Forecast | C20: ='Rolling Forecast'!D11 -> 205.47717 | D20: ='Rolling Forecast'!E11 -> 195.94614 | E20: ='Rolling Forecast'!F11 -> 208.58783 | F20: ='Rolling Forecast'!G11 -> 227.55036 | G20: ='Rolling Forecast'!H11 -> 196.75963 | H20: ='Rolling Forecast'!I11 -> 209.4538 | I20: ='Rolling Forecast'!J11 -> 228.49505 | J20: ='Rolling Forecast'!K11 -> 234.28327 | ... N20: ='Rolling Forecast'!O11 -> 235.73753
B21: Variance | C21: =C20-C19 -> -0.36692352 | D21: =D20-D19 -> -0.34990382 | E21: =E20-E19 -> -0.37247826 | F21: =F20-F19 -> -0.40633992 | G21: =G20-G19 -> -0.35135648 | H21: =H20-H19 -> -0.37402464 | I21: =I20-I19 -> -0.40802688 | J21: =J20-J19 -> -0.41836298 | ... N21: =N20-N19 -> -0.42095988
B22: Variance % | C22: =IFERROR((C20-C19)/ABS(C19),0) -> -0.0017825312 | D22: =IFERROR((D20-D19)/ABS(D19),0) -> -0.0017825312 | E22: =IFERROR((E20-E19)/ABS(E19),0) -> -0.0017825312 | F22: =IFERROR((F20-F19)/ABS(F19),0) -> -0.0017825312 | G22: =IFERROR((G20-G19)/ABS(G19),0) -> -0.0017825312 | H22: =IFERROR((H20-H19)/ABS(H19),0) -> -0.0017825312 | I22: =IFERROR((I20-I19)/ABS(I19),0) -> -0.0017825312 | J22: =IFERROR((J20-J19)/ABS(J19),0) -> -0.0017825312 | ... N22: =IFERROR((N20-N19)/ABS(N19),0) -> -0.0017825312
B24: Other Operating Expenses
B25: Budget | C25: ='Monthly Budget'!F11 -> 567.0803 | D25: ='Monthly Budget'!G11 -> 540.77635 | E25: ='Monthly Budget'!H11 -> 575.66515 | F25: ='Monthly Budget'!I11 -> 627.99835 | G25: ='Monthly Budget'!J11 -> 543.02144 | H25: ='Monthly Budget'!K11 -> 578.05508 | I25: ='Monthly Budget'!L11 -> 630.60554 | J25: ='Monthly Budget'!M11 -> 646.57999 | ... N25: ='Monthly Budget'!Q11 -> 650.59349
B26: Forecast | C26: ='Rolling Forecast'!D12 -> 585.60994 | D26: ='Rolling Forecast'!E12 -> 558.4465 | E26: ='Rolling Forecast'!F12 -> 594.4753 | F26: ='Rolling Forecast'!G12 -> 648.51851 | G26: ='Rolling Forecast'!H12 -> 560.76494 | H26: ='Rolling Forecast'!I12 -> 596.94333 | I26: ='Rolling Forecast'!J12 -> 651.2109 | J26: ='Rolling Forecast'!K12 -> 667.70732 | ... N26: ='Rolling Forecast'!O12 -> 671.85197
B27: Variance | C27: =C26-C25 -> 18.529638 | D27: =D26-D25 -> 17.670143 | E27: =E26-E25 -> 18.810152 | F27: =F26-F25 -> 20.520166 | G27: =G26-G25 -> 17.743502 | H27: =H26-H25 -> 18.888244 | I27: =I26-I25 -> 20.605357 | J27: =J26-J25 -> 21.12733 | ... N27: =N26-N25 -> 21.258474
B28: Variance % | C28: =IFERROR((C26-C25)/ABS(C25),0) -> 0.03267551 | D28: =IFERROR((D26-D25)/ABS(D25),0) -> 0.03267551 | E28: =IFERROR((E26-E25)/ABS(E25),0) -> 0.03267551 | F28: =IFERROR((F26-F25)/ABS(F25),0) -> 0.03267551 | G28: =IFERROR((G26-G25)/ABS(G25),0) -> 0.03267551 | H28: =IFERROR((H26-H25)/ABS(H25),0) -> 0.03267551 | I28: =IFERROR((I26-I25)/ABS(I25),0) -> 0.03267551 | J28: =IFERROR((J26-J25)/ABS(J25),0) -> 0.03267551 | ... N28: =IFERROR((N26-N25)/ABS(N25),0) -> 0.03267551
B30: EBITDA
B31: Budget | C31: ='Monthly Budget'!F12 -> 462.14017 | D31: ='Monthly Budget'!G12 -> 440.70386 | E31: ='Monthly Budget'!H12 -> 469.13637 | F31: ='Monthly Budget'!I12 -> 511.78513 | G31: ='Monthly Budget'!J12 -> 442.53349 | H31: ='Monthly Budget'!K12 -> 471.08403 | I31: ='Monthly Budget'!L12 -> 513.90986 | J31: ='Monthly Budget'!M12 -> 526.92817 | ... N31: ='Monthly Budget'!Q12 -> 530.19897
B32: Forecast | C32: ='Rolling Forecast'!D13 -> 452.04978 | D32: ='Rolling Forecast'!E13 -> 431.08151 | E32: ='Rolling Forecast'!F13 -> 458.89322 | F32: ='Rolling Forecast'!G13 -> 500.61078 | G32: ='Rolling Forecast'!H13 -> 432.87118 | H32: ='Rolling Forecast'!I13 -> 460.79836 | I32: ='Rolling Forecast'!J13 -> 502.68912 | J32: ='Rolling Forecast'!K13 -> 515.42319 | ... N32: ='Rolling Forecast'!O13 -> 518.62257
B33: Variance | C33: =C32-C31 -> -10.090397 | D33: =D32-D31 -> -9.6223551 | E33: =E32-E31 -> -10.243152 | F33: =F32-F31 -> -11.174348 | G33: =G32-G31 -> -9.6623032 | H33: =H32-H31 -> -10.285678 | I33: =I32-I31 -> -11.220739 | J33: =J32-J31 -> -11.504982 | ... N33: =N32-N31 -> -11.576397
B34: Variance % | C34: =IFERROR((C32-C31)/ABS(C31),0) -> -0.021834061 | D34: =IFERROR((D32-D31)/ABS(D31),0) -> -0.021834061 | E34: =IFERROR((E32-E31)/ABS(E31),0) -> -0.021834061 | F34: =IFERROR((F32-F31)/ABS(F31),0) -> -0.021834061 | G34: =IFERROR((G32-G31)/ABS(G31),0) -> -0.021834061 | H34: =IFERROR((H32-H31)/ABS(H31),0) -> -0.021834061 | I34: =IFERROR((I32-I31)/ABS(I31),0) -> -0.021834061 | J34: =IFERROR((J32-J31)/ABS(J31),0) -> -0.021834061 | ... N34: =IFERROR((N32-N31)/ABS(N31),0) -> -0.021834061
B36: Depreciation
B37: Budget | C37: ='Monthly Budget'!F15 -> 55.904904 | D37: ='Monthly Budget'!G15 -> 59.511672 | E37: ='Monthly Budget'!H15 -> 64.921824 | F37: ='Monthly Budget'!I15 -> 59.690078 | G37: ='Monthly Budget'!J15 -> 63.541051 | H37: ='Monthly Budget'!K15 -> 69.31751 | I37: ='Monthly Budget'!L15 -> 69.998347 | J37: ='Monthly Budget'!M15 -> 74.51437 | ... N37: ='Monthly Budget'!Q15 -> 74.639232
B38: Forecast | C38: ='Rolling Forecast'!D16 -> 62.430732 | D38: ='Rolling Forecast'!E16 -> 55.955542 | E38: ='Rolling Forecast'!F16 -> 59.565578 | F38: ='Rolling Forecast'!G16 -> 64.98063 | G38: ='Rolling Forecast'!H16 -> 59.744145 | H38: ='Rolling Forecast'!I16 -> 63.598607 | I38: ='Rolling Forecast'!J16 -> 69.380298 | J38: ='Rolling Forecast'!K16 -> 70.061751 | ... N38: ='Rolling Forecast'!O16 -> 68.48127
B39: Variance | C39: =C38-C37 -> 6.525828 | D39: =D38-D37 -> -3.5561295 | E39: =E38-E37 -> -5.3562465 | F39: =F38-F37 -> 5.2905516 | G39: =G38-G37 -> -3.7969057 | H39: =H38-H37 -> -5.7189039 | I39: =I38-I37 -> -0.6180492 | J39: =J38-J37 -> -4.4526181 | ... N39: =N38-N37 -> -6.157962
B40: Variance % | C40: =IFERROR((C38-C37)/ABS(C37),0) -> 0.11673087 | D40: =IFERROR((D38-D37)/ABS(D37),0) -> -0.05975516 | E40: =IFERROR((E38-E37)/ABS(E37),0) -> -0.082503019 | F40: =IFERROR((F38-F37)/ABS(F37),0) -> 0.088633685 | G40: =IFERROR((G38-G37)/ABS(G37),0) -> -0.05975516 | H40: =IFERROR((H38-H37)/ABS(H37),0) -> -0.082503019 | I40: =IFERROR((I38-I37)/ABS(I37),0) -> -0.0088294828 | J40: =IFERROR((J38-J37)/ABS(J37),0) -> -0.05975516 | ... N40: =IFERROR((N38-N37)/ABS(N37),0) -> -0.082503019
B42: Interest
B43: Budget | C43: ='Monthly Budget'!F17 -> 15.466132 | D43: ='Monthly Budget'!G17 -> 16.463947 | E43: ='Monthly Budget'!H17 -> 17.96067 | F43: ='Monthly Budget'!I17 -> 9.4143125 | G43: ='Monthly Budget'!J17 -> 10.021687 | H43: ='Monthly Budget'!K17 -> 10.93275 | I43: ='Monthly Budget'!L17 -> 12.25027 | J43: ='Monthly Budget'!M17 -> 13.04061 | ... N43: ='Monthly Budget'!Q17 -> 16.32366
B44: Forecast | C44: ='Rolling Forecast'!D18 -> 18.315234 | D44: ='Rolling Forecast'!E18 -> 15.610003 | E44: ='Rolling Forecast'!F18 -> 16.6171 | F44: ='Rolling Forecast'!G18 -> 18.127746 | G44: ='Rolling Forecast'!H18 -> 9.5018875 | H44: ='Rolling Forecast'!I18 -> 10.114912 | I44: ='Rolling Forecast'!J18 -> 11.03445 | J44: ='Rolling Forecast'!K18 -> 12.364226 | ... N44: ='Rolling Forecast'!O18 -> 15.102549
B45: Variance | C45: =C44-C43 -> 2.8491015 | D45: =D44-D43 -> -0.853944 | E45: =E44-E43 -> -1.3435695 | F45: =F44-F43 -> 8.7134335 | G45: =G44-G43 -> -0.5198 | H45: =H44-H43 -> -0.8178375 | I45: =I44-I43 -> -1.21582 | J45: =J44-J43 -> -0.676384 | ... N45: =N44-N43 -> -1.221111
B46: Variance % | C46: =IFERROR((C44-C43)/ABS(C43),0) -> 0.18421551 | D46: =IFERROR((D44-D43)/ABS(D43),0) -> -0.051867512 | E46: =IFERROR((E44-E43)/ABS(E43),0) -> -0.074806202 | F46: =IFERROR((F44-F43)/ABS(F43),0) -> 0.92555176 | G46: =IFERROR((G44-G43)/ABS(G43),0) -> -0.051867512 | H46: =IFERROR((H44-H43)/ABS(H43),0) -> -0.074806202 | I46: =IFERROR((I44-I43)/ABS(I43),0) -> -0.099248425 | J46: =IFERROR((J44-J43)/ABS(J43),0) -> -0.051867512 | ... N46: =IFERROR((N44-N43)/ABS(N43),0) -> -0.074806202
B48: Tax
B49: Budget | C49: ='Monthly Budget'!F19 -> 93.701703 | D49: ='Monthly Budget'!G19 -> 87.519054 | E49: ='Monthly Budget'!H19 -> 92.700234 | F49: ='Monthly Budget'!I19 -> 106.07211 | G49: ='Monthly Budget'!J19 -> 88.515364 | H49: ='Monthly Budget'!K19 -> 93.775596 | I49: ='Monthly Budget'!L19 -> 103.52958 | J49: ='Monthly Budget'!M19 -> 105.40448 | ... N49: ='Monthly Budget'!Q19 -> 105.39421
B50: Forecast | C50: ='Rolling Forecast'!D20 -> 90.636495 | D50: ='Rolling Forecast'!E20 -> 87.709565 | E50: ='Rolling Forecast'!F20 -> 93.368246 | F50: ='Rolling Forecast'!G20 -> 101.85627 | G50: ='Rolling Forecast'!H20 -> 88.688606 | H50: ='Rolling Forecast'!I20 -> 94.410452 | I50: ='Rolling Forecast'!J20 -> 102.99322 | J50: ='Rolling Forecast'!K20 -> 105.60831 | ... N50: ='Rolling Forecast'!O20 -> 106.11199
B51: Variance | C51: =C50-C49 -> -3.0652085 | D51: =D50-D49 -> 0.19051027 | E51: =E50-E49 -> 0.66801267 | F51: =F50-F49 -> -4.215846 | G51: =G50-G49 -> 0.17324208 | H51: =H50-H49 -> 0.63485593 | I51: =I50-I49 -> -0.53636206 | J51: =J50-J49 -> 0.20382153 | ... N51: =N50-N49 -> 0.71777833
B52: Variance % | C52: =IFERROR((C50-C49)/ABS(C49),0) -> -0.032712409 | D52: =IFERROR((D50-D49)/ABS(D49),0) -> 0.0021767862 | E52: =IFERROR((E50-E49)/ABS(E49),0) -> 0.0072061595 | F52: =IFERROR((F50-F49)/ABS(F49),0) -> -0.039745092 | G52: =IFERROR((G50-G49)/ABS(G49),0) -> 0.0019571978 | H52: =IFERROR((H50-H49)/ABS(H49),0) -> 0.0067699483 | I52: =IFERROR((I50-I49)/ABS(I49),0) -> -0.0051807614 | J52: =IFERROR((J50-J49)/ABS(J49),0) -> 0.0019337084 | ... N52: =IFERROR((N50-N49)/ABS(N49),0) -> 0.0068104151
B54: PAT
B55: Budget | C55: ='Monthly Budget'!F20 -> 310.18495 | D55: ='Monthly Budget'!G20 -> 289.71825 | E55: ='Monthly Budget'!H20 -> 306.86974 | F55: ='Monthly Budget'!I20 -> 351.13528 | G55: ='Monthly Budget'!J20 -> 293.01638 | H55: ='Monthly Budget'!K20 -> 310.42956 | I55: ='Monthly Budget'!L20 -> 342.71862 | J55: ='Monthly Budget'!M20 -> 348.92519 | ... N55: ='Monthly Budget'!Q20 -> 348.89118
B56: Forecast | C56: ='Rolling Forecast'!D21 -> 295.05072 | D56: ='Rolling Forecast'!E21 -> 285.52263 | E56: ='Rolling Forecast'!F21 -> 303.94344 | F56: ='Rolling Forecast'!G21 -> 331.57466 | G56: ='Rolling Forecast'!H21 -> 288.70972 | H56: ='Rolling Forecast'!I21 -> 307.33615 | I56: ='Rolling Forecast'!J21 -> 335.2758 | J56: ='Rolling Forecast'!K21 -> 343.78874 | ... N56: ='Rolling Forecast'!O21 -> 345.42839
B57: Variance | C57: =C56-C55 -> -15.134232 | D57: =D56-D55 -> -4.1956236 | E57: =E56-E55 -> -2.9262988 | F57: =F56-F55 -> -19.560614 | G57: =G56-G55 -> -4.3066597 | H57: =H56-H55 -> -3.0934071 | I57: =I56-I55 -> -7.4428152 | J57: =J56-J55 -> -5.1364491 | ... N57: =N56-N55 -> -3.4627904
B58: Variance % | C58: =IFERROR((C56-C55)/ABS(C55),0) -> -0.048790993 | D58: =IFERROR((D56-D55)/ABS(D55),0) -> -0.014481738 | E58: =IFERROR((E56-E55)/ABS(E55),0) -> -0.0095359641 | F58: =IFERROR((F56-F55)/ABS(F55),0) -> -0.055706776 | G58: =IFERROR((G56-G55)/ABS(G55),0) -> -0.014697676 | H58: =IFERROR((H56-H55)/ABS(H55),0) -> -0.0099649245 | I58: =IFERROR((I56-I55)/ABS(I55),0) -> -0.021716985 | J58: =IFERROR((J56-J55)/ABS(J55),0) -> -0.014720775 | ... N58: =IFERROR((N56-N55)/ABS(N55),0) -> -0.0099251303

Sheet Variance Analysis
B2: ="Variance Analysis -"&'Data Sheet'!B1 -> Variance Analysis -NESTLE INDIA LTD
B4: Part 1 — Budget vs Actual (Q1 FY26-27: Apr-Jun 2026, YTD)
B5: Line Item | C5: Budget (YTD) | D5: Actual (YTD) | E5: Variance | F5: Variance % | H5: Driver / Explanation
B6: Revenue | C6: ='Budget VS Actuals'!C7+'Budget VS Actuals'!D7+'Budget VS Actuals'!E7 -> 5767.2331 | D6: ='Budget VS Actuals'!C8+'Budget VS Actuals'!D8+'Budget VS Actuals'!E8 -> 6378.18 | E6: =D6-C6 -> 610.94688 | F6: =IFERROR((D6-C6)/ABS(C6),0) -> 0.10593414 | G6: =IF(E6>=0,"Revenue exceeded budget — attributable to the modelled revenue growth assumption; recent quarterly trends ran ahead of the budgeted growth rate.","Revenue fell short of budget — attributable to the modelled revenue growth assumption running ahead of the derived actual trend; likely driver based on model assumptions.") -> Revenue exceeded budget — attributable to the modelled revenue growth assumption; recent quarterly trends ran ahead of the budgeted growth rate.
B7: COGS | C7: ='Budget VS Actuals'!C13+'Budget VS Actuals'!D13+'Budget VS Actuals'!E13 -> 2237.6865 | D7: ='Budget VS Actuals'!C14+'Budget VS Actuals'!D14+'Budget VS Actuals'!E14 -> 2395.8248 | E7: =D7-C7 -> 158.1383 | F7: =IFERROR((D7-C7)/ABS(C7),0) -> 0.070670446 | G7: =IF(E7<=0,"Material cost came in below budget as a % of revenue — primarily a function of the modelled COGS ratio versus actual mix; likely driver based on model assumptions.","Material cost exceeded budget as a % of revenue, resulting in margin pressure; likely driver based on model assumptions rather than a confirmed operational cause.") -> Material cost exceeded budget as a % of revenue, resulting in margin pressure; likely driver based on model assumptions rather than a confirmed operational cause.
B8: Employee Cost | C8: ='Budget VS Actuals'!C19+'Budget VS Actuals'!D19+'Budget VS Actuals'!E19 -> 588.25778 | D8: ='Budget VS Actuals'!C20+'Budget VS Actuals'!D20+'Budget VS Actuals'!E20 -> 638.8866 | E8: =D8-C8 -> 50.628822 | F8: =IFERROR((D8-C8)/ABS(C8),0) -> 0.086065707 | G8: =IF(E8<=0,"Employee costs tracked below budget; variance is primarily attributable to the modelled cost ratio versus the derived actual run-rate.","Employee costs increased faster than budgeted relative to revenue.") -> Employee costs increased faster than budgeted relative to revenue.
B9: Other Operating Expenses | C9: ='Budget VS Actuals'!C25+'Budget VS Actuals'!D25+'Budget VS Actuals'!E25 -> 1620.5925 | D9: ='Budget VS Actuals'!C26+'Budget VS Actuals'!D26+'Budget VS Actuals'!E26 -> 1805.3387 | E9: =D9-C9 -> 184.74614 | F9: =IFERROR((D9-C9)/ABS(C9),0) -> 0.11399913 | G9: =IF(E9<=0,"Other operating expenses ran below budget as a % of revenue; variance is primarily attributable to the modelled cost assumption.","Other operating expenses exceeded the budgeted % of revenue.") -> Other operating expenses exceeded the budgeted % of revenue.
B10: EBITDA | C10: ='Budget VS Actuals'!C31+'Budget VS Actuals'!D31+'Budget VS Actuals'!E31 -> 1320.6964 | D10: ='Budget VS Actuals'!C32+'Budget VS Actuals'!D32+'Budget VS Actuals'!E32 -> 1538.13 | E10: =D10-C10 -> 217.43362 | F10: =IFERROR((D10-C10)/ABS(C10),0) -> 0.16463558 | G10: =IF(E10>=0,"EBITDA outperformed budget, driven through from the favourable revenue and cost-ratio variances above.","EBITDA fell short of budget, driven through from the unfavourable revenue/cost variances above.") -> EBITDA outperformed budget, driven through from the favourable revenue and cost-ratio variances above.
B11: Depreciation | C11: ='Budget VS Actuals'!C37+'Budget VS Actuals'!D37+'Budget VS Actuals'!E37 -> 173.26176 | D11: ='Budget VS Actuals'!C38+'Budget VS Actuals'!D38+'Budget VS Actuals'!E38 -> 187.8 | E11: =D11-C11 -> 14.53824 | F11: =IFERROR((D11-C11)/ABS(C11),0) -> 0.08390911 | G11: =IF(E11<=0,"Depreciation tracked below the budgeted % of revenue.","Depreciation exceeded the budgeted % of revenue.") -> Depreciation exceeded the budgeted % of revenue.
B12: Interest | C12: ='Budget VS Actuals'!C43+'Budget VS Actuals'!D43+'Budget VS Actuals'!E43 -> 50.40675 | D12: ='Budget VS Actuals'!C44+'Budget VS Actuals'!D44+'Budget VS Actuals'!E44 -> 42.18 | E12: =D12-C12 -> -8.22675 | F12: =IFERROR((D12-C12)/ABS(C12),0) -> -0.16320731 | G12: =IF(E12<=0,"Finance costs came in below the budgeted % of revenue.","Finance costs exceeded the budgeted % of revenue.") -> Finance costs came in below the budgeted % of revenue.
B13: Tax | C13: ='Budget VS Actuals'!C49+'Budget VS Actuals'!D49+'Budget VS Actuals'!E49 -> 263.20745 | D13: ='Budget VS Actuals'!C50+'Budget VS Actuals'!D50+'Budget VS Actuals'!E50 -> 349.27 | E13: =D13-C13 -> 86.062546 | F13: =IFERROR((D13-C13)/ABS(C13),0) -> 0.32697609 | G13: =IF(E13<=0,"Tax expense tracked below budget, consistent with the lower PBT-linked tax charge.","Tax expense exceeded budget, consistent with the higher PBT-linked tax charge.") -> Tax expense exceeded budget, consistent with the higher PBT-linked tax charge.
B14: PAT | C14: ='Budget VS Actuals'!C55+'Budget VS Actuals'!D55+'Budget VS Actuals'!E55 -> 871.30744 | D14: ='Budget VS Actuals'!C56+'Budget VS Actuals'!D56+'Budget VS Actuals'!E56 -> 975.12 | E14: =D14-C14 -> 103.81256 | F14: =IFERROR((D14-C14)/ABS(C14),0) -> 0.11914573 | G14: =IF(E14>=0,"PAT favourable overall, driven by the revenue and margin variances above.","PAT unfavourable overall, driven by the revenue and margin variances above.") -> PAT favourable overall, driven by the revenue and margin variances above.
B16: Part 2 — Budget vs Forecast (12-Month: Jul-2026 to Jun-2027)
B17: Line Item | C17: Budget (12-mo) | D17: Forecast (12-mo) | E17: Variance | F17: Variance % | H17: Driver / Explanation
B18: Revenue | C18: =SUM('Budget VS Forecast'!C7:N7) -> 26372.602 | D18: =SUM('Budget VS Forecast'!C8:N8) -> 26852.104 | E18: =D18-C18 -> 479.50186 | F18: =IFERROR((D18-C18)/ABS(C18),0) -> 0.018181818 | G18: =IF(E18>=0,"Revenue exceeded budget — attributable to the modelled revenue growth assumption; recent quarterly trends ran ahead of the budgeted growth rate.","Revenue fell short of budget — attributable to the modelled revenue growth assumption running ahead of the derived actual trend; likely driver based on model assumptions.") -> Revenue exceeded budget — attributable to the modelled revenue growth assumption; recent quarterly trends ran ahead of the budgeted growth rate.
B19: COGS | C19: =SUM('Budget VS Forecast'!C13:N13) -> 10232.57 | D19: =SUM('Budget VS Forecast'!C14:N14) -> 10606.581 | E19: =D19-C19 -> 374.01145 | F19: =IFERROR((D19-C19)/ABS(C19),0) -> 0.036551078 | G19: =IF(E19<=0,"Material cost came in below budget as a % of revenue — primarily a function of the modelled COGS ratio versus actual mix; likely driver based on model assumptions.","Material cost exceeded budget as a % of revenue, resulting in margin pressure; likely driver based on model assumptions rather than a confirmed operational cause.") -> Material cost exceeded budget as a % of revenue, resulting in margin pressure; likely driver based on model assumptions rather than a confirmed operational cause.
B20: Employee Cost | C20: =SUM('Budget VS Forecast'!C19:N19) -> 2690.0054 | D20: =SUM('Budget VS Forecast'!C20:N20) -> 2685.2104 | E20: =D20-C20 -> -4.7950186 | F20: =IFERROR((D20-C20)/ABS(C20),0) -> -0.0017825312 | G20: =IF(E20<=0,"Employee costs tracked below budget; variance is primarily attributable to the modelled cost ratio versus the derived actual run-rate.","Employee costs increased faster than budgeted relative to revenue.") -> Employee costs tracked below budget; variance is primarily attributable to the modelled cost ratio versus the derived actual run-rate.
B21: Other Operating Expenses | C21: =SUM('Budget VS Forecast'!C25:N25) -> 7410.7012 | D21: =SUM('Budget VS Forecast'!C26:N26) -> 7652.8496 | E21: =D21-C21 -> 242.14844 | F21: =IFERROR((D21-C21)/ABS(C21),0) -> 0.03267551 | G21: =IF(E21<=0,"Other operating expenses ran below budget as a % of revenue; variance is primarily attributable to the modelled cost assumption.","Other operating expenses exceeded the budgeted % of revenue.") -> Other operating expenses exceeded the budgeted % of revenue.
B22: EBITDA | C22: =SUM('Budget VS Forecast'!C31:N31) -> 6039.3259 | D22: =SUM('Budget VS Forecast'!C32:N32) -> 5907.4629 | E22: =D22-C22 -> -131.86301 | F22: =IFERROR((D22-C22)/ABS(C22),0) -> -0.021834061 | G22: =IF(E22>=0,"EBITDA outperformed budget, driven through from the favourable revenue and cost-ratio variances above.","EBITDA fell short of budget, driven through from the unfavourable revenue/cost variances above.") -> EBITDA fell short of budget, driven through from the unfavourable revenue/cost variances above.
B23: Depreciation | C23: =SUM('Budget VS Forecast'!C37:N37) -> 806.01936 | D23: =SUM('Budget VS Forecast'!C38:N38) -> 794.47334 | E23: =D23-C23 -> -11.546018 | F23: =IFERROR((D23-C23)/ABS(C23),0) -> -0.01432474 | G23: =IF(E23<=0,"Depreciation tracked below the budgeted % of revenue.","Depreciation exceeded the budgeted % of revenue.") -> Depreciation tracked below the budgeted % of revenue.
B24: Interest | C24: =SUM('Budget VS Forecast'!C43:N43) -> 165.12 | D24: =SUM('Budget VS Forecast'!C44:N44) -> 168.49573 | E24: =D24-C24 -> 3.375726 | F24: =IFERROR((D24-C24)/ABS(C24),0) -> 0.020444077 | G24: =IF(E24<=0,"Finance costs came in below the budgeted % of revenue.","Finance costs exceeded the budgeted % of revenue.") -> Finance costs exceeded the budgeted % of revenue.
B25: Tax | C25: =SUM('Budget VS Forecast'!C49:N49) -> 1215.5892 | D25: =SUM('Budget VS Forecast'!C50:N50) -> 1206.1278 | E25: =D25-C25 -> -9.4614022 | F25: =IFERROR((D25-C25)/ABS(C25),0) -> -0.0077833882 | G25: =IF(E25<=0,"Tax expense tracked below budget, consistent with the lower PBT-linked tax charge.","Tax expense exceeded budget, consistent with the higher PBT-linked tax charge.") -> Tax expense tracked below budget, consistent with the lower PBT-linked tax charge.
B26: PAT | C26: =SUM('Budget VS Forecast'!C55:N55) -> 4024.0193 | D26: =SUM('Budget VS Forecast'!C56:N56) -> 3926.3308 | E26: =D26-C26 -> -97.688502 | F26: =IFERROR((D26-C26)/ABS(C26),0) -> -0.02427635 | G26: =IF(E26>=0,"PAT favourable overall, driven by the revenue and margin variances above.","PAT unfavourable overall, driven by the revenue and margin variances above.") -> PAT unfavourable overall, driven by the revenue and margin variances above.

Sheet Model Checks
B2: ='Data Sheet'!B1&" — Model Checks" -> NESTLE INDIA LTD — Model Checks
B3: Consolidated integrity checks for this FP&A model. All values are formula-linked to the underlying sheets — nothing below is a hardcoded pass/fail.
B5: Check | C5: Result | D5: Detail / Basis | E5: Status
B6: Monthly seasonality allocation = 100% | C6: =Assumptions!E7 -> 1 | D6: Assumptions!E7 (Month1 % + Month2 % + Month3 %) | E6: =IF(ABS(Assumptions!E7-1)<0.0001,"OK","FLAG") -> OK
B7: Cost-mix split (COGS/Employee/Other) = 100% | C7: =Assumptions!E32 -> 1 | D7: Assumptions!E32 (COGS share + Employee share + Other share) | E7: =IF(ABS(Assumptions!E32-1)<0.0001,"OK","FLAG") -> OK
B8: Quarterly reconciliation (Derived Monthly Actuals = Reported Quarter) | C8: ='Monthly Actuals'!C45 -> ALL QUARTERS RECONCILE | D8: 'Monthly Actuals'!B33:I43 — 10 quarters checked (Revenue & Total Opex) | E8: =IF('Monthly Actuals'!C45="ALL QUARTERS RECONCILE","OK","FLAG") -> OK
B9: Monthly Budget 12-month Revenue > 0 | C9: ='Monthly Budget'!C23 -> 26372.602 | D9: 'Monthly Budget'!C23 (12-mo sum, Jul-26 to Jun-27) | E9: =IF('Monthly Budget'!C23>0,"OK","FLAG") -> OK
B10: Monthly Budget 12-month EBITDA Margin in plausible range (0-100%) | C10: ='Monthly Budget'!C24/'Monthly Budget'!C23 -> 0.229 | D10: EBITDA (12-mo) ÷ Revenue (12-mo) | E10: =IF(AND(('Monthly Budget'!C24/'Monthly Budget'!C23)>0,('Monthly Budget'!C24/'Monthly Budget'!C23)<1),"OK","FLAG") -> OK
B11: Rolling Forecast 12-month Revenue > 0 | C11: ='Rolling Forecast'!C25 -> 26852.104 | D11: 'Rolling Forecast'!C25 (12-mo sum) | E11: =IF('Rolling Forecast'!C25>0,"OK","FLAG") -> OK
B12: Rolling Forecast 12-month EBITDA Margin in plausible range (0-100%) | C12: ='Rolling Forecast'!C26/'Rolling Forecast'!C25 -> 0.22 | D12: EBITDA (12-mo) ÷ Revenue (12-mo) | E12: =IF(AND(('Rolling Forecast'!C26/'Rolling Forecast'!C25)>0,('Rolling Forecast'!C26/'Rolling Forecast'!C25)<1),"OK","FLAG") -> OK
B13: Budget vs Actual variance formula consistency (Revenue, Q1 FY26-27) | C13: ='Variance Analysis'!E6 -> 610.94688 | D13: 'Variance Analysis'!D6−C6 cross-checked against 'Budget VS Actuals' detail | E13: =IF(ROUND('Variance Analysis'!E6-('Variance Analysis'!D6-'Variance Analysis'!C6),2)=0,"OK","FLAG") -> OK
B14: Budget vs Forecast sheet is linked to Rolling Forecast (not manually duplicated) | C14: ='Budget VS Forecast'!C8 -> 2054.7717 | D14: 'Budget VS Forecast'!C8 formula references 'Rolling Forecast'!D8 directly (verified by formula inspection). | E14: ="OK" -> OK
B15: Workbook-wide formula error check (broken references, div-by-zero, type errors, unknown names) | C15: Verified | D15: Verified via LibreOffice recalculation (recalc.py) at last save — 0 errors across 3,182 formulas. | E15: ="OK" -> OK
B16: Budget Checks (Monthly Budget, representative month: Jul-2026)
B17: Budget COGS / Budget Revenue = Budget COGS assumption | C17: ='Monthly Budget'!F9/'Monthly Budget'!F7 -> 0.388 | D17: 'Monthly Budget'!F9 ÷ F7 vs Assumptions!D15 | E17: =IF(ROUND('Monthly Budget'!F9/'Monthly Budget'!F7-Assumptions!D15,4)=0,"OK","FLAG") -> OK
B18: Budget Employee Cost / Budget Revenue = Budget Employee assumption | C18: ='Monthly Budget'!F10/'Monthly Budget'!F7 -> 0.102 | D18: 'Monthly Budget'!F10 ÷ F7 vs Assumptions!D16 | E18: =IF(ROUND('Monthly Budget'!F10/'Monthly Budget'!F7-Assumptions!D16,4)=0,"OK","FLAG") -> OK
B19: Budget Other Opex / Budget Revenue = Budget Other Opex assumption | C19: ='Monthly Budget'!F11/'Monthly Budget'!F7 -> 0.281 | D19: 'Monthly Budget'!F11 ÷ F7 vs Assumptions!D17 | E19: =IF(ROUND('Monthly Budget'!F11/'Monthly Budget'!F7-Assumptions!D17,4)=0,"OK","FLAG") -> OK
B20: Budget Total Opex = COGS + Employee Cost + Other Opex | C20: ='Monthly Budget'!F8 -> 1555.9392 | D20: 'Monthly Budget'!F8 vs F9+F10+F11 | E20: =IF(ROUND('Monthly Budget'!F8-('Monthly Budget'!F9+'Monthly Budget'!F10+'Monthly Budget'!F11),2)=0,"OK","FLAG") -> OK
B21: Budget EBITDA = Revenue − Total Opex | C21: ='Monthly Budget'!F12 -> 462.14017 | D21: 'Monthly Budget'!F12 vs F7-F8 | E21: =IF(ROUND('Monthly Budget'!F12-('Monthly Budget'!F7-'Monthly Budget'!F8),2)=0,"OK","FLAG") -> OK
B22: Budget EBITDA Margin = EBITDA / Revenue | C22: ='Monthly Budget'!F13 -> 0.229 | D22: 'Monthly Budget'!F13 vs F12/F7 | E22: =IF(ROUND('Monthly Budget'!F13-('Monthly Budget'!F12/'Monthly Budget'!F7),4)=0,"OK","FLAG") -> OK
B23: Forecast Checks (Rolling Forecast, representative month: Jul-2026)
B24: Forecast COGS / Forecast Revenue = Forecast COGS assumption | C24: ='Rolling Forecast'!D10/'Rolling Forecast'!D8 -> 0.395 | D24: 'Rolling Forecast'!D10 ÷ D8 vs Assumptions!E15 | E24: =IF(ROUND('Rolling Forecast'!D10/'Rolling Forecast'!D8-Assumptions!E15,4)=0,"OK","FLAG") -> OK
B25: Forecast Employee Cost / Forecast Revenue = Forecast Employee assumption | C25: ='Rolling Forecast'!D11/'Rolling Forecast'!D8 -> 0.1 | D25: 'Rolling Forecast'!D11 ÷ D8 vs Assumptions!E16 | E25: =IF(ROUND('Rolling Forecast'!D11/'Rolling Forecast'!D8-Assumptions!E16,4)=0,"OK","FLAG") -> OK
B26: Forecast Other Opex / Forecast Revenue = Forecast Other Opex assumption | C26: ='Rolling Forecast'!D12/'Rolling Forecast'!D8 -> 0.285 | D26: 'Rolling Forecast'!D12 ÷ D8 vs Assumptions!E17 | E26: =IF(ROUND('Rolling Forecast'!D12/'Rolling Forecast'!D8-Assumptions!E17,4)=0,"OK","FLAG") -> OK
B27: Forecast Total Opex = sum of cost lines | C27: ='Rolling Forecast'!D9 -> 1602.7219 | D27: 'Rolling Forecast'!D9 vs D10+D11+D12 | E27: =IF(ROUND('Rolling Forecast'!D9-('Rolling Forecast'!D10+'Rolling Forecast'!D11+'Rolling Forecast'!D12),2)=0,"OK","FLAG") -> OK
B28: Forecast EBITDA = Revenue − Total Opex | C28: ='Rolling Forecast'!D13 -> 452.04978 | D28: 'Rolling Forecast'!D13 vs D8−D9 | E28: =IF(ROUND('Rolling Forecast'!D13-('Rolling Forecast'!D8-'Rolling Forecast'!D9),2)=0,"OK","FLAG") -> OK
B29: Forecast EBITDA Margin = EBITDA / Revenue | C29: ='Rolling Forecast'!D14 -> 0.22 | D29: 'Rolling Forecast'!D14 vs D13/D8 | E29: =IF(ROUND('Rolling Forecast'!D14-('Rolling Forecast'!D13/'Rolling Forecast'!D8),4)=0,"OK","FLAG") -> OK
B30: Profitability Checks (Budget & Forecast, representative month)
B31: Budget EBIT = EBITDA − Depreciation + Other Income | C31: ='Monthly Budget'!F16 -> 419.35279 | D31: 'Monthly Budget'!F16 vs F12−F15+F14 | E31: =IF(ROUND('Monthly Budget'!F16-('Monthly Budget'!F12-'Monthly Budget'!F15+'Monthly Budget'!F14),2)=0,"OK","FLAG") -> OK
B32: Budget PBT = EBIT − Interest | C32: ='Monthly Budget'!F18 -> 403.88665 | D32: 'Monthly Budget'!F18 vs F16−F17 | E32: =IF(ROUND('Monthly Budget'!F18-('Monthly Budget'!F16-'Monthly Budget'!F17),2)=0,"OK","FLAG") -> OK
B33: Budget PAT = PBT − Tax | C33: ='Monthly Budget'!F20 -> 310.18495 | D33: 'Monthly Budget'!F20 vs F18−F19 | E33: =IF(ROUND('Monthly Budget'!F20-('Monthly Budget'!F18-'Monthly Budget'!F19),2)=0,"OK","FLAG") -> OK
B34: Forecast EBIT = EBITDA − Depreciation + Other Income | C34: ='Rolling Forecast'!D17 -> 404.00245 | D34: 'Rolling Forecast'!D17 vs D13−D16+D15 | E34: =IF(ROUND('Rolling Forecast'!D17-('Rolling Forecast'!D13-'Rolling Forecast'!D16+'Rolling Forecast'!D15),2)=0,"OK","FLAG") -> OK
B35: Forecast PBT = EBIT − Interest | C35: ='Rolling Forecast'!D19 -> 385.68721 | D35: 'Rolling Forecast'!D19 vs D17−D18 | E35: =IF(ROUND('Rolling Forecast'!D19-('Rolling Forecast'!D17-'Rolling Forecast'!D18),2)=0,"OK","FLAG") -> OK
B36: Forecast PAT = PBT − Tax | C36: ='Rolling Forecast'!D21 -> 295.05072 | D36: 'Rolling Forecast'!D21 vs D19−D20 | E36: =IF(ROUND('Rolling Forecast'!D21-('Rolling Forecast'!D19-'Rolling Forecast'!D20),2)=0,"OK","FLAG") -> OK
B42: Known limitations (not checks, but disclosed for transparency)
B43: • Depreciation and Interest Budget/Forecast use a simplified YoY-growth methodology, not a full PP&E/debt driver schedule (no monthly/quarterly balance sheet data available). See Assumptions notes 6 and Section D.
B44: • "COGS" is defined narrowly (Material Cost only) on Assumptions/Monthly Actuals/Budget/Forecast, but broadly (incl. Employee Cost & Mfg. Overheads) on Historical FS. See Assumptions note 7.
B45: • The COGS / Employee / Other Opex split within Derived Monthly Actuals uses an analyst-assumed cost-mix ratio (Assumptions Section E), since the reported quarterly source does not report this split.
B46: • Rolling Forecast is a single 12-month forward-projection window, refreshed by manually advancing the base month — not a fully automated multi-period rolling engine.

Sheet Assumptions
B2: A. Monthly Seasonality (allocation of a reported quarter into its 3 calendar months)
B3: Assumption | E3: Value | F3: Unit | H3: Purpose / Methodology | I3: Source / Basis | J3: Model Impact (where it is used)
B4: Month 1 of quarter (%) | E4: 0.31 | F4: % of quarter | H4: Allocates the reported quarter into Month 1. | I4: Analyst assumption — modelled intra-quarter skew (not company data). | J4: Drives every Derived Monthly Actual, Month 1 of each quarter (Monthly Actuals!row 9+).
B5: Month 2 of quarter (%) | E5: 0.33 | F5: % of quarter | H5: Allocates the reported quarter into Month 2. | I5: Analyst assumption — modelled intra-quarter skew (not company data). | J5: Drives every Derived Monthly Actual, Month 2 of each quarter.
B6: Month 3 of quarter (%) | E6: 0.36 | F6: % of quarter | H6: Allocates the reported quarter into Month 3. | I6: Analyst assumption — modelled intra-quarter skew (not company data). | J6: Drives every Derived Monthly Actual, Month 3 of each quarter.
B7: Check: sum of 3 months | E7: =E4+E5+E6 -> 1 | F7: 1 | H7: Validates the 3 allocation % sum to 100%. | I7: Formula check (E4+E5+E6). | J7: If not 100%, Monthly Actuals will not reconcile — see Model Checks sheet.
B9: B. Revenue Assumptions
B10: Assumption | C10: Base (FY25-26) | D10: Budget | E10: Forecast | F10: Unit | H10: Purpose / Methodology | I10: Source / Basis | J10: Model Impact (where it is used)
B11: Revenue Growth, YoY | C11: ='Data Sheet'!K17/'Data Sheet'!J17-1 -> 0.14617881 | D11: 0.1 | E11: 0.12 | F11: % p.a. | H11: YoY growth applied to prior-year month to build Budget/Forecast revenue. | I11: Base = Historical trend (FY25-26 vs FY24-25 Sales, Data Sheet). Budget/Forecast = Analyst assumption. | J11: Monthly Budget!row 7; Rolling Forecast!row 8.
B13: C. Cost Assumptions (% of Revenue)
B14: Assumption | C14: Base (FY25-26) | D14: Budget | E14: Forecast Value | F14: Unit | H14: Purpose / Methodology | I14: Source / Basis | J14: Model Impact (where it is used)
B15: COGS / Material Cost % of Revenue | C15: ='Data Sheet'!K18/'Data Sheet'!K17 -> 0.39361336 | D15: 0.388 | E15: 0.395 | F15: % of revenue | H15: % of revenue → COGS / Material Cost line. | I15: Base = Historical average (Raw Material ÷ Sales). Budget/Forecast = Analyst assumption. | J15: Monthly Budget / Rolling Forecast Total Opex (row 8/9), split via Section E.
B16: Employee Cost % of Revenue | C16: ='Data Sheet'!K22/'Data Sheet'!K17 -> 0.098399886 | D16: 0.102 | E16: 0.1 | F16: % of revenue | H16: % of revenue → Employee Cost line. | I16: Base = Historical average (Employee Cost ÷ Sales). Budget/Forecast = Analyst assumption. | J16: Monthly Budget / Rolling Forecast Total Opex (row 8/9), split via Section E.
B17: Other Operating Expenses % of Revenue | C17: =('Data Sheet'!K20+'Data Sheet'!K21+'Data Sheet'!K23+'Data Sheet'!K24-'Data Sheet'!K19)/'Data Sheet'!K17 -> 0.27878996 | D17: 0.281 | E17: 0.285 | F17: % of revenue | H17: % of revenue → Other Operating Expenses line. | I17: Base = Historical average (computed from Data Sheet). Budget/Forecast = Analyst assumption. | J17: Monthly Budget / Rolling Forecast Total Opex (row 8/9), split via Section E.
B18: Implied EBITDA Margin | C18: =100%-(SUM(C15:C17)) -> 0.22919679 | D18: =1-(D15+D16+D17) -> 0.229 | E18: =1-(E15+E16+E17) -> 0.22 | H18: Check: 100% minus the 3 cost ratios (sense-check only). | I18: Formula check — not an independent assumption. | J18: Informational only — not referenced elsewhere.
B20: D. Profit, Tax and Other Income Assumptions
B21: Assumption | C21: Base (FY25-26) | D21: Budget | E21: Forecast Value | F21: Unit | H21: Purpose / Methodology | I21: Source / Basis | J21: Model Impact (where it is used)
B22: Depreciation — YoY Growth Assumption (Budget/Forecast driver; Base column = historical ratio, memo only) | C22: ='Data Sheet'!K26/('Data Sheet'!K62+'Data Sheet'!K63) -> 0.10286727 | D22: 0.104 | E22: 0.105 | F22: % YoY growth (Budget/Forecast); Base col = % of fixed assets (memo) | H22: SIMPLIFIED DRIVER: prior-year same-month Depreciation × (1+rate) — not a %-of-PP&E calc. | I22: Base (memo) = Historical ratio (Deprec.÷Fixed Assets). Budget/Forecast = Analyst YoY growth assumption. | J22: Monthly Budget!row 15; Rolling Forecast!row 16.
B23: Interest — YoY Growth Assumption (Budget/Forecast driver; Base column = historical ratio, memo only) | C23: ='Data Sheet'!K27/'Data Sheet'!K59 -> 0.35642561 | D23: 0.075 | E23: 0.085 | F23: % YoY growth (Budget/Forecast); Base col = % of debt (memo) | H23: SIMPLIFIED DRIVER: prior-year same-month Interest × (1+rate) — not a %-of-debt calc. | I23: Base (memo) = Historical ratio (Interest÷Borrowings). Budget/Forecast = Analyst YoY growth assumption. | J23: Monthly Budget!row 17; Rolling Forecast!row 18.
B24: Other Income % of Revenue | C24: ='Data Sheet'!K25/'Data Sheet'!K17 -> 0.0069200073 | D24: 0.0065 | E24: 0.007 | F24: % of revenue | H24: % of revenue → Other Income line. | I24: Base = Historical average. Budget/Forecast = Analyst assumption. | J24: Monthly Budget!row 14; Rolling Forecast!row 15.
B25: Effective Tax Rate | C25: ='Data Sheet'!K29/'Data Sheet'!K28 -> 0.23104791 | D25: 0.232 | E25: 0.235 | F25: % of EBT | H25: Effective tax rate applied to Budget/Forecast PBT. | I25: Base = Historical average (Tax ÷ PBT). Budget/Forecast = Analyst assumption. | J25: Monthly Budget!row 19; Rolling Forecast!row 20.
B27: E. Cost-Mix Split (used to break Monthly Actuals Total Opex into COGS / Employee / Other)
B28: Assumption | E28: Value | F28: Unit | H28: Purpose / Methodology | I28: Source / Basis | J28: Model Impact (where it is used)
B29: COGS share of Total Opex | E29: 0.495 | F29: % of opex | H29: Splits Total Opex into the COGS component (source doesn't report this split). | I29: Analyst assumption — based on FY25-26 historical cost mix. | J29: Monthly Actuals!row 11; Monthly Budget!row 9; Rolling Forecast!row 10.
B30: Employee share of Total Opex | E30: 0.132 | F30: % of opex | H30: Splits Total Opex into the Employee Cost component. | I30: Analyst assumption — based on FY25-26 historical cost mix. | J30: Monthly Actuals!row 12; Monthly Budget!row 10; Rolling Forecast!row 11.
B31: Other Opex share of Total Opex | E31: 0.373 | F31: % of opex | H31: Splits Total Opex into the Other Opex component. | I31: Analyst assumption — based on FY25-26 historical cost mix. | J31: Monthly Actuals!row 13; Monthly Budget!row 11; Rolling Forecast!row 12.
E32: =E29+E30+E31 -> 1
B33: Note.
B34: 1. Annual and quarterly figures in the Data Sheet are as reported in Nestlé India's standalone financial statements and are in ₹ Crore ..
B35: 2. Monthly figures shown on the Monthly Actuals sheet are NOT company-reported , they are Derived Monthly Actuals, allocated from reported quarterly totals using the seasonality % in Section A. They reconcile exactly to the reported quarterly figures (see Checks section on Monthly Actuals and Variance Analysis sheets).
B36: 3. Budget values represent an internally modelled (assumed), not company guidance.
B37: 4. Forecast values are model-generated estimates using a separate (editable) growth assumption from Budget, so that Budget vs Forecast variance is meaningful.
B38: 5. COGS / Employee / Other Opex are not split in the quarterly source, the split assumption in Section E should be treated as an approximation, not a reported figure.
B39: 6. Depreciation and Interest Budget/Forecast values are a simplified YoY-growth methodology (Section D, rows 22-23), not a driver-based % of a fixed-asset or debt balance — no quarterly/monthly PP&E or debt schedule is available. The historical ratios shown in the Base column of rows 22-23 are informational only.
B40: 7. "COGS" is defined differently across sheets: Monthly Actuals/Budget/Forecast/Assumptions define COGS as Raw Material Cost only (% of revenue, Section C). Historical FS defines its "COGS" line more broadly (Raw Material + Power & Fuel + Other Mfr. Exp + Employee Cost − Change in Inventory) — see note on Historical FS. Both are internally consistent within their own sheet; they are not directly comparable line-for-line.
B41: 8. Quarterly reconciliation of Derived Monthly Actuals to reported quarterly figures, and other model integrity checks, are consolidated on the Model Checks sheet.

Sheet Financials>

Sheet Common Size Statement
B2: ="Common Size Income Statement"& "-" &'Data Sheet'!B1 -> Common Size Income Statement-NESTLE INDIA LTD
B4: Particulars | C4: ='Data Sheet'!B16 -> 43100 | D4: ='Data Sheet'!C16 -> 43465 | E4: ='Data Sheet'!D16 -> 43830 | F4: ='Data Sheet'!E16 -> 44196 | G4: ='Data Sheet'!F16 -> 44561 | H4: ='Data Sheet'!G16 -> 44926 | I4: ='Data Sheet'!H16 -> 45291 | J4: ='Data Sheet'!I16 -> 45382 | ... L4: ='Data Sheet'!K16 -> 46112
B5: Note: FY2023-24 represents a 15-month transition period (change from Jan–Dec to Apr–Mar year-end) and should not be directly compared with normal 12-month years.
B6: Sales | C6: =IFERROR('Data Sheet'!B17/'Data Sheet'!B$17,0) -> 1 | D6: =IFERROR('Data Sheet'!C17/'Data Sheet'!C$17,0) -> 1 | E6: =IFERROR('Data Sheet'!D17/'Data Sheet'!D$17,0) -> 1 | F6: =IFERROR('Data Sheet'!E17/'Data Sheet'!E$17,0) -> 1 | G6: =IFERROR('Data Sheet'!F17/'Data Sheet'!F$17,0) -> 1 | H6: =IFERROR('Data Sheet'!G17/'Data Sheet'!G$17,0) -> 1 | I6: =IFERROR('Data Sheet'!H17/'Data Sheet'!H$17,0) -> 1 | J6: =IFERROR('Data Sheet'!I17/'Data Sheet'!I$17,0) -> 1 | ... L6: =IFERROR('Data Sheet'!K17/'Data Sheet'!K$17,0) -> 1
B7: Raw Material Cost | C7: =IFERROR('Data Sheet'!B18/'Data Sheet'!B$17,0) -> 0.36934443 | D7: =IFERROR('Data Sheet'!C18/'Data Sheet'!C$17,0) -> 0.339101 | E7: =IFERROR('Data Sheet'!D18/'Data Sheet'!D$17,0) -> 0.36550623 | F7: =IFERROR('Data Sheet'!E18/'Data Sheet'!E$17,0) -> 0.36717071 | G7: =IFERROR('Data Sheet'!F18/'Data Sheet'!F$17,0) -> 0.35963689 | H7: =IFERROR('Data Sheet'!G18/'Data Sheet'!G$17,0) -> 0.3941786 | I7: =IFERROR('Data Sheet'!H18/'Data Sheet'!H$17,0) -> 0.44298793 | J7: =IFERROR('Data Sheet'!I18/'Data Sheet'!I$17,0) -> 0.37718912 | ... L7: =IFERROR('Data Sheet'!K18/'Data Sheet'!K$17,0) -> 0.39361336
B8: Change in Inventory | C8: =IFERROR('Data Sheet'!B19/'Data Sheet'!B$17,0) -> 0.0079483696 | D8: =IFERROR('Data Sheet'!C19/'Data Sheet'!C$17,0) -> 0.00053222248 | E8: =IFERROR('Data Sheet'!D19/'Data Sheet'!D$17,0) -> 0.011657463 | F8: =IFERROR('Data Sheet'!E19/'Data Sheet'!E$17,0) -> 0.0051932468 | G8: =IFERROR('Data Sheet'!F19/'Data Sheet'!F$17,0) -> 0.0045852981 | H8: =IFERROR('Data Sheet'!G19/'Data Sheet'!G$17,0) -> 0.01481154 | I8: =IFERROR('Data Sheet'!H19/'Data Sheet'!H$17,0) -> 0.002091884 | J8: =IFERROR('Data Sheet'!I19/'Data Sheet'!I$17,0) -> 0.0018726001 | ... L8: =IFERROR('Data Sheet'!K19/'Data Sheet'!K$17,0) -> 0.007265511
B9: Power and Fuel | C9: =IFERROR('Data Sheet'!B20/'Data Sheet'!B$17,0) -> 0.028816336 | D9: =IFERROR('Data Sheet'!C20/'Data Sheet'!C$17,0) -> 0.030479257 | E9: =IFERROR('Data Sheet'!D20/'Data Sheet'!D$17,0) -> 0.027531147 | F9: =IFERROR('Data Sheet'!E20/'Data Sheet'!E$17,0) -> 0.023496576 | G9: =IFERROR('Data Sheet'!F20/'Data Sheet'!F$17,0) -> 0.027682745 | H9: =IFERROR('Data Sheet'!G20/'Data Sheet'!G$17,0) -> 0.033888344 | I9: =IFERROR('Data Sheet'!H20/'Data Sheet'!H$17,0) -> 0 | J9: =IFERROR('Data Sheet'!I20/'Data Sheet'!I$17,0) -> 0.027663895 | ... L9: =IFERROR('Data Sheet'!K20/'Data Sheet'!K$17,0) -> 0.025360404
B10: Other Mfr. Exp | C10: =IFERROR('Data Sheet'!B21/'Data Sheet'!B$17,0) -> 0.08969789 | D10: =IFERROR('Data Sheet'!C21/'Data Sheet'!C$17,0) -> 0.084115948 | E10: =IFERROR('Data Sheet'!D21/'Data Sheet'!D$17,0) -> 0.083156142 | F10: =IFERROR('Data Sheet'!E21/'Data Sheet'!E$17,0) -> 0.077929413 | G10: =IFERROR('Data Sheet'!F21/'Data Sheet'!F$17,0) -> 0.091548574 | H10: =IFERROR('Data Sheet'!G21/'Data Sheet'!G$17,0) -> 0.094897544 | I10: =IFERROR('Data Sheet'!H21/'Data Sheet'!H$17,0) -> 0 | J10: =IFERROR('Data Sheet'!I21/'Data Sheet'!I$17,0) -> 0.07933954 | ... L10: =IFERROR('Data Sheet'!K21/'Data Sheet'!K$17,0) -> 0.078441865
B11: Employee Cost | C11: =IFERROR('Data Sheet'!B22/'Data Sheet'!B$17,0) -> 0.10164742 | D11: =IFERROR('Data Sheet'!C22/'Data Sheet'!C$17,0) -> 0.0995504 | E11: =IFERROR('Data Sheet'!D22/'Data Sheet'!D$17,0) -> 0.10172044 | F11: =IFERROR('Data Sheet'!E22/'Data Sheet'!E$17,0) -> 0.11243046 | G11: =IFERROR('Data Sheet'!F22/'Data Sheet'!F$17,0) -> 0.10379096 | H11: =IFERROR('Data Sheet'!G22/'Data Sheet'!G$17,0) -> 0.096790192 | I11: =IFERROR('Data Sheet'!H22/'Data Sheet'!H$17,0) -> 0.096682578 | J11: =IFERROR('Data Sheet'!I22/'Data Sheet'!I$17,0) -> 0.095764144 | ... L11: =IFERROR('Data Sheet'!K22/'Data Sheet'!K$17,0) -> 0.098399886
B12: Selling and admin | C12: =IFERROR('Data Sheet'!B23/'Data Sheet'!B$17,0) -> 0.18222307 | D12: =IFERROR('Data Sheet'!C23/'Data Sheet'!C$17,0) -> 0.19002557 | E12: =IFERROR('Data Sheet'!D23/'Data Sheet'!D$17,0) -> 0.17997801 | F12: =IFERROR('Data Sheet'!E23/'Data Sheet'!E$17,0) -> 0.16830674 | G12: =IFERROR('Data Sheet'!F23/'Data Sheet'!F$17,0) -> 0.1968795 | H12: =IFERROR('Data Sheet'!G23/'Data Sheet'!G$17,0) -> 0.1889186 | I12: =IFERROR('Data Sheet'!H23/'Data Sheet'!H$17,0) -> 0 | J12: =IFERROR('Data Sheet'!I23/'Data Sheet'!I$17,0) -> 0.19831113 | ... L12: =IFERROR('Data Sheet'!K23/'Data Sheet'!K$17,0) -> 0.20647733
B13: Other Expenses | C13: =IFERROR('Data Sheet'!B24/'Data Sheet'!B$17,0) -> 0.026767303 | D13: =IFERROR('Data Sheet'!C24/'Data Sheet'!C$17,0) -> 0.025451039 | E13: =IFERROR('Data Sheet'!D24/'Data Sheet'!D$17,0) -> 0.017214142 | F13: =IFERROR('Data Sheet'!E24/'Data Sheet'!E$17,0) -> 0.016047155 | G13: =IFERROR('Data Sheet'!F24/'Data Sheet'!F$17,0) -> -0.0166262 | H13: =IFERROR('Data Sheet'!G24/'Data Sheet'!G$17,0) -> -0.013208293 | I13: =IFERROR('Data Sheet'!H24/'Data Sheet'!H$17,0) -> 0.22866001 | J13: =IFERROR('Data Sheet'!I24/'Data Sheet'!I$17,0) -> -0.015927349 | ... L13: =IFERROR('Data Sheet'!K24/'Data Sheet'!K$17,0) -> -0.024224128
B14: Other Income | C14: =IFERROR('Data Sheet'!B25/'Data Sheet'!B$17,0) -> 0.017675032 | D14: =IFERROR('Data Sheet'!C25/'Data Sheet'!C$17,0) -> 0.022928959 | E14: =IFERROR('Data Sheet'!D25/'Data Sheet'!D$17,0) -> 0.019959738 | F14: =IFERROR('Data Sheet'!E25/'Data Sheet'!E$17,0) -> 0.010925069 | G14: =IFERROR('Data Sheet'!F25/'Data Sheet'!F$17,0) -> -0.0076238468 | H14: =IFERROR('Data Sheet'!G25/'Data Sheet'!G$17,0) -> 0.0063478874 | I14: =IFERROR('Data Sheet'!H25/'Data Sheet'!H$17,0) -> 0.0060388052 | J14: =IFERROR('Data Sheet'!I25/'Data Sheet'!I$17,0) -> 0.0065176157 | ... L14: =IFERROR('Data Sheet'!K25/'Data Sheet'!K$17,0) -> 0.0069200073
B15: Depreciation | C15: =IFERROR('Data Sheet'!B26/'Data Sheet'!B$17,0) -> 0.034192176 | D15: =IFERROR('Data Sheet'!C26/'Data Sheet'!C$17,0) -> 0.029725644 | E15: =IFERROR('Data Sheet'!D26/'Data Sheet'!D$17,0) -> 0.029925862 | F15: =IFERROR('Data Sheet'!E26/'Data Sheet'!E$17,0) -> 0.027743758 | G15: =IFERROR('Data Sheet'!F26/'Data Sheet'!F$17,0) -> 0.026526754 | H15: =IFERROR('Data Sheet'!G26/'Data Sheet'!G$17,0) -> 0.023851036 | I15: =IFERROR('Data Sheet'!H26/'Data Sheet'!H$17,0) -> 0.022425142 | J15: =IFERROR('Data Sheet'!I26/'Data Sheet'!I$17,0) -> 0.023274271 | ... L15: =IFERROR('Data Sheet'!K26/'Data Sheet'!K$17,0) -> 0.030198319
B16: Interest | C16: =IFERROR('Data Sheet'!B27/'Data Sheet'!B$17,0) -> 0.0091811861 | D16: =IFERROR('Data Sheet'!C27/'Data Sheet'!C$17,0) -> 0.0099138614 | E16: =IFERROR('Data Sheet'!D27/'Data Sheet'!D$17,0) -> 0.010439085 | F16: =IFERROR('Data Sheet'!E27/'Data Sheet'!E$17,0) -> 0.0122981 | G16: =IFERROR('Data Sheet'!F27/'Data Sheet'!F$17,0) -> 0.013681949 | H16: =IFERROR('Data Sheet'!G27/'Data Sheet'!G$17,0) -> 0.0091477994 | I16: =IFERROR('Data Sheet'!H27/'Data Sheet'!H$17,0) -> 0.0062369617 | J16: =IFERROR('Data Sheet'!I27/'Data Sheet'!I$17,0) -> 0.0059641984 | ... L16: =IFERROR('Data Sheet'!K27/'Data Sheet'!K$17,0) -> 0.0068370864
B17: Profit before tax | C17: =IFERROR('Data Sheet'!B28/'Data Sheet'!B$17,0) -> 0.1837536 | D17: =IFERROR('Data Sheet'!C28/'Data Sheet'!C$17,0) -> 0.21509847 | E17: =IFERROR('Data Sheet'!D28/'Data Sheet'!D$17,0) -> 0.21614614 | F17: =IFERROR('Data Sheet'!E28/'Data Sheet'!E$17,0) -> 0.21069541 | G17: =IFERROR('Data Sheet'!F28/'Data Sheet'!F$17,0) -> 0.19384027 | H17: =IFERROR('Data Sheet'!G28/'Data Sheet'!G$17,0) -> 0.19269561 | I17: =IFERROR('Data Sheet'!H28/'Data Sheet'!H$17,0) -> 0.21113807 | J17: =IFERROR('Data Sheet'!I28/'Data Sheet'!I$17,0) -> 0.21681126 | ... L17: =IFERROR('Data Sheet'!K28/'Data Sheet'!K$17,0) -> 0.19908139
... B20: Dividend Amount | C20: =IFERROR('Data Sheet'!B31/'Data Sheet'!B$17,0) -> 0.082841472 | D20: =IFERROR('Data Sheet'!C31/'Data Sheet'!C$17,0) -> 0.09819372 | E20: =IFERROR('Data Sheet'!D31/'Data Sheet'!D$17,0) -> 0.26660091 | F20: =IFERROR('Data Sheet'!E31/'Data Sheet'!E$17,0) -> 0.14444911 | G20: =IFERROR('Data Sheet'!F31/'Data Sheet'!F$17,0) -> 0.13082244 | H20: =IFERROR('Data Sheet'!G31/'Data Sheet'!G$17,0) -> 0.12553974 | I20: =IFERROR('Data Sheet'!H31/'Data Sheet'!H$17,0) -> 0.087717436 | J20: =IFERROR('Data Sheet'!I31/'Data Sheet'!I$17,0) -> 0.12727449 | ... L20: =IFERROR('Data Sheet'!K31/'Data Sheet'!K$17,0) -> 0.099935218
B23: ="Common Size Balance Sheet"&"-"&'Data Sheet'!B1 -> Common Size Balance Sheet-NESTLE INDIA LTD
B25: Particulars | C25: ='Data Sheet'!B16 -> 43100 | D25: ='Data Sheet'!C16 -> 43465 | E25: ='Data Sheet'!D16 -> 43830 | F25: ='Data Sheet'!E16 -> 44196 | G25: ='Data Sheet'!F16 -> 44561 | H25: ='Data Sheet'!G16 -> 44926 | I25: ='Data Sheet'!H16 -> 45291 | J25: ='Data Sheet'!I16 -> 45382 | ... L25: ='Data Sheet'!K16 -> 46112
B27: Equity Share Capital | C27: ='Historical FS'!C39/'Historical FS'!C$43 -> 0.013095935 | D27: ='Historical FS'!D39/'Historical FS'!D$43 -> 0.011921247 | E27: ='Historical FS'!E39/'Historical FS'!E$43 -> 0.013442187 | F27: ='Historical FS'!F39/'Historical FS'!F$43 -> 0.01220548 | G27: ='Historical FS'!G39/'Historical FS'!G$43 -> 0.011709798 | H27: ='Historical FS'!H39/'Historical FS'!H$43 -> 0.010738701 | I27: ='Historical FS'!I39/'Historical FS'!I$43 -> 0.010738701 | J27: ='Historical FS'!J39/'Historical FS'!J$43 -> 0.009162734 | ... L27: ='Historical FS'!L39/'Historical FS'!L$43 -> 0.014436441
B28: Reserves | C28: ='Historical FS'!C40/'Historical FS'!C$43 -> 0.45149465 | D28: ='Historical FS'!D40/'Historical FS'!D$43 -> 0.44229533 | E28: ='Historical FS'!E40/'Historical FS'!E$43 -> 0.25407295 | F28: ='Historical FS'!F40/'Historical FS'!F$43 -> 0.24341591 | G28: ='Historical FS'!G40/'Historical FS'!G$43 -> 0.22466976 | H28: ='Historical FS'!H40/'Historical FS'!H$43 -> 0.2631494 | I28: ='Historical FS'!I40/'Historical FS'!I$43 -> 0.2631494 | J28: ='Historical FS'!J40/'Historical FS'!J$43 -> 0.30832001 | ... L28: ='Historical FS'!L40/'Historical FS'!L$43 -> 0.38304596
B29: Borrowings | C29: ='Historical FS'!C41/'Historical FS'!C$43 -> 0.004772777 | D29: ='Historical FS'!D41/'Historical FS'!D$43 -> 0.0043446652 | E29: ='Historical FS'!E41/'Historical FS'!E$43 -> 0.026340664 | F29: ='Historical FS'!F41/'Historical FS'!F$43 -> 0.018670258 | G29: ='Historical FS'!G41/'Historical FS'!G$43 -> 0.032360432 | H29: ='Historical FS'!H41/'Historical FS'!H$43 -> 0.030128949 | I29: ='Historical FS'!I41/'Historical FS'!I$43 -> 0.030128949 | J29: ='Historical FS'!J41/'Historical FS'!J$43 -> 0.032740477 | ... L29: ='Historical FS'!L41/'Historical FS'!L$43 -> 0.033252553
B30: Other Liabilities | C30: ='Historical FS'!C42/'Historical FS'!C$43 -> 0.53063664 | D30: ='Historical FS'!D42/'Historical FS'!D$43 -> 0.54143876 | E30: ='Historical FS'!E42/'Historical FS'!E$43 -> 0.7061442 | F30: ='Historical FS'!F42/'Historical FS'!F$43 -> 0.72570835 | G30: ='Historical FS'!G42/'Historical FS'!G$43 -> 0.73126001 | H30: ='Historical FS'!H42/'Historical FS'!H$43 -> 0.69598296 | I30: ='Historical FS'!I42/'Historical FS'!I$43 -> 0.69598296 | J30: ='Historical FS'!J42/'Historical FS'!J$43 -> 0.64977678 | ... L30: ='Historical FS'!L42/'Historical FS'!L$43 -> 0.56926505
B31: Total liablities | C31: ='Historical FS'!C43/'Historical FS'!C$43 -> 1 | D31: ='Historical FS'!D43/'Historical FS'!D$43 -> 1 | E31: ='Historical FS'!E43/'Historical FS'!E$43 -> 1 | F31: ='Historical FS'!F43/'Historical FS'!F$43 -> 1 | G31: ='Historical FS'!G43/'Historical FS'!G$43 -> 1 | H31: ='Historical FS'!H43/'Historical FS'!H$43 -> 1 | I31: ='Historical FS'!I43/'Historical FS'!I$43 -> 1 | J31: ='Historical FS'!J43/'Historical FS'!J$43 -> 1 | ... L31: ='Historical FS'!L43/'Historical FS'!L$43 -> 1
B33: Fixed Assests Net Block | C33: ='Historical FS'!C45/'Historical FS'!C$56 -> 0.3553342 | D33: ='Historical FS'!D45/'Historical FS'!D$56 -> 0.29680963 | E33: ='Historical FS'!E45/'Historical FS'!E$56 -> 0.32642821 | F33: ='Historical FS'!F45/'Historical FS'!F$56 -> 0.27588411 | G33: ='Historical FS'!G45/'Historical FS'!G$56 -> 0.36368991 | H33: ='Historical FS'!H45/'Historical FS'!H$56 -> 0.33898966 | I33: ='Historical FS'!I45/'Historical FS'!I$56 -> 0.33898966 | J33: ='Historical FS'!J45/'Historical FS'!J$56 -> 0.32882546 | ... L33: ='Historical FS'!L45/'Historical FS'!L$56 -> 0.47093958
B34: Capital Work in Progress | C34: ='Historical FS'!C46/'Historical FS'!C$56 -> 0.012788978 | D34: ='Historical FS'!D46/'Historical FS'!D$56 -> 0.013006795 | E34: ='Historical FS'!E46/'Historical FS'!E$56 -> 0.019977861 | F34: ='Historical FS'!F46/'Historical FS'!F$56 -> 0.080835674 | G34: ='Historical FS'!G46/'Historical FS'!G$56 -> 0.029903584 | H34: ='Historical FS'!H46/'Historical FS'!H$56 -> 0.039912059 | I34: ='Historical FS'!I46/'Historical FS'!I$56 -> 0.039912059 | J34: ='Historical FS'!J46/'Historical FS'!J$56 -> 0.16551364 | ... L34: ='Historical FS'!L46/'Historical FS'!L$56 -> 0.037955645
B35: Investments | C35: ='Historical FS'!C47/'Historical FS'!C$56 -> 0.26877362 | D35: ='Historical FS'!D47/'Historical FS'!D$56 -> 0.32869235 | E35: ='Historical FS'!E47/'Historical FS'!E$56 -> 0.24411887 | F35: ='Historical FS'!F47/'Historical FS'!F$56 -> 0.18529367 | G35: ='Historical FS'!G47/'Historical FS'!G$56 -> 0.093996573 | H35: ='Historical FS'!H47/'Historical FS'!H$56 -> 0.086597897 | I35: ='Historical FS'!I47/'Historical FS'!I$56 -> 0.086597897 | J35: ='Historical FS'!J47/'Historical FS'!J$56 -> 0.044081284 | ... L35: ='Historical FS'!L47/'Historical FS'!L$56 -> 0.052825561
B36: Other Assets | C36: ='Historical FS'!C48/'Historical FS'!C$56 -> 0.030494704 | D36: ='Historical FS'!D48/'Historical FS'!D$56 -> 0.027641913 | E36: ='Historical FS'!E48/'Historical FS'!E$56 -> 0.030906434 | F36: ='Historical FS'!F48/'Historical FS'!F$56 -> 0.033759382 | G36: ='Historical FS'!G48/'Historical FS'!G$56 -> 0.20952062 | H36: ='Historical FS'!H48/'Historical FS'!H$56 -> 0.1930037 | I36: ='Historical FS'!I48/'Historical FS'!I$56 -> 0.1930037 | J36: ='Historical FS'!J48/'Historical FS'!J$56 -> 0.16046283 | ... L36: ='Historical FS'!L48/'Historical FS'!L$56 -> 0.12087965
B37: Total Non Current Assets | C37: ='Historical FS'!C49/'Historical FS'!C$56 -> 0.6673915 | D37: ='Historical FS'!D49/'Historical FS'!D$56 -> 0.66615068 | E37: ='Historical FS'!E49/'Historical FS'!E$56 -> 0.62143138 | F37: ='Historical FS'!F49/'Historical FS'!F$56 -> 0.57577284 | G37: ='Historical FS'!G49/'Historical FS'!G$56 -> 0.69711068 | H37: ='Historical FS'!H49/'Historical FS'!H$56 -> 0.65850331 | I37: ='Historical FS'!I49/'Historical FS'!I$56 -> 0.65850331 | J37: ='Historical FS'!J49/'Historical FS'!J$56 -> 0.69888321 | ... L37: ='Historical FS'!L49/'Historical FS'!L$56 -> 0.68260043
B39: Receivables | C39: ='Historical FS'!C51/'Historical FS'!C$56 -> 0.012084063 | D39: ='Historical FS'!D51/'Historical FS'!D$56 -> 0.01540415 | E39: ='Historical FS'!E51/'Historical FS'!E$56 -> 0.017333199 | F39: ='Historical FS'!F51/'Historical FS'!F$56 -> 0.020877929 | G39: ='Historical FS'!G51/'Historical FS'!G$56 -> 0.020156349 | H39: ='Historical FS'!H51/'Historical FS'!H$56 -> 0.021371596 | I39: ='Historical FS'!I51/'Historical FS'!I$56 -> 0.021371596 | J39: ='Historical FS'!J51/'Historical FS'!J$56 -> 0.028552531 | ... L39: ='Historical FS'!L51/'Historical FS'!L$56 -> 0.024666153
B40: Inventory | C40: ='Historical FS'!C52/'Historical FS'!C$56 -> 0.12257507 | D40: ='Historical FS'!D52/'Historical FS'!D$56 -> 0.11937938 | E40: ='Historical FS'!E52/'Historical FS'!E$56 -> 0.17887644 | F40: ='Historical FS'!F52/'Historical FS'!F$56 -> 0.17930739 | G40: ='Historical FS'!G52/'Historical FS'!G$56 -> 0.19342056 | H40: ='Historical FS'!H52/'Historical FS'!H$56 -> 0.21481522 | I40: ='Historical FS'!I52/'Historical FS'!I$56 -> 0.21481522 | J40: ='Historical FS'!J52/'Historical FS'!J$56 -> 0.19855061 | ... L40: ='Historical FS'!L52/'Historical FS'!L$56 -> 0.19234763
B41: Cash & Bank | C41: ='Historical FS'!C53/'Historical FS'!C$56 -> 0.19794936 | D41: ='Historical FS'!D53/'Historical FS'!D$56 -> 0.19906579 | E41: ='Historical FS'!E53/'Historical FS'!E$56 -> 0.18235898 | F41: ='Historical FS'!F53/'Historical FS'!F$56 -> 0.22404183 | G41: ='Historical FS'!G53/'Historical FS'!G$56 -> 0.089312411 | H41: ='Historical FS'!H53/'Historical FS'!H$56 -> 0.10530988 | I41: ='Historical FS'!I53/'Historical FS'!I$56 -> 0.10530988 | J41: ='Historical FS'!J53/'Historical FS'!J$56 -> 0.074013642 | ... L41: ='Historical FS'!L53/'Historical FS'!L$56 -> 0.10038579
B42: Total Current Assets | C42: ='Historical FS'!C54/'Historical FS'!C$56 -> 0.3326085 | D42: ='Historical FS'!D54/'Historical FS'!D$56 -> 0.33384932 | E42: ='Historical FS'!E54/'Historical FS'!E$56 -> 0.37856862 | F42: ='Historical FS'!F54/'Historical FS'!F$56 -> 0.42422716 | G42: ='Historical FS'!G54/'Historical FS'!G$56 -> 0.30288932 | H42: ='Historical FS'!H54/'Historical FS'!H$56 -> 0.34149669 | I42: ='Historical FS'!I54/'Historical FS'!I$56 -> 0.34149669 | J42: ='Historical FS'!J54/'Historical FS'!J$56 -> 0.30111679 | ... L42: ='Historical FS'!L54/'Historical FS'!L$56 -> 0.31739957
B44: Total Assets | C44: ='Historical FS'!C56/'Historical FS'!C$56 -> 1 | D44: ='Historical FS'!D56/'Historical FS'!D$56 -> 1 | E44: ='Historical FS'!E56/'Historical FS'!E$56 -> 1 | F44: ='Historical FS'!F56/'Historical FS'!F$56 -> 1 | G44: ='Historical FS'!G56/'Historical FS'!G$56 -> 1 | H44: ='Historical FS'!H56/'Historical FS'!H$56 -> 1 | I44: ='Historical FS'!I56/'Historical FS'!I$56 -> 1 | J44: ='Historical FS'!J56/'Historical FS'!J$56 -> 1 | ... L44: ='Historical FS'!L56/'Historical FS'!L$56 -> 1

Sheet Ratio analysis
B2: ="Ratio Analysis -"&'Data Sheet'!B1 -> Ratio Analysis -NESTLE INDIA LTD
B3: Years | C3: ='Data Sheet'!B16 -> 43100 | D3: ='Data Sheet'!C16 -> 43465 | E3: ='Data Sheet'!D16 -> 43830 | F3: ='Data Sheet'!E16 -> 44196 | G3: ='Data Sheet'!F16 -> 44561 | H3: ='Data Sheet'!G16 -> 44926 | I3: ='Data Sheet'!H16 -> 45291 | J3: ='Data Sheet'!I16 -> 45382 | ... L3: ='Data Sheet'!K16 -> 46112 | M3: Trendlines | N3: Mean | O3: Median
B4: Note: FY2023-24 (period ended Mar-2024, shown above) was a 15-month transition year following Nestlé India's change from a January–December financial year to an April–March financial year. It is therefore not directly comparable with the normal 12-month years shown alongside it for growth and trend analysis.
B5: Sales growth | D5: =IFERROR('Historical FS'!D6/'Historical FS'!C6-1,0) -> 0.12814398 | E5: =IFERROR('Historical FS'!E6/'Historical FS'!D6-1,0) -> 0.095342212 | F5: =IFERROR('Historical FS'!F6/'Historical FS'!E6-1,0) -> 0.079322333 | G5: =IFERROR('Historical FS'!G6/'Historical FS'!F6-1,0) -> 0.10416156 | H5: =IFERROR('Historical FS'!H6/'Historical FS'!G6-1,0) -> 0.1462879 | I5: =IFERROR('Historical FS'!I6/'Historical FS'!H6-1,0) -> 0.13193734 | J5: =IFERROR('Historical FS'!J6/'Historical FS'!I6-1,0) -> 0.27541082 | K5: =IFERROR('Historical FS'!K6/'Historical FS'!J6-1,0) -> -0.17185984 | L5: =IFERROR('Historical FS'!L6/'Historical FS'!K6-1,0) -> 0.14617881 | N5: =IFERROR(AVERAGE(D5:L5),0) -> 0.10388057 | O5: =IFERROR(MEDIAN(D5:L5),0) -> 0.12814398
B6: EBITDA growth | D6: =IFERROR('Historical FS'!D14/'Historical FS'!C14-1,0) -> 0.2485631 | E6: =IFERROR('Historical FS'!E14/'Historical FS'!D14-1,0) -> 0.11775065 | F6: =IFERROR('Historical FS'!F14/'Historical FS'!E14-1,0) -> 0.094200719 | G6: =IFERROR('Historical FS'!G14/'Historical FS'!F14-1,0) -> 0.11272841 | H6: =IFERROR('Historical FS'!H14/'Historical FS'!G14-1,0) -> 0.040391309 | I6: =IFERROR('Historical FS'!I14/'Historical FS'!H14-1,0) -> 0.20632492 | J6: =IFERROR('Historical FS'!J14/'Historical FS'!I14-1,0) -> 0.30689624 | K6: =IFERROR('Historical FS'!K14/'Historical FS'!J14-1,0) -> -0.18342769 | L6: =IFERROR('Historical FS'!L14/'Historical FS'!K14-1,0) -> 0.1122601 | N6: =IFERROR(AVERAGE(D6:L6),0) -> 0.11729864 | O6: =IFERROR(MEDIAN(D6:L6),0) -> 0.11272841
B7: EBT growth | D7: =IFERROR('Historical FS'!D22/'Historical FS'!C22-1,0) -> 0.32058392 | E7: =IFERROR('Historical FS'!E22/'Historical FS'!D22-1,0) -> 0.10067725 | F7: =IFERROR('Historical FS'!F22/'Historical FS'!E22-1,0) -> 0.052104178 | G7: =IFERROR('Historical FS'!G22/'Historical FS'!F22-1,0) -> 0.015831257 | H7: =IFERROR('Historical FS'!H22/'Historical FS'!G22-1,0) -> 0.13951885 | I7: =IFERROR('Historical FS'!I22/'Historical FS'!H22-1,0) -> 0.24027248 | J7: =IFERROR('Historical FS'!J22/'Historical FS'!I22-1,0) -> 0.30968058 | K7: =IFERROR('Historical FS'!K22/'Historical FS'!J22-1,0) -> -0.1590888 | L7: =IFERROR('Historical FS'!L22/'Historical FS'!K22-1,0) -> 0.036465676 | N7: =IFERROR(AVERAGE(D7:L7),0) -> 0.11733838 | O7: =IFERROR(MEDIAN(D7:L7),0) -> 0.10067725
B8: Net profit growth | D8: =IFERROR('Historical FS'!D26/'Historical FS'!C26-1,0) -> 0.31157616 | E8: =IFERROR('Historical FS'!E26/'Historical FS'!D26-1,0) -> 0.22496935 | F8: =IFERROR('Historical FS'!F26/'Historical FS'!E26-1,0) -> 0.057908801 | G8: =IFERROR('Historical FS'!G26/'Historical FS'!F26-1,0) -> 0.017277892 | H8: =IFERROR('Historical FS'!H26/'Historical FS'!G26-1,0) -> 0.12845011 | I8: =IFERROR('Historical FS'!I26/'Historical FS'!H26-1,0) -> 0.25440072 | J8: =IFERROR('Historical FS'!J26/'Historical FS'!I26-1,0) -> 0.31152811 | K8: =IFERROR('Historical FS'!K26/'Historical FS'!J26-1,0) -> -0.1572248 | L8: =IFERROR('Historical FS'!L26/'Historical FS'!K26-1,0) -> 0.069422236 | N8: =IFERROR(AVERAGE(D8:L8),0) -> 0.13536762 | O8: =IFERROR(MEDIAN(D8:L8),0) -> 0.12845011
B9: Dividend growth | D9: =IFERROR('Historical FS'!D33/'Historical FS'!C33-1,0) -> 0.33721253 | E9: =IFERROR('Historical FS'!E33/'Historical FS'!D33-1,0) -> 1.9739094 | F9: =IFERROR('Historical FS'!F33/'Historical FS'!E33-1,0) -> -0.41520397 | G9: =IFERROR('Historical FS'!G33/'Historical FS'!F33-1,0) -> 0 | H9: =IFERROR('Historical FS'!H33/'Historical FS'!G33-1,0) -> 0.1 | I9: =IFERROR('Historical FS'!I33/'Historical FS'!H33-1,0) -> -0.20908997 | J9: =IFERROR('Historical FS'!J33/'Historical FS'!I33-1,0) -> 0.85028222 | K9: =IFERROR('Historical FS'!K33/'Historical FS'!J33-1,0) -> -0.1614896 | L9: =IFERROR('Historical FS'!L33/'Historical FS'!K33-1,0) -> -0.11115721 | N9: =IFERROR(AVERAGE(D9:L9),0) -> 0.26271816 | O9: =IFERROR(MEDIAN(D9:L9),0) -> 0
B11: Gross margin | C11: =IFERROR('Historical FS'!C11,0) -> 0.4184423 | D11: =IFERROR('Historical FS'!D11,0) -> 0.44728562 | E11: =IFERROR('Historical FS'!E11,0) -> 0.4337435 | F11: =IFERROR('Historical FS'!F11,0) -> 0.42416609 | G11: =IFERROR('Historical FS'!G11,0) -> 0.42192612 | H11: =IFERROR('Historical FS'!H11,0) -> 0.39505686 | I11: =IFERROR('Historical FS'!I11,0) -> 0.46242138 | J11: =IFERROR('Historical FS'!J11,0) -> 0.4219159 | ... L11: =IFERROR('Historical FS'!L11,0) -> 0.41144999 | N11: =IFERROR(AVERAGE(D11:L11),0) -> 0.42657286 | O11: =IFERROR(MEDIAN(D11:L11),0) -> 0.42192612
B12: EBITDA margin | C12: =IFERROR('Historical FS'!C15,0) -> 0.20945193 | D12: =IFERROR('Historical FS'!D15,0) -> 0.23180902 | E12: =IFERROR('Historical FS'!E15,0) -> 0.23655135 | F12: =IFERROR('Historical FS'!F15,0) -> 0.2398122 | G12: =IFERROR('Historical FS'!G15,0) -> 0.24167282 | H12: =IFERROR('Historical FS'!H15,0) -> 0.21934656 | I12: =IFERROR('Historical FS'!I15,0) -> 0.23376137 | J12: =IFERROR('Historical FS'!J15,0) -> 0.23953211 | ... L12: =IFERROR('Historical FS'!L15,0) -> 0.22919679 | N12: =IFERROR(AVERAGE(D12:L12),0) -> 0.2342076 | O12: =IFERROR(MEDIAN(D12:L12),0) -> 0.23618622
B13: EBIT margin | C13: =IFERROR(('Historical FS'!C14-'Historical FS'!C18)/'Historical FS'!C6,) -> 0.17525975 | D13: =IFERROR(('Historical FS'!D14-'Historical FS'!D18)/'Historical FS'!D6,) -> 0.20208337 | E13: =IFERROR(('Historical FS'!E14-'Historical FS'!E18)/'Historical FS'!E6,) -> 0.20662549 | F13: =IFERROR(('Historical FS'!F14-'Historical FS'!F18)/'Historical FS'!F6,) -> 0.21206844 | G13: =IFERROR(('Historical FS'!G14-'Historical FS'!G18)/'Historical FS'!G6,) -> 0.21514607 | H13: =IFERROR(('Historical FS'!H14-'Historical FS'!H18)/'Historical FS'!H6,) -> 0.19549552 | I13: =IFERROR(('Historical FS'!I14-'Historical FS'!I18)/'Historical FS'!I6,) -> 0.21133622 | J13: =IFERROR(('Historical FS'!J14-'Historical FS'!J18)/'Historical FS'!J6,) -> 0.21625784 | ... L13: =IFERROR(('Historical FS'!L14-'Historical FS'!L18)/'Historical FS'!L6,) -> 0.19899847 | N13: =IFERROR(AVERAGE(D13:L13),0) -> 0.20749678 | O13: =IFERROR(MEDIAN(D13:L13),0) -> 0.20945957
B14: EBT margin | C14: =IFERROR('Historical FS'!C23,0) -> 0.1837536 | D14: =IFERROR('Historical FS'!D23,0) -> 0.21509847 | E14: =IFERROR('Historical FS'!E23,0) -> 0.21614614 | F14: =IFERROR('Historical FS'!F23,0) -> 0.21069541 | G14: =IFERROR('Historical FS'!G23,0) -> 0.19384027 | H14: =IFERROR('Historical FS'!H23,0) -> 0.19269561 | I14: =IFERROR('Historical FS'!I23,0) -> 0.21113807 | J14: =IFERROR('Historical FS'!J23,0) -> 0.21681126 | ... L14: =IFERROR('Historical FS'!L23,0) -> 0.19908139 | N14: =IFERROR(AVERAGE(D14:L14),0) -> 0.20840682 | O14: =IFERROR(MEDIAN(D14:L14),0) -> 0.21113807
B15: Net profit margin | C15: =IFERROR('Historical FS'!C27,0) -> 0.12240149 | D15: =IFERROR('Historical FS'!D27,0) -> 0.14230354 | E15: =IFERROR('Historical FS'!E27,0) -> 0.15914431 | F15: =IFERROR('Historical FS'!F27,0) -> 0.15598692 | G15: =IFERROR('Historical FS'!G27,0) -> 0.1437127 | H15: =IFERROR('Historical FS'!H27,0) -> 0.14147634 | I15: =IFERROR('Historical FS'!I27,0) -> 0.15678255 | J15: =IFERROR('Historical FS'!J27,0) -> 0.16122234 | ... L15: =IFERROR('Historical FS'!L27,0) -> 0.15308405 | N15: =IFERROR(AVERAGE(D15:L15),0) -> 0.15308714 | O15: =IFERROR(MEDIAN(D15:L15),0) -> 0.15598692
B17: Sales expense% sales | C17: =IFERROR('Historical FS'!C12/'Historical FS'!C6,0) -> 0.20899037 | D17: =IFERROR('Historical FS'!D12/'Historical FS'!D6,0) -> 0.2154766 | E17: =IFERROR('Historical FS'!E12/'Historical FS'!E6,0) -> 0.19719215 | F17: =IFERROR('Historical FS'!F12/'Historical FS'!F6,0) -> 0.18435389 | G17: =IFERROR('Historical FS'!G12/'Historical FS'!G6,0) -> 0.1802533 | H17: =IFERROR('Historical FS'!H12/'Historical FS'!H6,0) -> 0.17571031 | I17: =IFERROR('Historical FS'!I12/'Historical FS'!I6,0) -> 0.22866001 | J17: =IFERROR('Historical FS'!J12/'Historical FS'!J6,0) -> 0.18238379 | ... L17: =IFERROR('Historical FS'!L12/'Historical FS'!L6,0) -> 0.1822532 | N17: =IFERROR(AVERAGE(D17:L17),0) -> 0.19236525 | O17: =IFERROR(MEDIAN(D17:L17),0) -> 0.18435389
B18: Depreciation% sales | C18: =IFERROR('Historical FS'!C19,0) -> 0.034192176 | D18: =IFERROR('Historical FS'!D19,0) -> 0.029725644 | E18: =IFERROR('Historical FS'!E19,0) -> 0.029925862 | F18: =IFERROR('Historical FS'!F19,0) -> 0.027743758 | G18: =IFERROR('Historical FS'!G19,0) -> 0.026526754 | H18: =IFERROR('Historical FS'!H19,0) -> 0.023851036 | I18: =IFERROR('Historical FS'!I19,0) -> 0.022425142 | J18: =IFERROR('Historical FS'!J19,0) -> 0.023274271 | ... L18: =IFERROR('Historical FS'!L19,0) -> 0.030198319 | N18: =IFERROR(AVERAGE(D18:L18),0) -> 0.026710826 | O18: =IFERROR(MEDIAN(D18:L18),0) -> 0.026726649
B19: Operating income% sales | C19: =IFERROR('Ratio analysis'!C13,0) -> 0.17525975 | D19: =IFERROR('Ratio analysis'!D13,0) -> 0.20208337 | E19: =IFERROR('Ratio analysis'!E13,0) -> 0.20662549 | F19: =IFERROR('Ratio analysis'!F13,0) -> 0.21206844 | G19: =IFERROR('Ratio analysis'!G13,0) -> 0.21514607 | H19: =IFERROR('Ratio analysis'!H13,0) -> 0.19549552 | I19: =IFERROR('Ratio analysis'!I13,0) -> 0.21133622 | J19: =IFERROR('Ratio analysis'!J13,0) -> 0.21625784 | ... L19: =IFERROR('Ratio analysis'!L13,0) -> 0.19899847 | N19: =IFERROR(AVERAGE(D19:L19),0) -> 0.20749678 | O19: =IFERROR(MEDIAN(D19:L19),0) -> 0.20945957
B21: Return on capital employed | C21: =IFERROR(('Historical FS'!C14-'Historical FS'!C18)/SUM('Historical FS'!C39:C41),0) -> 0.50764383 | D21: =IFERROR(('Historical FS'!D14-'Historical FS'!D18)/SUM('Historical FS'!D39:D41),0) -> 0.61527469 | E21: =IFERROR(('Historical FS'!E14-'Historical FS'!E18)/SUM('Historical FS'!E39:E41),0) -> 1.2125049 | F21: =IFERROR(('Historical FS'!F14-'Historical FS'!F18)/SUM('Historical FS'!F39:F41),0) -> 1.3065723 | G21: =IFERROR(('Historical FS'!G14-'Historical FS'!G18)/SUM('Historical FS'!G39:G41),0) -> 1.4331719 | H21: =IFERROR(('Historical FS'!H14-'Historical FS'!H18)/SUM('Historical FS'!H39:H41),0) -> 1.2101301 | I21: =IFERROR(('Historical FS'!I14-'Historical FS'!I18)/SUM('Historical FS'!I39:I41),0) -> 1.4807835 | J21: =IFERROR(('Historical FS'!J14-'Historical FS'!J18)/SUM('Historical FS'!J39:J41),0) -> 1.4314162 | ... L21: =IFERROR(('Historical FS'!L14-'Historical FS'!L18)/SUM('Historical FS'!L39:L41),0) -> 0.80087079 | N21: =IFERROR(AVERAGE(D21:L21),0) -> 1.1435023 | O21: =IFERROR(MEDIAN(D21:L21),0) -> 1.2125049
B22: Retained earning | C22: =IFERROR('Historical FS'!C35,0) -> 0.32319885 | D22: =IFERROR('Historical FS'!D35,0) -> 0.30996994 | E22: =IFERROR('Historical FS'!E35,0) -> 0 | F22: =IFERROR('Historical FS'!F35,0) -> 0.073966472 | G22: =IFERROR('Historical FS'!G35,0) -> 0.089694629 | H22: =IFERROR('Historical FS'!H35,0) -> 0.11264495 | I22: =IFERROR('Historical FS'!I35,0) -> 0.4405153 | J22: =IFERROR('Historical FS'!J35,0) -> 0.21056539 | ... L22: =IFERROR('Historical FS'!L35,0) -> 0.34718727 | N22: =IFERROR(AVERAGE(D22:L22),0) -> 0.19990047 | O22: =IFERROR(MEDIAN(D22:L22),0) -> 0.21056539
B23: Return on equity% | C23: =IFERROR('Historical FS'!C26/SUM('Historical FS'!C39:C40),) -> 0.3581809 | D23: =IFERROR('Historical FS'!D26/SUM('Historical FS'!D39:D40),) -> 0.43740983 | E23: =IFERROR('Historical FS'!E26/SUM('Historical FS'!E39:E40),) -> 1.0258329 | F23: =IFERROR('Historical FS'!F26/SUM('Historical FS'!F39:F40),) -> 1.0312429 | G23: =IFERROR('Historical FS'!G26/SUM('Historical FS'!G39:G40),) -> 1.0883846 | H23: =IFERROR('Historical FS'!H26/SUM('Historical FS'!H39:H40),) -> 0.97208408 | I23: =IFERROR('Historical FS'!I26/SUM('Historical FS'!I39:I40),) -> 1.219383 | J23: =IFERROR('Historical FS'!J26/SUM('Historical FS'!J39:J40),) -> 1.1771833 | ... L23: =IFERROR('Historical FS'!L26/SUM('Historical FS'!L39:L40),) -> 0.66762851 | N23: =IFERROR(AVERAGE(D23:L23),0) -> 0.93602181 | O23: =IFERROR(MEDIAN(D23:L23),0) -> 1.0258329
B24: Self sustained growth rate | C24: =C22*C23 -> 0.11576365 | D24: =D22*D23 -> 0.1355839 | E24: =E22*E23 -> 0 | F24: =F22*F23 -> 0.076277398 | G24: =G22*G23 -> 0.097622253 | H24: =H22*H23 -> 0.10950036 | I24: =I22*I23 -> 0.53715685 | J24: =J22*J23 -> 0.24787407 | ... L24: =L22*L23 -> 0.23179212 | N24: =IFERROR(AVERAGE(D24:L24),0) -> 0.17872645 | O24: =IFERROR(MEDIAN(D24:L24),0) -> 0.1355839
B25: Interest coverage ratio | C25: =IFERROR(('Historical FS'!C14-'Historical FS'!C18)/'Historical FS'!C20,0) -> 19.08901 | D25: =IFERROR(('Historical FS'!D14-'Historical FS'!D18)/'Historical FS'!D20,0) -> 20.383921 | E25: =IFERROR(('Historical FS'!E14-'Historical FS'!E18)/'Historical FS'!E20,0) -> 19.793448 | F25: =IFERROR(('Historical FS'!F14-'Historical FS'!F18)/'Historical FS'!F20,0) -> 17.244 | G25: =IFERROR(('Historical FS'!G14-'Historical FS'!G18)/'Historical FS'!G20,0) -> 15.724812 | H25: =IFERROR(('Historical FS'!H14-'Historical FS'!H18)/'Historical FS'!H20,0) -> 21.370771 | I25: =IFERROR(('Historical FS'!I14-'Historical FS'!I18)/'Historical FS'!I20,0) -> 33.884483 | J25: =IFERROR(('Historical FS'!J14-'Historical FS'!J18)/'Historical FS'!J20,0) -> 36.259331 | ... L25: =IFERROR(('Historical FS'!L14-'Historical FS'!L18)/'Historical FS'!L20,0) -> 29.105742 | N25: =IFERROR(AVERAGE(D25:L25),0) -> 24.986646 | O25: =IFERROR(MEDIAN(D25:L25),0) -> 21.370771
B27: Debtor turnover ratio | C27: =IFERROR('Historical FS'!C6/'Historical FS'!C51,0) -> 112.50534 | D27: =IFERROR('Historical FS'!D6/'Historical FS'!D51,0) -> 90.635444 | E27: =IFERROR('Historical FS'!E6/'Historical FS'!E51,0) -> 99.484437 | F27: =IFERROR('Historical FS'!F6/'Historical FS'!F51,0) -> 80.943612 | G27: =IFERROR('Historical FS'!G6/'Historical FS'!G51,0) -> 88.814786 | H27: =IFERROR('Historical FS'!H6/'Historical FS'!H51,0) -> 88.055448 | I27: =IFERROR('Historical FS'!I6/'Historical FS'!I51,0) -> 99.67325 | J27: =IFERROR('Historical FS'!J6/'Historical FS'!J51,0) -> 81.188478 | ... L27: =IFERROR('Historical FS'!L6/'Historical FS'!L51,0) -> 70.278326 | N27: =IFERROR(AVERAGE(D27:L27),0) -> 83.855831 | O27: =IFERROR(MEDIAN(D27:L27),0) -> 88.055448
B28: Creditor turnover ratio | C28: =IFERROR('Historical FS'!C6/'Historical FS'!C41,0) -> 284.84917 | D28: =IFERROR('Historical FS'!D6/'Historical FS'!D41,0) -> 321.35088 | E28: =IFERROR('Historical FS'!E6/'Historical FS'!E41,0) -> 65.464698 | F28: =IFERROR('Historical FS'!F6/'Historical FS'!F41,0) -> 90.514815 | G28: =IFERROR('Historical FS'!G6/'Historical FS'!G41,0) -> 55.320086 | H28: =IFERROR('Historical FS'!H6/'Historical FS'!H41,0) -> 62.461038 | I28: =IFERROR('Historical FS'!I6/'Historical FS'!I41,0) -> 70.701981 | J28: =IFERROR('Historical FS'!J6/'Historical FS'!J41,0) -> 70.803384 | ... L28: =IFERROR('Historical FS'!L6/'Historical FS'!L41,0) -> 52.131214 | N28: =IFERROR(AVERAGE(D28:L28),0) -> 89.562333 | O28: =IFERROR(MEDIAN(D28:L28),0) -> 65.464698
B29: Inventory turnover ratio | C29: =IFERROR('Historical FS'!C6/'Historical FS'!C52,0) -> 11.091338 | D29: =IFERROR('Historical FS'!D6/'Historical FS'!D52,0) -> 11.695169 | E29: =IFERROR('Historical FS'!E6/'Historical FS'!E52,0) -> 9.640082 | F29: =IFERROR('Historical FS'!F6/'Historical FS'!F52,0) -> 9.4247924 | G29: =IFERROR('Historical FS'!G6/'Historical FS'!G52,0) -> 9.2553857 | H29: =IFERROR('Historical FS'!H6/'Historical FS'!H52,0) -> 8.7604847 | I29: =IFERROR('Historical FS'!I6/'Historical FS'!I52,0) -> 9.9163197 | J29: =IFERROR('Historical FS'!J6/'Historical FS'!J52,0) -> 11.675293 | ... L29: =IFERROR('Historical FS'!L6/'Historical FS'!L52,0) -> 9.0123072 | N29: =IFERROR(AVERAGE(D29:L29),0) -> 9.607528 | O29: =IFERROR(MEDIAN(D29:L29),0) -> 9.4247924
B30: Fixed asset turnover ratio | C30: =IFERROR('Historical FS'!C6/'Historical FS'!C45,0) -> 3.8260364 | D30: =IFERROR('Historical FS'!D6/'Historical FS'!D45,0) -> 4.7038973 | E30: =IFERROR('Historical FS'!E6/'Historical FS'!E45,0) -> 5.2825813 | F30: =IFERROR('Historical FS'!F6/'Historical FS'!F45,0) -> 6.1255248 | G30: =IFERROR('Historical FS'!G6/'Historical FS'!G45,0) -> 4.9222752 | H30: =IFERROR('Historical FS'!H6/'Historical FS'!H45,0) -> 5.5514538 | I30: =IFERROR('Historical FS'!I6/'Historical FS'!I45,0) -> 6.2838979 | J30: =IFERROR('Historical FS'!J6/'Historical FS'!J45,0) -> 7.0497479 | ... L30: =IFERROR('Historical FS'!L6/'Historical FS'!L45,0) -> 3.6809307 | N30: =IFERROR(AVERAGE(D30:L30),0) -> 5.2545587 | O30: =IFERROR(MEDIAN(D30:L30),0) -> 5.2825813
B31: Capital turnover ratio | C31: =IFERROR('Historical FS'!C6/SUM('Historical FS'!C39:C40),0) -> 2.9262788 | D31: =IFERROR('Historical FS'!D6/SUM('Historical FS'!D39:D40),0) -> 3.0737804 | E31: =IFERROR('Historical FS'!E6/SUM('Historical FS'!E39:E40),0) -> 6.4459291 | F31: =IFERROR('Historical FS'!F6/SUM('Historical FS'!F39:F40),0) -> 6.6110858 | G31: =IFERROR('Historical FS'!G6/SUM('Historical FS'!G39:G40),0) -> 7.5733361 | H31: =IFERROR('Historical FS'!H6/SUM('Historical FS'!H39:H40),0) -> 6.8710012 | I31: =IFERROR('Historical FS'!I6/SUM('Historical FS'!I39:I40),0) -> 7.7775428 | J31: =IFERROR('Historical FS'!J6/SUM('Historical FS'!J39:J40),0) -> 7.3016142 | ... L31: =IFERROR('Historical FS'!L6/SUM('Historical FS'!L39:L40),0) -> 4.3611892 | N31: =IFERROR(AVERAGE(D31:L31),0) -> 6.1024627 | O31: =IFERROR(MEDIAN(D31:L31),0) -> 6.6110858
B33: Debtor days | C33: =IFERROR(365/C27,0) -> 3.2442905 | D33: =IFERROR(365/D27,0) -> 4.0271221 | E33: =IFERROR(365/E27,0) -> 3.6689156 | F33: =IFERROR(365/F27,0) -> 4.509312 | G33: =IFERROR(365/G27,0) -> 4.1096761 | H33: =IFERROR(365/H27,0) -> 4.1451155 | I33: =IFERROR(365/I27,0) -> 3.6619655 | J33: =IFERROR(365/J27,0) -> 4.4957118 | ... L33: =IFERROR(365/L27,0) -> 5.1936354 | N33: =IFERROR(AVERAGE(D33:L33),0) -> 4.4858684 | O33: =IFERROR(MEDIAN(D33:L33),0) -> 4.1451155
B34: Payable days | C34: =IFERROR(365/C28,0) -> 1.2813799 | D34: =IFERROR(365/D28,0) -> 1.1358301 | E34: =IFERROR(365/E28,0) -> 5.5755241 | F34: =IFERROR(365/F28,0) -> 4.0324891 | G34: =IFERROR(365/G28,0) -> 6.5979652 | H34: =IFERROR(365/H28,0) -> 5.8436429 | I34: =IFERROR(365/I28,0) -> 5.1625144 | J34: =IFERROR(365/J28,0) -> 5.1551208 | ... L34: =IFERROR(365/L28,0) -> 7.0015634 | N34: =IFERROR(AVERAGE(D34:L34),0) -> 6.8430214 | O34: =IFERROR(MEDIAN(D34:L34),0) -> 5.5755241
B35: Inventory days | C35: =IFERROR(365/C29,0) -> 32.908563 | D35: =IFERROR(365/D29,0) -> 31.209469 | E35: =IFERROR(365/E29,0) -> 37.862749 | F35: =IFERROR(365/F29,0) -> 38.727643 | G35: =IFERROR(365/G29,0) -> 39.436498 | H35: =IFERROR(365/H29,0) -> 41.664362 | I35: =IFERROR(365/I29,0) -> 36.80801 | J35: =IFERROR(365/J29,0) -> 31.262599 | ... L35: =IFERROR(365/L29,0) -> 40.500173 | N35: =IFERROR(AVERAGE(D35:L35),0) -> 38.774176 | O35: =IFERROR(MEDIAN(D35:L35),0) -> 38.727643
B36: Cash conversion | C36: =SUM(C33,C35)-C34 -> 34.871473 | D36: =SUM(D33,D35)-D34 -> 34.100761 | E36: =SUM(E33,E35)-E34 -> 35.95614 | F36: =SUM(F33,F35)-F34 -> 39.204466 | G36: =SUM(G33,G35)-G34 -> 36.948209 | H36: =SUM(H33,H35)-H34 -> 39.965834 | I36: =SUM(I33,I35)-I34 -> 35.307461 | J36: =SUM(J33,J35)-J34 -> 30.60319 | ... L36: =SUM(L33,L35)-L34 -> 38.692245 | N36: =IFERROR(AVERAGE(D36:L36),0) -> 36.417023 | O36: =IFERROR(MEDIAN(D36:L36),0) -> 36.948209
B38: CFO/sales | C38: =IFERROR('Historical FS'!C62/'Historical FS'!C6,0) -> 0.18160466 | D38: =IFERROR('Historical FS'!D62/'Historical FS'!D6,0) -> 0.18175708 | E38: =IFERROR('Historical FS'!E62/'Historical FS'!E6,0) -> 0.18556622 | F38: =IFERROR('Historical FS'!F62/'Historical FS'!F6,0) -> 0.18385577 | G38: =IFERROR('Historical FS'!G62/'Historical FS'!G6,0) -> 0.15168999 | H38: =IFERROR('Historical FS'!H62/'Historical FS'!H6,0) -> 0.16200725 | I38: =IFERROR('Historical FS'!I62/'Historical FS'!I6,0) -> 0.17735736 | J38: =IFERROR('Historical FS'!J62/'Historical FS'!J6,0) -> 0.17114081 | ... L38: =IFERROR('Historical FS'!L62/'Historical FS'!L6,0) -> 0.21799383 | N38: =IFERROR(AVERAGE(D38:L38),0) -> 0.1751812 | O38: =IFERROR(MEDIAN(D38:L38),0) -> 0.17735736
B39: CFO/total assets | C39: =IFERROR('Historical FS'!C62/'Historical FS'!C56,0) -> 0.24689545 | D39: =IFERROR('Historical FS'!D62/'Historical FS'!D56,0) -> 0.25376233 | E39: =IFERROR('Historical FS'!E62/'Historical FS'!E56,0) -> 0.31998734 | F39: =IFERROR('Historical FS'!F62/'Historical FS'!F56,0) -> 0.31070429 | G39: =IFERROR('Historical FS'!G62/'Historical FS'!G56,0) -> 0.27155267 | H39: =IFERROR('Historical FS'!H62/'Historical FS'!H56,0) -> 0.30487908 | I39: =IFERROR('Historical FS'!I62/'Historical FS'!I56,0) -> 0.37780245 | J39: =IFERROR('Historical FS'!J62/'Historical FS'!J56,0) -> 0.39672776 | ... L39: =IFERROR('Historical FS'!L62/'Historical FS'!L56,0) -> 0.37789142 | N39: =IFERROR(AVERAGE(D39:L39),0) -> 0.31682495 | O39: =IFERROR(MEDIAN(D39:L39),0) -> 0.31070429
B40: CFO/total debt | C40: =IFERROR('Historical FS'!C62/'Historical FS'!C41,0) -> 51.729937 | D40: =IFERROR('Historical FS'!D62/'Historical FS'!D41,0) -> 58.407797 | E40: =IFERROR('Historical FS'!E62/'Historical FS'!E41,0) -> 12.148036 | F40: =IFERROR('Historical FS'!F62/'Historical FS'!F41,0) -> 16.641671 | G40: =IFERROR('Historical FS'!G62/'Historical FS'!G41,0) -> 8.3915034 | H40: =IFERROR('Historical FS'!H62/'Historical FS'!H41,0) -> 10.119141 | I40: =IFERROR('Historical FS'!I62/'Historical FS'!I41,0) -> 12.539516 | J40: =IFERROR('Historical FS'!J62/'Historical FS'!J41,0) -> 12.117348 | ... L40: =IFERROR('Historical FS'!L62/'Historical FS'!L41,0) -> 11.364283 | N40: =IFERROR(AVERAGE(D40:L40),0) -> 16.027135 | O40: =IFERROR(MEDIAN(D40:L40),0) -> 12.117348

Sheet Data Room>

Sheet Historical FS
B2: ="Historical Financial Statement -"&'Data Sheet'!B1 -> Historical Financial Statement -NESTLE INDIA LTD
B3: Years | C3: ='Data Sheet'!B16 -> 43100 | D3: ='Data Sheet'!C16 -> 43465 | E3: ='Data Sheet'!D16 -> 43830 | F3: ='Data Sheet'!E16 -> 44196 | G3: ='Data Sheet'!F16 -> 44561 | H3: ='Data Sheet'!G16 -> 44926 | I3: ='Data Sheet'!H16 -> 45291 | J3: ='Data Sheet'!I16 -> 45382 | ... L3: ='Data Sheet'!K16 -> 46112
B4: Note: FY2023-24 (period ended Mar-2024, shown above) was a 15-month transition year following Nestlé India's change from a January–December financial year to an April–March financial year. It is therefore not directly comparable with the normal 12-month years shown alongside it for growth and trend analysis.
A5: # | B5: Income Statement
B6: Sales | C6: =IFERROR('Data Sheet'!B17,0) -> 10009.6 | D6: =IFERROR('Data Sheet'!C17,0) -> 11292.27 | E6: =IFERROR('Data Sheet'!D17,0) -> 12368.9 | F6: =IFERROR('Data Sheet'!E17,0) -> 13350.03 | G6: =IFERROR('Data Sheet'!F17,0) -> 14740.59 | H6: =IFERROR('Data Sheet'!G17,0) -> 16896.96 | I6: =IFERROR('Data Sheet'!H17,0) -> 19126.3 | J6: =IFERROR('Data Sheet'!I17,0) -> 24393.89 | ... L6: =IFERROR('Data Sheet'!K17,0) -> 23154.6
B7: Sales Growth Rate | C7: 0 | D7: =(D6/C6-1) -> 0.12814398 | E7: =(E6/D6-1) -> 0.095342212 | F7: =(F6/E6-1) -> 0.079322333 | G7: =(G6/F6-1) -> 0.10416156 | H7: =(H6/G6-1) -> 0.1462879 | I7: =(I6/H6-1) -> 0.13193734 | J7: =(J6/I6-1) -> 0.27541082 | K7: =(K6/J6-1) -> -0.17185984 | L7: =(L6/K6-1) -> 0.14617881
B8: COGS (broad: Raw Material + Power & Fuel + Other Mfr. Exp + Employee Cost − Δ Inventory) | C8: =IFERROR(SUM('Data Sheet'!B20:B22,'Data Sheet'!B18)-1*'Data Sheet'!B19,0) -> 5821.16 | D8: =IFERROR(SUM('Data Sheet'!C20:C22,'Data Sheet'!C18)-1*'Data Sheet'!C19,0) -> 6241.4 | E8: =IFERROR(SUM('Data Sheet'!D20:D22,'Data Sheet'!D18)-1*'Data Sheet'!D19,0) -> 7003.97 | F8: =IFERROR(SUM('Data Sheet'!E20:E22,'Data Sheet'!E18)-1*'Data Sheet'!E19,0) -> 7687.4 | G8: =IFERROR(SUM('Data Sheet'!F20:F22,'Data Sheet'!F18)-1*'Data Sheet'!F19,0) -> 8521.15 | H8: =IFERROR(SUM('Data Sheet'!G20:G22,'Data Sheet'!G18)-1*'Data Sheet'!G19,0) -> 10221.7 | I8: =IFERROR(SUM('Data Sheet'!H20:H22,'Data Sheet'!H18)-1*'Data Sheet'!H19,0) -> 10281.89 | J8: =IFERROR(SUM('Data Sheet'!I20:I22,'Data Sheet'!I18)-1*'Data Sheet'!I19,0) -> 14101.72 | ... L8: =IFERROR(SUM('Data Sheet'!K20:K22,'Data Sheet'!K18)-1*'Data Sheet'!K19,0) -> 13627.64
B9: COGS % of Sales (broad definition — see note below) | C9: =(C8/C6) -> 0.5815577 | D9: =(D8/D6) -> 0.55271438 | E9: =(E8/E6) -> 0.5662565 | F9: =(F8/F6) -> 0.57583391 | G9: =(G8/G6) -> 0.57807388 | H9: =(H8/H6) -> 0.60494314 | I9: =(I8/I6) -> 0.53757862 | J9: =(J8/J6) -> 0.5780841 | ... L9: =(L8/L6) -> 0.58855001
B10: Gross Profits | C10: =(C6-C8) -> 4188.44 | D10: =(D6-D8) -> 5050.87 | E10: =(E6-E8) -> 5364.93 | F10: =(F6-F8) -> 5662.63 | G10: =(G6-G8) -> 6219.44 | H10: =(H6-H8) -> 6675.26 | I10: =(I6-I8) -> 8844.41 | J10: =(J6-J8) -> 10292.17 | ... L10: =(L6-L8) -> 9526.96
B11: Gross Profits% of Sales | C11: =C10/C6 -> 0.4184423 | D11: =D10/D6 -> 0.44728562 | E11: =E10/E6 -> 0.4337435 | F11: =F10/F6 -> 0.42416609 | G11: =G10/G6 -> 0.42192612 | H11: =H10/H6 -> 0.39505686 | I11: =I10/I6 -> 0.46242138 | J11: =J10/J6 -> 0.4219159 | ... L11: =L10/L6 -> 0.41144999
B12: Selling & Adm Expense | C12: =IFERROR(SUM('Data Sheet'!B23:B24),0) -> 2091.91 | D12: =IFERROR(SUM('Data Sheet'!C23:C24),0) -> 2433.22 | E12: =IFERROR(SUM('Data Sheet'!D23:D24),0) -> 2439.05 | F12: =IFERROR(SUM('Data Sheet'!E23:E24),0) -> 2461.13 | G12: =IFERROR(SUM('Data Sheet'!F23:F24),0) -> 2657.04 | H12: =IFERROR(SUM('Data Sheet'!G23:G24),0) -> 2968.97 | I12: =IFERROR(SUM('Data Sheet'!H23:H24),0) -> 4373.42 | J12: =IFERROR(SUM('Data Sheet'!I23:I24),0) -> 4449.05 | ... L12: =IFERROR(SUM('Data Sheet'!K23:K24),0) -> 4220
B13: S&A Exp % of sales | C13: =C12/C6 -> 0.20899037 | D13: =D12/D6 -> 0.2154766 | E13: =E12/E6 -> 0.19719215 | F13: =F12/F6 -> 0.18435389 | G13: =G12/G6 -> 0.1802533 | H13: =H12/H6 -> 0.17571031 | I13: =I12/I6 -> 0.22866001 | J13: =J12/J6 -> 0.18238379 | ... L13: =L12/L6 -> 0.1822532
B14: EBITDA | C14: =C10-C12 -> 2096.53 | D14: =D10-D12 -> 2617.65 | E14: =E10-E12 -> 2925.88 | F14: =F10-F12 -> 3201.5 | G14: =G10-G12 -> 3562.4 | H14: =H10-H12 -> 3706.29 | I14: =I10-I12 -> 4470.99 | J14: =J10-J12 -> 5843.12 | ... L14: =L10-L12 -> 5306.96
B15: EBITDA% of Sales | C15: =C14/C6 -> 0.20945193 | D15: =D14/D6 -> 0.23180902 | E15: =E14/E6 -> 0.23655135 | F15: =F14/F6 -> 0.2398122 | G15: =G14/G6 -> 0.24167282 | H15: =H14/H6 -> 0.21934656 | I15: =I14/I6 -> 0.23376137 | J15: =J14/J6 -> 0.23953211 | ... L15: =L14/L6 -> 0.22919679
B16: Other Income | C16: =IFERROR('Data Sheet'!B25,0) -> 176.92 | D16: =IFERROR('Data Sheet'!C25,0) -> 258.92 | E16: =IFERROR('Data Sheet'!D25,0) -> 246.88 | F16: =IFERROR('Data Sheet'!E25,0) -> 145.85 | G16: =IFERROR('Data Sheet'!F25,0) -> -112.38 | H16: =IFERROR('Data Sheet'!G25,0) -> 107.26 | I16: =IFERROR('Data Sheet'!H25,0) -> 115.5 | J16: =IFERROR('Data Sheet'!I25,0) -> 158.99 | ... L16: =IFERROR('Data Sheet'!K25,0) -> 160.23
B17: % of Sales | C17: =C16/C6 -> 0.017675032 | D17: =D16/D6 -> 0.022928959 | E17: =E16/E6 -> 0.019959738 | F17: =F16/F6 -> 0.010925069 | G17: =G16/G6 -> -0.0076238468 | H17: =H16/H6 -> 0.0063478874 | I17: =I16/I6 -> 0.0060388052 | J17: =J16/J6 -> 0.0065176157 | ... L17: =L16/L6 -> 0.0069200073
B18: Depreciation | C18: =IFERROR('Data Sheet'!B26,0) -> 342.25 | D18: =IFERROR('Data Sheet'!C26,0) -> 335.67 | E18: =IFERROR('Data Sheet'!D26,0) -> 370.15 | F18: =IFERROR('Data Sheet'!E26,0) -> 370.38 | G18: =IFERROR('Data Sheet'!F26,0) -> 391.02 | H18: =IFERROR('Data Sheet'!G26,0) -> 403.01 | I18: =IFERROR('Data Sheet'!H26,0) -> 428.91 | J18: =IFERROR('Data Sheet'!I26,0) -> 567.75 | ... L18: =IFERROR('Data Sheet'!K26,0) -> 699.23
B19: Depreciation% of Sales | C19: =C18/C6 -> 0.034192176 | D19: =D18/D6 -> 0.029725644 | E19: =E18/E6 -> 0.029925862 | F19: =F18/F6 -> 0.027743758 | G19: =G18/G6 -> 0.026526754 | H19: =H18/H6 -> 0.023851036 | I19: =I18/I6 -> 0.022425142 | J19: =J18/J6 -> 0.023274271 | ... L19: =L18/L6 -> 0.030198319
B20: Interest | C20: =IFERROR('Data Sheet'!B27,0) -> 91.9 | D20: =IFERROR('Data Sheet'!C27,0) -> 111.95 | E20: =IFERROR('Data Sheet'!D27,0) -> 129.12 | F20: =IFERROR('Data Sheet'!E27,0) -> 164.18 | G20: =IFERROR('Data Sheet'!F27,0) -> 201.68 | H20: =IFERROR('Data Sheet'!G27,0) -> 154.57 | I20: =IFERROR('Data Sheet'!H27,0) -> 119.29 | J20: =IFERROR('Data Sheet'!I27,0) -> 145.49 | ... L20: =IFERROR('Data Sheet'!K27,0) -> 158.31
B21: Interest% of Sales | C21: =C20/C6 -> 0.0091811861 | D21: =D20/D6 -> 0.0099138614 | E21: =E20/E6 -> 0.010439085 | F21: =F20/F6 -> 0.0122981 | G21: =G20/G6 -> 0.013681949 | H21: =H20/H6 -> 0.0091477994 | I21: =I20/I6 -> 0.0062369617 | J21: =J20/J6 -> 0.0059641984 | ... L21: =L20/L6 -> 0.0068370864
B22: EBT | C22: =C14+C16-(C18+C20) -> 1839.3 | D22: =D14+D16-(D18+D20) -> 2428.95 | E22: =E14+E16-(E18+E20) -> 2673.49 | F22: =F14+F16-(F18+F20) -> 2812.79 | G22: =G14+G16-(G18+G20) -> 2857.32 | H22: =H14+H16-(H18+H20) -> 3255.97 | I22: =I14+I16-(I18+I20) -> 4038.29 | J22: =J14+J16-(J18+J20) -> 5288.87 | ... L22: =L14+L16-(L18+L20) -> 4609.65
B23: EBT% of Sales | C23: =C22/C6 -> 0.1837536 | D23: =D22/D6 -> 0.21509847 | E23: =E22/E6 -> 0.21614614 | F23: =F22/F6 -> 0.21069541 | G23: =G22/G6 -> 0.19384027 | H23: =H22/H6 -> 0.19269561 | I23: =I22/I6 -> 0.21113807 | J23: =J22/J6 -> 0.21681126 | ... L23: =L22/L6 -> 0.19908139
B24: Tax | C24: =IFERROR('Data Sheet'!B29,0) -> 614.11 | D24: =IFERROR('Data Sheet'!C29,0) -> 822.02 | E24: =IFERROR('Data Sheet'!D29,0) -> 705.05 | F24: =IFERROR('Data Sheet'!E29,0) -> 730.36 | G24: =IFERROR('Data Sheet'!F29,0) -> 738.91 | H24: =IFERROR('Data Sheet'!G29,0) -> 865.45 | I24: =IFERROR('Data Sheet'!H29,0) -> 1039.62 | J24: =IFERROR('Data Sheet'!I29,0) -> 1356.03 | ... L24: =IFERROR('Data Sheet'!K29,0) -> 1065.05
B25: Effective Tax Rate | C25: =C24/C22 -> 0.33388246 | D25: =D24/D22 -> 0.33842607 | E25: =E24/E22 -> 0.26371896 | F25: =F24/F22 -> 0.25965678 | G25: =G24/G22 -> 0.25860247 | H25: =H24/H22 -> 0.26580405 | I25: =I24/I22 -> 0.25744065 | J25: =J24/J22 -> 0.25639314 | ... L25: =L24/L22 -> 0.23104791
B26: Net Profits | C26: =C22-C24 -> 1225.19 | D26: =D22-D24 -> 1606.93 | E26: =E22-E24 -> 1968.44 | F26: =F22-F24 -> 2082.43 | G26: =G22-G24 -> 2118.41 | H26: =H22-H24 -> 2390.52 | I26: =I22-I24 -> 2998.67 | J26: =J22-J24 -> 3932.84 | ... L26: =L22-L24 -> 3544.6
B27: Net Margins | C27: =C26/C6 -> 0.12240149 | D27: =D26/D6 -> 0.14230354 | E27: =E26/E6 -> 0.15914431 | F27: =F26/F6 -> 0.15598692 | G27: =G26/G6 -> 0.1437127 | H27: =H26/H6 -> 0.14147634 | I27: =I26/I6 -> 0.15678255 | J27: =J26/J6 -> 0.16122234 | ... L27: =L26/L6 -> 0.15308405
B29: No. of Equity Shares | C29: =IFERROR('Data Sheet'!B93,0) -> 192.8 | D29: =IFERROR('Data Sheet'!C93,0) -> 192.8 | E29: =IFERROR('Data Sheet'!D93,0) -> 192.8 | F29: =IFERROR('Data Sheet'!E93,0) -> 192.8 | G29: =IFERROR('Data Sheet'!F93,0) -> 192.8 | H29: =IFERROR('Data Sheet'!G93,0) -> 192.8 | I29: =IFERROR('Data Sheet'!H93,0) -> 192.8 | J29: =IFERROR('Data Sheet'!I93,0) -> 192.83 | ... L29: =IFERROR('Data Sheet'!K93,0) -> 192.83
B31: Earning Per Share | C31: =C26/C29 -> 6.3547199 | D31: =D26/D29 -> 8.3346992 | E31: =E26/E29 -> 10.209751 | F31: =F26/F29 -> 10.800985 | G31: =G26/G29 -> 10.987604 | H31: =H26/H29 -> 12.398963 | I31: =I26/I29 -> 15.553268 | J31: =J26/J29 -> 20.395374 | ... L31: =L26/L29 -> 18.381995
B32: EPS Growth rate | D32: =IFERROR(C31/D31,0) -> 0.76244143 | E32: =IFERROR(D31/E31,0) -> 0.81634695 | F32: =IFERROR(E31/F31,0) -> 0.94526107 | G32: =IFERROR(F31/G31,0) -> 0.98301556 | H32: =IFERROR(G31/H31,0) -> 0.88617121 | I32: =IFERROR(H31/I31,0) -> 0.79719342 | J32: =IFERROR(I31/J31,0) -> 0.762588 | K32: =IFERROR(J31/K31,0) -> 1.186556 | L32: =IFERROR(K31/L31,0) -> 0.93508435
B33: Dividend Per Share | C33: =IFERROR('Data Sheet'!B31/'Historical FS'!C29,0) -> 4.3008817 | D33: =IFERROR('Data Sheet'!C31/'Historical FS'!D29,0) -> 5.7511929 | E33: =IFERROR('Data Sheet'!D31/'Historical FS'!E29,0) -> 17.103527 | F33: =IFERROR('Data Sheet'!E31/'Historical FS'!F29,0) -> 10.002075 | G33: =IFERROR('Data Sheet'!F31/'Historical FS'!G29,0) -> 10.002075 | H33: =IFERROR('Data Sheet'!G31/'Historical FS'!H29,0) -> 11.002282 | I33: =IFERROR('Data Sheet'!H31/'Historical FS'!I29,0) -> 8.7018154 | J33: =IFERROR('Data Sheet'!I31/'Historical FS'!J29,0) -> 16.100814 | ... L33: =IFERROR('Data Sheet'!K31/'Historical FS'!L29,0) -> 12
B34: Dividend Payout Ratio | C34: =IFERROR(C33/C31,0) -> 0.67680115 | D34: =IFERROR(D33/D31,0) -> 0.69003006 | E34: =IFERROR(E33/E31,0) -> 1.6752149 | F34: =IFERROR(F33/F31,0) -> 0.92603353 | G34: =IFERROR(G33/G31,0) -> 0.91030537 | H34: =IFERROR(H33/H31,0) -> 0.88735505 | I34: =IFERROR(I33/I31,0) -> 0.5594847 | J34: =IFERROR(J33/J31,0) -> 0.78943461 | ... L34: =IFERROR(L33/L31,0) -> 0.65281273
B35: Retained Earning | C35: =IFERROR(IF(C31>C33,1-C34,0),0) -> 0.32319885 | D35: =IFERROR(IF(D31>D33,1-D34,0),0) -> 0.30996994 | E35: =IFERROR(IF(E31>E33,1-E34,0),0) -> 0 | F35: =IFERROR(IF(F31>F33,1-F34,0),0) -> 0.073966472 | G35: =IFERROR(IF(G31>G33,1-G34,0),0) -> 0.089694629 | H35: =IFERROR(IF(H31>H33,1-H34,0),0) -> 0.11264495 | I35: =IFERROR(IF(I31>I33,1-I34,0),0) -> 0.4405153 | J35: =IFERROR(IF(J31>J33,1-J34,0),0) -> 0.21056539 | ... L35: =IFERROR(IF(L31>L33,1-L34,0),0) -> 0.34718727
A38: # | B38: Balance Sheet
B39: Equity Share Capital | C39: =IFERROR('Data Sheet'!B57,0) -> 96.42 | D39: =IFERROR('Data Sheet'!C57,0) -> 96.42 | E39: =IFERROR('Data Sheet'!D57,0) -> 96.42 | F39: =IFERROR('Data Sheet'!E57,0) -> 96.42 | G39: =IFERROR('Data Sheet'!F57,0) -> 96.42 | H39: =IFERROR('Data Sheet'!G57,0) -> 96.42 | I39: =IFERROR('Data Sheet'!H57,0) -> 96.42 | J39: =IFERROR('Data Sheet'!I57,0) -> 96.42 | ... L39: =IFERROR('Data Sheet'!K57,0) -> 192.83
B40: Reserves | C40: =IFERROR('Data Sheet'!B58,0) -> 3324.17 | D40: =IFERROR('Data Sheet'!C58,0) -> 3577.32 | E40: =IFERROR('Data Sheet'!D58,0) -> 1822.45 | F40: =IFERROR('Data Sheet'!E58,0) -> 1922.92 | G40: =IFERROR('Data Sheet'!F58,0) -> 1849.96 | H40: =IFERROR('Data Sheet'!G58,0) -> 2362.75 | I40: =IFERROR('Data Sheet'!H58,0) -> 2362.75 | J40: =IFERROR('Data Sheet'!I58,0) -> 3244.47 | ... L40: =IFERROR('Data Sheet'!K58,0) -> 5116.41
B41: Borrowings | C41: =IFERROR('Data Sheet'!B59,0) -> 35.14 | D41: =IFERROR('Data Sheet'!C59,0) -> 35.14 | E41: =IFERROR('Data Sheet'!D59,0) -> 188.94 | F41: =IFERROR('Data Sheet'!E59,0) -> 147.49 | G41: =IFERROR('Data Sheet'!F59,0) -> 266.46 | H41: =IFERROR('Data Sheet'!G59,0) -> 270.52 | I41: =IFERROR('Data Sheet'!H59,0) -> 270.52 | J41: =IFERROR('Data Sheet'!I59,0) -> 344.53 | ... L41: =IFERROR('Data Sheet'!K59,0) -> 444.16
B42: Other Liabilities | C42: =IFERROR('Data Sheet'!B60,0) -> 3906.86 | D42: =IFERROR('Data Sheet'!C60,0) -> 4379.2 | E42: =IFERROR('Data Sheet'!D60,0) -> 5065.13 | F42: =IFERROR('Data Sheet'!E60,0) -> 5732.9 | G42: =IFERROR('Data Sheet'!F60,0) -> 6021.29 | H42: =IFERROR('Data Sheet'!G60,0) -> 6249.05 | I42: =IFERROR('Data Sheet'!H60,0) -> 6249.05 | J42: =IFERROR('Data Sheet'!I60,0) -> 6837.64 | ... L42: =IFERROR('Data Sheet'!K60,0) -> 7603.77
B43: Total liablities | C43: =IFERROR('Data Sheet'!B61,0) -> 7362.59 | D43: =IFERROR('Data Sheet'!C61,0) -> 8088.08 | E43: =IFERROR('Data Sheet'!D61,0) -> 7172.94 | F43: =IFERROR('Data Sheet'!E61,0) -> 7899.73 | G43: =IFERROR('Data Sheet'!F61,0) -> 8234.13 | H43: =IFERROR('Data Sheet'!G61,0) -> 8978.74 | I43: =IFERROR('Data Sheet'!H61,0) -> 8978.74 | J43: =IFERROR('Data Sheet'!I61,0) -> 10523.06 | ... L43: =IFERROR('Data Sheet'!K61,0) -> 13357.17
B45: Fixed Assests Net Block | C45: =IFERROR('Data Sheet'!B62,0) -> 2616.18 | D45: =IFERROR('Data Sheet'!C62,0) -> 2400.62 | E45: =IFERROR('Data Sheet'!D62,0) -> 2341.45 | F45: =IFERROR('Data Sheet'!E62,0) -> 2179.41 | G45: =IFERROR('Data Sheet'!F62,0) -> 2994.67 | H45: =IFERROR('Data Sheet'!G62,0) -> 3043.7 | I45: =IFERROR('Data Sheet'!H62,0) -> 3043.7 | J45: =IFERROR('Data Sheet'!I62,0) -> 3460.25 | ... L45: =IFERROR('Data Sheet'!K62,0) -> 6290.42
B46: Capital Work in Progress | C46: =IFERROR('Data Sheet'!B63,0) -> 94.16 | D46: =IFERROR('Data Sheet'!C63,0) -> 105.2 | E46: =IFERROR('Data Sheet'!D63,0) -> 143.3 | F46: =IFERROR('Data Sheet'!E63,0) -> 638.58 | G46: =IFERROR('Data Sheet'!F63,0) -> 246.23 | H46: =IFERROR('Data Sheet'!G63,0) -> 358.36 | I46: =IFERROR('Data Sheet'!H63,0) -> 358.36 | J46: =IFERROR('Data Sheet'!I63,0) -> 1741.71 | ... L46: =IFERROR('Data Sheet'!K63,0) -> 506.98
B47: Investments | C47: =IFERROR('Data Sheet'!B64,0) -> 1978.87 | D47: =IFERROR('Data Sheet'!C64,0) -> 2658.49 | E47: =IFERROR('Data Sheet'!D64,0) -> 1751.05 | F47: =IFERROR('Data Sheet'!E64,0) -> 1463.77 | G47: =IFERROR('Data Sheet'!F64,0) -> 773.98 | H47: =IFERROR('Data Sheet'!G64,0) -> 777.54 | I47: =IFERROR('Data Sheet'!H64,0) -> 777.54 | J47: =IFERROR('Data Sheet'!I64,0) -> 463.87 | ... L47: =IFERROR('Data Sheet'!K64,0) -> 705.6
B48: Other Assets | C48: =IFERROR('Data Sheet'!B65-SUM('Data Sheet'!B67:B69,0),0) -> 224.52 | D48: =IFERROR('Data Sheet'!C65-SUM('Data Sheet'!C67:C69,0),0) -> 223.57 | E48: =IFERROR('Data Sheet'!D65-SUM('Data Sheet'!D67:D69,0),0) -> 221.69 | F48: =IFERROR('Data Sheet'!E65-SUM('Data Sheet'!E67:E69,0),0) -> 266.69 | G48: =IFERROR('Data Sheet'!F65-SUM('Data Sheet'!F67:F69,0),0) -> 1725.22 | H48: =IFERROR('Data Sheet'!G65-SUM('Data Sheet'!G67:G69,0),0) -> 1732.93 | I48: =IFERROR('Data Sheet'!H65-SUM('Data Sheet'!H67:H69,0),0) -> 1732.93 | J48: =IFERROR('Data Sheet'!I65-SUM('Data Sheet'!I67:I69,0),0) -> 1688.56 | ... L48: =IFERROR('Data Sheet'!K65-SUM('Data Sheet'!K67:K69,0),0) -> 1614.61
B49: Total Non Current Assets | C49: =SUM(C45:C48) -> 4913.73 | D49: =SUM(D45:D48) -> 5387.88 | E49: =SUM(E45:E48) -> 4457.49 | F49: =SUM(F45:F48) -> 4548.45 | G49: =SUM(G45:G48) -> 5740.1 | H49: =SUM(H45:H48) -> 5912.53 | I49: =SUM(I45:I48) -> 5912.53 | J49: =SUM(J45:J48) -> 7354.39 | ... L49: =SUM(L45:L48) -> 9117.61
B51: Receivables | C51: =IFERROR('Data Sheet'!B67,0) -> 88.97 | D51: =IFERROR('Data Sheet'!C67,0) -> 124.59 | E51: =IFERROR('Data Sheet'!D67,0) -> 124.33 | F51: =IFERROR('Data Sheet'!E67,0) -> 164.93 | G51: =IFERROR('Data Sheet'!F67,0) -> 165.97 | H51: =IFERROR('Data Sheet'!G67,0) -> 191.89 | I51: =IFERROR('Data Sheet'!H67,0) -> 191.89 | J51: =IFERROR('Data Sheet'!I67,0) -> 300.46 | ... L51: =IFERROR('Data Sheet'!K67,0) -> 329.47
B52: Inventory | C52: =IFERROR('Data Sheet'!B68,0) -> 902.47 | D52: =IFERROR('Data Sheet'!C68,0) -> 965.55 | E52: =IFERROR('Data Sheet'!D68,0) -> 1283.07 | F52: =IFERROR('Data Sheet'!E68,0) -> 1416.48 | G52: =IFERROR('Data Sheet'!F68,0) -> 1592.65 | H52: =IFERROR('Data Sheet'!G68,0) -> 1928.77 | I52: =IFERROR('Data Sheet'!H68,0) -> 1928.77 | J52: =IFERROR('Data Sheet'!I68,0) -> 2089.36 | ... L52: =IFERROR('Data Sheet'!K68,0) -> 2569.22
B53: Cash & Bank | C53: =IFERROR('Data Sheet'!B69,0) -> 1457.42 | D53: =IFERROR('Data Sheet'!C69,0) -> 1610.06 | E53: =IFERROR('Data Sheet'!D69,0) -> 1308.05 | F53: =IFERROR('Data Sheet'!E69,0) -> 1769.87 | G53: =IFERROR('Data Sheet'!F69,0) -> 735.41 | H53: =IFERROR('Data Sheet'!G69,0) -> 945.55 | I53: =IFERROR('Data Sheet'!H69,0) -> 945.55 | J53: =IFERROR('Data Sheet'!I69,0) -> 778.85 | ... L53: =IFERROR('Data Sheet'!K69,0) -> 1340.87
B54: Total Current Assets | C54: =SUM(C51:C53) -> 2448.86 | D54: =SUM(D51:D53) -> 2700.2 | E54: =SUM(E51:E53) -> 2715.45 | F54: =SUM(F51:F53) -> 3351.28 | G54: =SUM(G51:G53) -> 2494.03 | H54: =SUM(H51:H53) -> 3066.21 | I54: =SUM(I51:I53) -> 3066.21 | J54: =SUM(J51:J53) -> 3168.67 | ... L54: =SUM(L51:L53) -> 4239.56
B56: Total Assets | C56: =SUM(C49,C54) -> 7362.59 | D56: =SUM(D49,D54) -> 8088.08 | E56: =SUM(E49,E54) -> 7172.94 | F56: =SUM(F49,F54) -> 7899.73 | G56: =SUM(G49,G54) -> 8234.13 | H56: =SUM(H49,H54) -> 8978.74 | I56: =SUM(I49,I54) -> 8978.74 | J56: =SUM(J49,J54) -> 10523.06 | ... L56: =SUM(L49,L54) -> 13357.17
B57: Check | C57: =IF(C56=C43,TRUE(),FALSE()) -> TRUE | D57: =IF(D56=D43,TRUE(),FALSE()) -> TRUE | E57: =IF(E56=E43,TRUE(),FALSE()) -> TRUE | F57: =IF(F56=F43,TRUE(),FALSE()) -> TRUE | G57: =IF(G56=G43,TRUE(),FALSE()) -> TRUE | H57: =IF(H56=H43,TRUE(),FALSE()) -> TRUE | I57: =IF(I56=I43,TRUE(),FALSE()) -> TRUE | J57: =IF(J56=J43,TRUE(),FALSE()) -> TRUE | ... L57: =IF(L56=L43,TRUE(),FALSE()) -> TRUE
A59: # | B59: Cash Flow Statement
B62: Cash from Operating Activity | C62: =IFERROR('Data Sheet'!B82,0) -> 1817.79 | D62: =IFERROR('Data Sheet'!C82,0) -> 2052.45 | E62: =IFERROR('Data Sheet'!D82,0) -> 2295.25 | F62: =IFERROR('Data Sheet'!E82,0) -> 2454.48 | G62: =IFERROR('Data Sheet'!F82,0) -> 2236 | H62: =IFERROR('Data Sheet'!G82,0) -> 2737.43 | I62: =IFERROR('Data Sheet'!H82,0) -> 3392.19 | J62: =IFERROR('Data Sheet'!I82,0) -> 4174.79 | ... L62: =IFERROR('Data Sheet'!K82,0) -> 5047.56
B63: Cash from Investing Activity | C63: =IFERROR('Data Sheet'!B83,0) -> -130.56 | D63: =IFERROR('Data Sheet'!C83,0) -> -52.41 | E63: =IFERROR('Data Sheet'!D83,0) -> 82.99 | F63: =IFERROR('Data Sheet'!E83,0) -> -321.46 | G63: =IFERROR('Data Sheet'!F83,0) -> -1920.33 | H63: =IFERROR('Data Sheet'!G83,0) -> -391.73 | I63: =IFERROR('Data Sheet'!H83,0) -> -926.99 | J63: =IFERROR('Data Sheet'!I83,0) -> -1237.42 | ... L63: =IFERROR('Data Sheet'!K83,0) -> -623.68
B64: Cash from Financing Activity | C64: =IFERROR('Data Sheet'!B84,0) -> -996.62 | D64: =IFERROR('Data Sheet'!C84,0) -> -1317.42 | E64: =IFERROR('Data Sheet'!D84,0) -> -3601.53 | F64: =IFERROR('Data Sheet'!E84,0) -> -1955.89 | G64: =IFERROR('Data Sheet'!F84,0) -> -2019.97 | H64: =IFERROR('Data Sheet'!G84,0) -> -2122.74 | I64: =IFERROR('Data Sheet'!H84,0) -> -2436.47 | J64: =IFERROR('Data Sheet'!I84,0) -> -3134.92 | ... L64: =IFERROR('Data Sheet'!K84,0) -> -3179.49
B66: Net Cash Flow | C66: =IFERROR('Data Sheet'!B85,0) -> 690.61 | D66: =IFERROR('Data Sheet'!C85,0) -> 682.62 | E66: =IFERROR('Data Sheet'!D85,0) -> -1223.29 | F66: =IFERROR('Data Sheet'!E85,0) -> 177.13 | G66: =IFERROR('Data Sheet'!F85,0) -> -1704.3 | H66: =IFERROR('Data Sheet'!G85,0) -> 222.96 | I66: =IFERROR('Data Sheet'!H85,0) -> 28.73 | J66: =IFERROR('Data Sheet'!I85,0) -> -197.55 | ... L66: =IFERROR('Data Sheet'!K85,0) -> 1244.39
B68: Note/ Key Assumptions
B103: Note: The "COGS" line above uses a BROAD definition (includes Power & Fuel, Other Mfr. Exp and Employee Cost) because the annual P&L source does not separately break out a narrow material-only COGS line. This differs from the "COGS / Material Cost" definition used on the Assumptions / Monthly Actuals / Monthly Budget / Rolling Forecast sheets, which is Raw Material Cost only (% of revenue). EBITDA and margin figures on this sheet are unaffected — only the COGS/Gross Profit split line differs. See Assumptions note 7.

Sheet Data Sheet
A1: COMPANY NAME | B1: NESTLE INDIA LTD | E1: =IF(B2<>B3, "A NEW VERSION OF THE WORKSHEET IS AVAILABLE", "")
A2: LATEST VERSION | B2: 2.1 | E2: PLEASE DO NOT MAKE ANY CHANGES TO THIS SHEET
A3: CURRENT VERSION | B3: 2.1
A5: META
A6: Number of shares | B6: =IF(B9>0, B9/B8, 0) -> 192.83141
A7: Face Value | B7: 1
A8: Current Price | B8: 1385.35
A9: Market Capitalization | B9: 267138.99
A15: PROFIT & LOSS
A16: Report Date | B16: 43100 | C16: 43465 | D16: 43830 | E16: 44196 | F16: 44561 | G16: 44926 | H16: 45291 | I16: 45382 | J16: 45747 | K16: 46112
A17: Sales | B17: 10009.6 | C17: 11292.27 | D17: 12368.9 | E17: 13350.03 | F17: 14740.59 | G17: 16896.96 | H17: 19126.3 | I17: 24393.89 | J17: 20201.56 | K17: 23154.6
A18: Raw Material Cost | B18: 3696.99 | C18: 3829.22 | D18: 4520.91 | E18: 4901.74 | F18: 5301.26 | G18: 6660.42 | H18: 8472.72 | I18: 9201.11 | J18: 7646.63 | K18: 9113.96
A19: Change in Inventory | B19: 79.56 | C19: 6.01 | D19: 144.19 | E19: 69.33 | F19: 67.59 | G19: 250.27 | H19: 40.01 | I19: 45.68 | J19: 139.66 | K19: 168.23
A20: Power and Fuel | B20: 288.44 | C20: 344.18 | D20: 340.53 | E20: 313.68 | F20: 408.06 | G20: 572.61 | I20: 674.83 | J20: 541.42 | K20: 587.21
A21: Other Mfr. Exp | B21: 897.84 | C21: 949.86 | D21: 1028.55 | E21: 1040.36 | F21: 1349.48 | G21: 1603.48 | I21: 1935.4 | J21: 1582.45 | K21: 1816.29
A22: Employee Cost | B22: 1017.45 | C22: 1124.15 | D22: 1258.17 | E22: 1500.95 | F22: 1529.94 | G22: 1635.46 | H22: 1849.18 | I22: 2336.06 | J22: 2062.02 | K22: 2278.41
A23: Selling and admin | B23: 1823.98 | C23: 2145.82 | D23: 2226.13 | E23: 2246.9 | F23: 2902.12 | G23: 3192.15 | I23: 4837.58 | J23: 4126.54 | K23: 4780.9
A24: Other Expenses | B24: 267.93 | C24: 287.4 | D24: 212.92 | E24: 214.23 | F24: -245.08 | G24: -223.18 | H24: 4373.42 | I24: -388.53 | J24: -389.17 | K24: -560.9
A25: Other Income | B25: 176.92 | C25: 258.92 | D25: 246.88 | E25: 145.85 | F25: -112.38 | G25: 107.26 | H25: 115.5 | I25: 158.99 | J25: 352.06 | K25: 160.23
A26: Depreciation | B26: 342.25 | C26: 335.67 | D26: 370.15 | E26: 370.38 | F26: 391.02 | G26: 403.01 | H26: 428.91 | I26: 567.75 | J26: 539.92 | K26: 699.23
A27: Interest | B27: 91.9 | C27: 111.95 | D27: 129.12 | E27: 164.18 | F27: 201.68 | G27: 154.57 | H27: 119.29 | I27: 145.49 | J27: 136 | K27: 158.31
A28: Profit before tax | B28: 1839.3 | C28: 2428.95 | D28: 2673.49 | E28: 2812.79 | F28: 2857.32 | G28: 3255.97 | H28: 4038.29 | I28: 5288.87 | J28: 4447.47 | K28: 4609.65
A29: Tax | B29: 614.11 | C29: 822.02 | D29: 705.05 | E29: 730.36 | F29: 738.91 | G29: 865.45 | H29: 1039.62 | I29: 1356.03 | J29: 1132.97 | K29: 1065.05
A30: Net profit | B30: 1225.19 | C30: 1606.93 | D30: 1968.44 | E30: 2082.43 | F30: 2118.41 | G30: 2390.52 | H30: 2998.67 | I30: 3932.84 | J30: 3314.5 | K30: 3544.6
A31: Dividend Amount | B31: 829.21 | C31: 1108.83 | D31: 3297.56 | E31: 1928.4 | F31: 1928.4 | G31: 2121.24 | H31: 1677.71 | I31: 3104.72 | J31: 2603.34 | K31: 2313.96
A40: Quarters
A41: Report Date | B41: 45382 | C41: 45473 | D41: 45565 | E41: 45657 | F41: 45747 | G41: 45838 | H41: 45930 | I41: 46022 | J41: 46112 | K41: 46203
A42: Sales | B42: 5267.59 | C42: 4813.95 | D42: 5104 | E42: 4779.73 | F42: 5503.88 | G42: 5096.16 | H42: 5643.61 | I42: 5667.04 | J42: 6747.79 | K42: 6378.18
A43: Expenses | B43: 3917.54 | C43: 3699.62 | D43: 3936.27 | E43: 3677.04 | F43: 4115.58 | G43: 3996.03 | H43: 4406.97 | I43: 4466.09 | J43: 4976.19 | K43: 4840.05
A44: Other Income | B44: 36.83 | C44: 39.12 | D44: 297.68 | E44: 4.44 | F44: 9.1 | G44: 4.17 | H44: 1.64 | I44: 169.78 | J44: -17.72 | K44: 16.24
A45: Depreciation | B45: 110.1 | C45: 112.71 | D45: 121.6 | E45: 150.27 | F45: 155.34 | G45: 156.94 | H45: 163.35 | I45: 174.41 | J45: 204.53 | K45: 187.8
A46: Interest | B46: 26.2 | C46: 31.68 | D46: 32.22 | E46: 34.6 | F46: 37.5 | G46: 46.89 | H46: 46.41 | I46: 28.25 | J46: 36.76 | K46: 42.18
A47: Profit before tax | B47: 1250.58 | C47: 1009.06 | D47: 1311.59 | E47: 922.26 | F47: 1204.56 | G47: 900.47 | H47: 1028.52 | I47: 1168.07 | J47: 1512.59 | K47: 1324.39
A48: Tax | B48: 316.41 | C48: 262.46 | D48: 325.23 | E48: 226.13 | F48: 319.15 | G48: 241.24 | H48: 275.32 | I48: 150.01 | J48: 398.48 | K48: 349.27
A49: Net profit | B49: 934.17 | C49: 746.6 | D49: 986.36 | E49: 696.13 | F49: 885.41 | G49: 659.23 | H49: 753.2 | I49: 1018.06 | J49: 1114.11 | K49: 975.12
A50: Operating Profit | B50: 1350.05 | C50: 1114.33 | D50: 1167.73 | E50: 1102.69 | F50: 1388.3 | G50: 1100.13 | H50: 1236.64 | I50: 1200.95 | J50: 1771.6 | K50: 1538.13
A55: BALANCE SHEET
A56: Report Date | B56: 43100 | C56: 43465 | D56: 43830 | E56: 44196 | F56: 44561 | G56: 44926 | H56: 45291 | I56: 45382 | J56: 45747 | K56: 46112
A57: Equity Share Capital | B57: 96.42 | C57: 96.42 | D57: 96.42 | E57: 96.42 | F57: 96.42 | G57: 96.42 | H57: 96.42 | I57: 96.42 | J57: 96.42 | K57: 192.83
A58: Reserves | B58: 3324.17 | C58: 3577.32 | D58: 1822.45 | E58: 1922.92 | F58: 1849.96 | G58: 2362.75 | H58: 2362.75 | I58: 3244.47 | J58: 4020.73 | K58: 5116.41
A59: Borrowings | B59: 35.14 | C59: 35.14 | D59: 188.94 | E59: 147.49 | F59: 266.46 | G59: 270.52 | H59: 270.52 | I59: 344.53 | J59: 1166.85 | K59: 444.16
A60: Other Liabilities | B60: 3906.86 | C60: 4379.2 | D60: 5065.13 | E60: 5732.9 | F60: 6021.29 | G60: 6249.05 | H60: 6249.05 | I60: 6837.64 | J60: 7039.89 | K60: 7603.77
A61: Total | B61: 7362.59 | C61: 8088.08 | D61: 7172.94 | E61: 7899.73 | F61: 8234.13 | G61: 8978.74 | H61: 8978.74 | I61: 10523.06 | J61: 12323.89 | K61: 13357.17
A62: Net Block | B62: 2616.18 | C62: 2400.62 | D62: 2341.45 | E62: 2179.41 | F62: 2994.67 | G62: 3043.7 | H62: 3043.7 | I62: 3460.25 | J62: 5473.61 | K62: 6290.42
A63: Capital Work in Progress | B63: 94.16 | C63: 105.2 | D63: 143.3 | E63: 638.58 | F63: 246.23 | G63: 358.36 | H63: 358.36 | I63: 1741.71 | J63: 1172.56 | K63: 506.98
A64: Investments | B64: 1978.87 | C64: 2658.49 | D64: 1751.05 | E64: 1463.77 | F64: 773.98 | G64: 777.54 | H64: 777.54 | I64: 463.87 | J64: 705.6 | K64: 705.6
A65: Other Assets | B65: 2673.38 | C65: 2923.77 | D65: 2937.14 | E65: 3617.97 | F65: 4219.25 | G65: 4799.14 | H65: 4799.14 | I65: 4857.23 | J65: 4972.12 | K65: 5854.17
A66: Total | B66: 7362.59 | C66: 8088.08 | D66: 7172.94 | E66: 7899.73 | F66: 8234.13 | G66: 8978.74 | H66: 8978.74 | I66: 10523.06 | J66: 12323.89 | K66: 13357.17
A67: Receivables | B67: 88.97 | C67: 124.59 | D67: 124.33 | E67: 164.93 | F67: 165.97 | G67: 191.89 | H67: 191.89 | I67: 300.46 | J67: 363.15 | K67: 329.47
... A69: Cash & Bank | B69: 1457.42 | C69: 1610.06 | D69: 1308.05 | E69: 1769.87 | F69: 735.41 | G69: 945.55 | H69: 945.55 | I69: 778.85 | J69: 95.65 | K69: 1340.87
A70: No. of Equity Shares | B70: 96415716 | C70: 96415716 | D70: 96415716 | E70: 96415716 | F70: 96415716 | G70: 96415716 | I70: 964157160 | J70: 964157160 | K70: 1928314320
A71: New Bonus Shares
A72: Face value | B72: 10 | C72: 10 | D72: 10 | E72: 10 | F72: 10 | G72: 10 | H72: 10 | I72: 1 | J72: 1 | K72: 1
A80: CASH FLOW:
A81: Report Date | B81: 43100 | C81: 43465 | D81: 43830 | E81: 44196 | F81: 44561 | G81: 44926 | H81: 45291 | I81: 45382 | J81: 45747 | K81: 46112
A82: Cash from Operating Activity | B82: 1817.79 | C82: 2052.45 | D82: 2295.25 | E82: 2454.48 | F82: 2236 | G82: 2737.43 | H82: 3392.19 | I82: 4174.79 | J82: 2934.53 | K82: 5047.56
A83: Cash from Investing Activity | B83: -130.56 | C83: -52.41 | D83: 82.99 | E83: -321.46 | F83: -1920.33 | G83: -391.73 | H83: -926.99 | I83: -1237.42 | J83: -1810.9 | K83: -623.68
A84: Cash from Financing Activity | B84: -996.62 | C84: -1317.42 | D84: -3601.53 | E84: -1955.89 | F84: -2019.97 | G84: -2122.74 | H84: -2436.47 | I84: -3134.92 | J84: -1846.3 | K84: -3179.49
A85: Net Cash Flow | B85: 690.61 | C85: 682.62 | D85: -1223.29 | E85: 177.13 | F85: -1704.3 | G85: 222.96 | H85: 28.73 | I85: -197.55 | J85: -722.67 | K85: 1244.39
A90: PRICE: | B90: 393.55 | C90: 554.24 | D90: 739.27 | E90: 919.51 | F90: 985.29 | G90: 980.3 | H90: 1329.02 | I90: 1311.18 | J90: 1125.38 | K90: 1174.8
A92: DERIVED:
A93: Adjusted Equity Shares in Cr | B93: 192.8 | C93: 192.8 | D93: 192.8 | E93: 192.8 | F93: 192.8 | G93: 192.8 | H93: 192.8 | I93: 192.83 | J93: 192.83 | K93: 192.83
